Workbook

Sheet NMCD_Entidad
A1: Evaluador | B1: Fecha Evaluación | C1: Aplicación | D1: Fuente | E1: Origen | F1: ID_Entidad | G1: Entidad | H1: Total Registros | I1: # Registros Inconsistencias Detectadas | J1: # Registros Cumplen Unicidad | K1: # Registros Cumplen Completitud | L1: # Registros Cumplen Validez | M1: # Registros No Cumplen Unicidad | N1: # Registros No Cumplen Completitud | O1: # Registros No Cumplen Validez | P1: % Unicidad Nivel Madurez | Q1: % Completitud Nivel Madurez | R1: % Validez Nivel Madurez | S1: % Nivel Madurez Calidad Datos | T1: % Inconsistencias Detectadas
A2: Daniel Giraldo | B2: 46182 | C2: CRM | D2: CRM Afiliados | E2: 192.6.1.152 | F2: OGD-TAB-0001 | G2: Afiliados | H2: 200 | I2: =SUM(Afiliados!D2:D201) -> 34 | J2: =SUM(Afiliados!A2:A201) -> 200 | K2: =SUM(Afiliados!B2:B201) -> 195 | L2: =SUM(Afiliados!C2:C201) -> 166 | M2: =H2-J2 -> 0 | N2: =$H2-K2 -> 5 | O2: =$H2-L2 -> 34 | P2: =AVERAGE(NMCD_DetalleCampos!Q2:Q19) -> 1 | Q2: =AVERAGE(NMCD_DetalleCampos!R2:R19) -> 0.99852941 | R2: =AVERAGE(NMCD_DetalleCampos!S2:S19) -> 0.99 | S2: =AVERAGE(P2:R2) -> 0.99617647 | T2: =I2/H2 -> 0.17

Sheet NMCD_DetalleCampos
A1: Fecha Evaluación | B1: ID_Entidad | C1: Entidad | D1: Total Registros | E1: ID Regla | F1: ID Dato | G1: Campo | H1: Aplica Unicidad | I1: Aplica Completitud | J1: Aplica Validez | K1: # Registros Cumplen Unicidad | L1: # Registros Cumplen Completitud | M1: # Registros Cumplen Validez | N1: # Registros No Cumplen Unicidad | O1: # Registros No Cumplen Completitud | P1: # Registros No Cumplen Validez | Q1: % Unicidad Nivel Madurez | R1: % Completitud Nivel Madurez | S1: % Validez Nivel Madurez | T1: Regla Unicidad | U1: Regla Completitud | V1: Regla Validez (Old) | W1: Regla Validez | X1: Observaciones | Y1: Criticidad
A2: 46182 | B2: OGD-TAB-0001 | C2: Afiliados | D2: 200 | E2: RCD001 | F2: SGD0001 | G2: Id_Afiliado | H2: SI | I2: SI | J2: SI | K2: =IF(H2="NO","",SUM(Afiliados!W2:W201)) -> 200 | L2: =SUM(Afiliados!Y2:Y201) -> 200 | M2: =SUM(Afiliados!AP2:AP201) -> 200 | N2: =IF(K2>0,$D2-K2,"") -> 0 | O2: =IF(L2>0,$D2-L2,"") -> 0 | P2: =IF(M2>0,$D2-M2,"") -> 0 | Q2: =IF(K2>0,K2/$D2,"") -> 1 | R2: =IF(L2>0,L2/$D2,"") -> 1 | S2: =IF(M2>0,M2/$D2,"") -> 1 | T2: Debe ser único | U2: No debe haber nulos o vacios | W2: Debe seguir el patrón AF####.
A3: 46182 | B3: OGD-TAB-0001 | C3: Afiliados | D3: 200 | E3: RCD002 | F3: SGD0002 | G3: Tipo_Documento | H3: NO | I3: SI | J3: SI | L3: =SUM(Afiliados!Z2:Z201) -> 200 | M3: =SUM(Afiliados!AQ2:AQ201) -> 200 | O3: =IF(L3>0,$D3-L3,"") -> 0 | P3: =IF(M3>0,$D3-M3,"") -> 0 | R3: =IF(L3>0,L3/$D3,"") -> 1 | S3: =IF(M3>0,M3/$D3,"") -> 1 | U3: No debe haber nulos o vacios | W3: Solo se permiten valores CC, CE, TI o PAS.
A4: 46182 | B4: OGD-TAB-0001 | C4: Afiliados | D4: 200 | E4: RCD003 | F4: SGD0003 | G4: Numero_Documento | H4: SI | I4: SI | J4: SI | K4: =IF(H4="NO","",SUM(Afiliados!X2:X201)) -> 200 | L4: =SUM(Afiliados!Y2:Y203) -> 200 | M4: =SUM(Afiliados!AR2:AR201) -> 200 | N4: =IF(K4>0,$D4-K4,"") -> 0 | O4: =IF(L4>0,$D4-L4,"") -> 0 | P4: =IF(M4>0,$D4-M4,"") -> 0 | Q4: =IF(K4>0,K4/$D4,"") -> 1 | R4: =IF(L4>0,L4/$D4,"") -> 1 | S4: =IF(M4>0,M4/$D4,"") -> 1 | T4: Debe ser único | U4: No debe haber nulos o vacios | W4: Debe contener únicamente números válidos.
A5: 46182 | B5: OGD-TAB-0001 | C5: Afiliados | D5: 200 | E5: RCD004 | F5: SGD0004 | G5: Nombre | H5: NO | I5: SI | J5: SI | L5: =SUM(Afiliados!AB2:AB201) -> 197 | M5: =SUM(Afiliados!AS2:AS201) -> 197 | O5: =IF(L5>0,$D5-L5,"") -> 3 | P5: =IF(M5>0,$D5-M5,"") -> 3 | R5: =IF(L5>0,L5/$D5,"") -> 0.985 | S5: =IF(M5>0,M5/$D5,"") -> 0.985 | U5: No debe haber nulos o vacios | W5: No debe contener números ni caracteres especiales.
A6: 46182 | B6: OGD-TAB-0001 | C6: Afiliados | D6: 200 | E6: RCD005 | F6: SGD0005 | G6: Apellido1 | H6: NO | I6: SI | J6: SI | L6: =SUM(Afiliados!AC2:AC201) -> 200 | M6: =SUM(Afiliados!AT2:AT201) -> 200 | O6: =IF(L6>0,$D6-L6,"") -> 0 | P6: =IF(M6>0,$D6-M6,"") -> 0 | R6: =IF(L6>0,L6/$D6,"") -> 1 | S6: =IF(M6>0,M6/$D6,"") -> 1 | U6: No debe haber nulos o vacios | W6: No debe contener números ni caracteres especiales.
A7: 46182 | B7: OGD-TAB-0001 | C7: Afiliados | D7: 200 | E7: RCD006 | F7: SGD0006 | G7: Apellido2 | H7: NO | I7: NO | J7: SI | M7: =SUM(Afiliados!AU2:AU201) -> 200 | O7: =IF(L7>0,$D7-L7,"") | P7: =IF(M7>0,$D7-M7,"") -> 0 | R7: =IF(L7>0,L7/$D7,"") | S7: =IF(M7>0,M7/$D7,"") -> 1 | W7: No debe contener números ni caracteres especiales.
A8: 46182 | B8: OGD-TAB-0001 | C8: Afiliados | D8: 200 | E8: RCD007 | F8: SGD0007 | G8: Genero | H8: NO | I8: SI | J8: SI | L8: =SUM(Afiliados!AD2:AD201) -> 200 | M8: =SUM(Afiliados!AV2:AV201) -> 200 | O8: =IF(L8>0,$D8-L8,"") -> 0 | P8: =IF(M8>0,$D8-M8,"") -> 0 | R8: =IF(L8>0,L8/$D8,"") -> 1 | S8: =IF(M8>0,M8/$D8,"") -> 1 | U8: No debe haber nulos o vacios | W8: Solo se permiten valores M, F u Otro.
A9: 46182 | B9: OGD-TAB-0001 | C9: Afiliados | D9: 200 | E9: RCD008 | F9: SGD0008 | G9: Fecha_Nacimiento | H9: NO | I9: SI | J9: SI | L9: =SUM(Afiliados!AE2:AE201) -> 200 | M9: =SUM(Afiliados!AW2:AW201) -> 200 | O9: =IF(L9>0,$D9-L9,"") -> 0 | P9: =IF(M9>0,$D9-M9,"") -> 0 | R9: =IF(L9>0,L9/$D9,"") -> 1 | S9: =IF(M9>0,M9/$D9,"") -> 1 | U9: No debe haber nulos o vacios | W9: Debe ser una fecha válida y no futura.
A10: 46182 | B10: OGD-TAB-0001 | C10: Afiliados | D10: 200 | E10: RCD009 | F10: SGD0009 | G10: Correo_Electronico | H10: NO | I10: SI | J10: SI | L10: =SUM(Afiliados!AF2:AF201) -> 200 | M10: =SUM(Afiliados!AX2:AX201) -> 197 | O10: =IF(L10>0,$D10-L10,"") -> 0 | P10: =IF(M10>0,$D10-M10,"") -> 3 | R10: =IF(L10>0,L10/$D10,"") -> 1 | S10: =IF(M10>0,M10/$D10,"") -> 0.985 | U10: No debe haber nulos o vacios | W10: Debe cumplir el formato estándar de correo electrónico.
A11: 46182 | B11: OGD-TAB-0001 | C11: Afiliados | D11: 200 | E11: RCD010 | F11: SGD0010 | G11: Telefono | H11: NO | I11: SI | J11: SI | L11: =SUM(Afiliados!AG2:AG201) -> 200 | M11: =SUM(Afiliados!AY2:AY201) -> 198 | O11: =IF(L11>0,$D11-L11,"") -> 0 | P11: =IF(M11>0,$D11-M11,"") -> 2 | R11: =IF(L11>0,L11/$D11,"") -> 1 | S11: =IF(M11>0,M11/$D11,"") -> 0.99 | U11: No debe haber nulos o vacios | W11: Debe contener 10 dígitos válidos para Colombia.
A12: 46182 | B12: OGD-TAB-0001 | C12: Afiliados | D12: 200 | E12: RCD011 | F12: SGD0011 | G12: Direccion | H12: NO | I12: SI | J12: SI | L12: =SUM(Afiliados!AH2:AH201) -> 200 | M12: =SUM(Afiliados!AZ2:AZ201) -> 200 | O12: =IF(L12>0,$D12-L12,"") -> 0 | P12: =IF(M12>0,$D12-M12,"") -> 0 | R12: =IF(L12>0,L12/$D12,"") -> 1 | S12: =IF(M12>0,M12/$D12,"") -> 1 | U12: No debe haber nulos o vacios | W12: Debe tener una estructura de dirección válida.
A13: 46182 | B13: OGD-TAB-0001 | C13: Afiliados | D13: 200 | E13: RCD012 | F13: SGD0012 | G13: Ciudad | H13: NO | I13: SI | J13: SI | L13: =SUM(Afiliados!AI2:AI201) -> 200 | M13: =SUM(Afiliados!BA2:BA201) -> 200 | O13: =IF(L13>0,$D13-L13,"") -> 0 | P13: =IF(M13>0,$D13-M13,"") -> 0 | R13: =IF(L13>0,L13/$D13,"") -> 1 | S13: =IF(M13>0,M13/$D13,"") -> 1 | U13: No debe haber nulos o vacios | W13: Debe existir en el catálogo oficial de ciudades.
A14: 46182 | B14: OGD-TAB-0001 | C14: Afiliados | D14: 200 | E14: RCD013 | F14: SGD0013 | G14: Departamento | H14: NO | I14: SI | J14: SI | L14: =SUM(Afiliados!AJ2:AJ201) -> 200 | M14: =SUM(Afiliados!BB2:BB201) -> 200 | O14: =IF(L14>0,$D14-L14,"") -> 0 | P14: =IF(M14>0,$D14-M14,"") -> 0 | R14: =IF(L14>0,L14/$D14,"") -> 1 | S14: =IF(M14>0,M14/$D14,"") -> 1 | U14: No debe haber nulos o vacios | W14: Debe existir en el catálogo oficial de departamentos.
A15: 46182 | B15: OGD-TAB-0001 | C15: Afiliados | D15: 200 | E15: RCD014 | F15: SGD0014 | G15: Fecha_Afiliacion | H15: NO | I15: SI | J15: SI | L15: =SUM(Afiliados!AK2:AK201) -> 198 | M15: =SUM(Afiliados!BC2:BC201) -> 198 | O15: =IF(L15>0,$D15-L15,"") -> 2 | P15: =IF(M15>0,$D15-M15,"") -> 2 | R15: =IF(L15>0,L15/$D15,"") -> 0.99 | S15: =IF(M15>0,M15/$D15,"") -> 0.99 | U15: No debe haber nulos o vacios | W15: Debe ser una fecha válida, no futura y posterior a la fecha de nacimiento.
A16: 46182 | B16: OGD-TAB-0001 | C16: Afiliados | D16: 200 | E16: RCD015 | F16: SGD0015 | G16: Estado_Afiliacion | H16: NO | I16: SI | J16: SI | L16: =SUM(Afiliados!AL2:AL201) -> 200 | M16: =SUM(Afiliados!BD2:BD201) -> 200 | O16: =IF(L16>0,$D16-L16,"") -> 0 | P16: =IF(M16>0,$D16-M16,"") -> 0 | R16: =IF(L16>0,L16/$D16,"") -> 1 | S16: =IF(M16>0,M16/$D16,"") -> 1 | U16: No debe haber nulos o vacios | W16: Solo se permiten valores Activo, Suspendido o Retirado.
A17: 46182 | B17: OGD-TAB-0001 | C17: Afiliados | D17: 200 | E17: RCD016 | F17: SGD0016 | G17: Canal_Afiliacion | H17: NO | I17: SI | J17: SI | L17: =SUM(Afiliados!AM2:AM201) -> 200 | M17: =SUM(Afiliados!BE2:BE201) -> 200 | O17: =IF(L17>0,$D17-L17,"") -> 0 | P17: =IF(M17>0,$D17-M17,"") -> 0 | R17: =IF(L17>0,L17/$D17,"") -> 1 | S17: =IF(M17>0,M17/$D17,"") -> 1 | U17: No debe haber nulos o vacios | W17: Solo se permiten valores Web, Presencial o Call Center.
A18: 46182 | B18: OGD-TAB-0001 | C18: Afiliados | D18: 200 | E18: RCD017 | F18: SGD0017 | G18: Tarifa_Afiliacion | H18: NO | I18: SI | J18: SI | L18: =SUM(Afiliados!AN2:AN201) -> 200 | M18: =SUM(Afiliados!BF2:BF201) -> 200 | O18: =IF(L18>0,$D18-L18,"") -> 0 | P18: =IF(M18>0,$D18-M18,"") -> 0 | R18: =IF(L18>0,L18/$D18,"") -> 1 | S18: =IF(M18>0,M18/$D18,"") -> 1 | U18: No debe haber nulos o vacios | W18: Debe ser un valor numérico mayor a cero.
A19: 46182 | B19: OGD-TAB-0001 | C19: Afiliados | D19: 200 | E19: RCD018 | F19: SGD0018 | G19: Fecha_Actualizacion | H19: NO | I19: SI | J19: SI | L19: =SUM(Afiliados!AO2:AO201) -> 200 | M19: =SUM(Afiliados!BG2:BG201) -> 174 | O19: =IF(L19>0,$D19-L19,"") -> 0 | P19: =IF(M19>0,$D19-M19,"") -> 26 | R19: =IF(L19>0,L19/$D19,"") -> 1 | S19: =IF(M19>0,M19/$D19,"") -> 0.87 | U19: No debe haber nulos o vacios | W19: Debe ser igual o posterior a la fecha de afiliación.

Sheet Afiliados
A1: Cumple Unicidad (1=Si, 0=No) | B1: Cumple Completitud (1=Si, 0=No) | C1: Cumple Validez (1=Si, 0=No) | D1: Inconsistencia Detectada (1=Si, 0=No) | E1: Id_Afiliado | F1: Tipo_Documento | G1: Numero_Documento | H1: Nombre | I1: Apellido1 | J1: Apellido2 | K1: Genero | L1: Fecha_Nacimiento | M1: Correo_Electronico | N1: Telefono | O1: Direccion | P1: Ciudad | Q1: Departamento | R1: Fecha_Afiliacion | S1: Estado_Afiliacion | T1: Canal_Afiliacion | U1: Tarifa_Afiliacion | V1: Fecha_Actualizacion | W1: =_xlfn.CONCAT("Unicidad ",E1) -> Unicidad Id_Afiliado | X1: =_xlfn.CONCAT("Unicidad ",G1) -> Unicidad Numero_Documento | Y1: =_xlfn.CONCAT("Completitud ",E1) -> Completitud Id_Afiliado | Z1: =_xlfn.CONCAT("Completitud ",F1) -> Completitud Tipo_Documento | AA1: =_xlfn.CONCAT("Completitud ",G1) -> Completitud Numero_Documento | AB1: =_xlfn.CONCAT("Completitud ",H1) -> Completitud Nombre | AC1: =_xlfn.CONCAT("Completitud ",I1) -> Completitud Apellido1 | AD1: =_xlfn.CONCAT("Completitud ",K1) -> Completitud Genero | AE1: =_xlfn.CONCAT("Completitud ",L1) -> Completitud Fecha_Nacimiento | AF1: =_xlfn.CONCAT("Completitud ",M1) -> Completitud Correo_Electronico | AG1: =_xlfn.CONCAT("Completitud ",N1) -> Completitud Telefono | AH1: =_xlfn.CONCAT("Completitud ",O1) -> Completitud Direccion | AI1: =_xlfn.CONCAT("Completitud ",P1) -> Completitud Ciudad | AJ1: =_xlfn.CONCAT("Completitud ",Q1) -> Completitud Departamento | AK1: =_xlfn.CONCAT("Completitud ",R1) -> Completitud Fecha_Afiliacion | ... AO1: =_xlfn.CONCAT("Completitud ",V1) -> Completitud Fecha_Actualizacion | AP1: =_xlfn.CONCAT("Validez ",E1) -> Validez Id_Afiliado | AQ1: =_xlfn.CONCAT("Validez ",F1) -> Validez Tipo_Documento | AR1: =_xlfn.CONCAT("Validez ",G1) -> Validez Numero_Documento | AS1: =_xlfn.CONCAT("Validez ",H1) -> Validez Nombre | AT1: =_xlfn.CONCAT("Validez ",I1) -> Validez Apellido1 | AU1: =_xlfn.CONCAT("Validez ",J1) -> Validez Apellido2 | AV1: =_xlfn.CONCAT("Validez ",K1) -> Validez Genero | AW1: =_xlfn.CONCAT("Validez ",L1) -> Validez Fecha_Nacimiento | ... BG1: =_xlfn.CONCAT("Validez ",V1) -> Validez Fecha_Actualizacion
A2: =IF(AND(W2=1,X2=1),1,0) -> 1 | B2: =IF(AND(Y2=1,Z2=1,AA2=1,AB2=1,AC2=1,AD2=1,AE2=1,AF2=1,AG2=1,AH2=1,AI2=1,AJ2=1,AK2=1,AL2=1,AM2=1,AN2=1,AO2=1),1,0) -> 1 | C2: =IF(AND(AP2=1,AQ2=1,AR2=1,AS2=1,AT2=1,AU2=1,AV2=1,AW2=1,AX2=1,AY2=1,AZ2=1,BA2=1,BB2=1,BC2=1,BD2=1,BE2=1,BF2=1,BG2=1),1,0) -> 1 | D2: =IF(SUM(A2:C2)<3,1,0) -> 0 | E2: AF0001 | F2: CC | G2: 1000000001 | H2: Paula | I2: Herrera | J2: Lopez | K2: F | L2: 31944 | M2: paula.herrera1@email.com | N2: 3425481014 | O2: Calle 1 #94-50 | P2: Barranquilla | Q2: Atlántico | R2: 45566 | S2: Activo | T2: Web | U2: 75000 | V2: 45922 | W2: =IF(COUNTIF(E$2:E$201,E2)>1,0,1) -> 1 | X2: =IF(COUNTIF(G$2:G$201,G2)>1,0,1) -> 1 | Y2: =IF(E2="",0,1) -> 1 | Z2: =IF(F2="",0,1) -> 1 | AA2: =IF(G2="",0,1) -> 1 | AB2: =IF(H2="",0,1) -> 1 | AC2: =IF(I2="",0,1) -> 1 | AD2: =IF(K2="",0,1) -> 1 | AE2: =IF(L2="",0,1) -> 1 | AF2: =IF(M2="",0,1) -> 1 | AG2: =IF(N2="",0,1) -> 1 | AH2: =IF(O2="",0,1) -> 1 | AI2: =IF(P2="",0,1) -> 1 | AJ2: =IF(Q2="",0,1) -> 1 | AK2: =IF(R2="",0,1) -> 1 | ... AO2: =IF(V2="",0,1) -> 1 | AP2: =IF(AND(LEFT(E2,2)="AF",LEN(E2)=6),1,0) -> 1 | AQ2: =IF(OR(F2="CC",F2="CE",F2="TI",F2="PAS"),1,0) -> 1 | AR2: =IF(AND(ISNUMBER(G2),COUNTIF($G:$G,G2)=1),1,0) -> 1 | AS2: {=IF(AND(H2<>"",SUMPRODUCT(--ISNUMBER(FIND({0;1;2;3;4;5;6;7;8;9},H2)))=0),1,0)} -> 1 | AT2: {=IF(AND(I2<>"",SUMPRODUCT(--ISNUMBER(FIND({0;1;2;3;4;5;6;7;8;9},I2)))=0),1,0)} -> 1 | AU2: {=IF(AND(J2<>"",SUMPRODUCT(--ISNUMBER(FIND({0;1;2;3;4;5;6;7;8;9},J2)))=0),1,0)} -> 1 | AV2: =IF(OR(ISBLANK(K2),K2=""),1,IF(ISTEXT(K2),1,0)) -> 1 | AW2: =IF(AND(ISNUMBER(L2),L2<=TODAY()),1,0) -> 1 | AX2: =IF(AND(ISNUMBER(SEARCH("@",M2)),ISNUMBER(SEARCH(".",M2,SEARCH("@",M2)+2)),NOT(ISNUMBER(SEARCH(" ",M2)))),1,0) -> 1 | AY2: =IF(AND(ISNUMBER(N2),LEN(N2)=10),1,0) -> 1 | AZ2: =IF(LEN(TRIM(O2))>=10,1,0) -> 1 | BA2: =IF(OR(ISBLANK(O2),O2=""),1,IF(ISTEXT(O2),1,0)) -> 1 | BB2: =IF(OR(ISBLANK(P2),P2=""),1,IF(ISTEXT(P2),1,0)) -> 1 | BC2: =IF(AND(ISNUMBER(R2),R2<=TODAY()),1,0) -> 1 | BD2: =IF(OR(ISBLANK(S2),S2=""),1,IF(ISTEXT(S2),1,0)) -> 1 | BE2: =IF(OR(ISBLANK(T2),T2=""),1,IF(ISTEXT(T2),1,0)) -> 1 | BF2: =IF(AND(ISNUMBER(U2),U2>0),1,0) -> 1 | BG2: =IF(AND(ISNUMBER(V2),V2<=TODAY()),1,0) -> 1
A3: =IF(AND(W3=1,X3=1),1,0) -> 1 | B3: =IF(AND(Y3=1,Z3=1,AA3=1,AB3=1,AC3=1,AD3=1,AE3=1,AF3=1,AG3=1,AH3=1,AI3=1,AJ3=1,AK3=1,AL3=1,AM3=1,AN3=1,AO3=1),1,0) -> 1 | C3: =IF(AND(AP3=1,AQ3=1,AR3=1,AS3=1,AT3=1,AU3=1,AV3=1,AW3=1,AX3=1,AY3=1,AZ3=1,BA3=1,BB3=1,BC3=1,BD3=1,BE3=1,BF3=1,BG3=1),1,0) -> 1 | D3: =IF(SUM(A3:C3)<3,1,0) -> 0 | E3: AF0002 | F3: TI | G3: 1000000002 | H3: Diana | I3: Martinez | J3: Rodriguez | K3: F | L3: 34253 | M3: diana.martinez2@email.com | N3: 3796270794 | O3: Calle 1 #12-10 | P3: Medellín | Q3: Antioquia | R3: 45506 | S3: Retirado | T3: Presencial | U3: 90000 | V3: 45765 | W3: =IF(COUNTIF(E$2:E$201,E3)>1,0,1) -> 1 | X3: =IF(COUNTIF(G$2:G$201,G3)>1,0,1) -> 1 | Y3: =IF(E3="",0,1) -> 1 | Z3: =IF(F3="",0,1) -> 1 | AA3: =IF(G3="",0,1) -> 1 | AB3: =IF(H3="",0,1) -> 1 | AC3: =IF(I3="",0,1) -> 1 | AD3: =IF(K3="",0,1) -> 1 | AE3: =IF(L3="",0,1) -> 1 | AF3: =IF(M3="",0,1) -> 1 | AG3: =IF(N3="",0,1) -> 1 | AH3: =IF(O3="",0,1) -> 1 | AI3: =IF(P3="",0,1) -> 1 | AJ3: =IF(Q3="",0,1) -> 1 | AK3: =IF(R3="",0,1) -> 1 | ... AO3: =IF(V3="",0,1) -> 1 | AP3: =IF(AND(LEFT(E3,2)="AF",LEN(E3)=6),1,0) -> 1 | AQ3: =IF(OR(F3="CC",F3="CE",F3="TI",F3="PAS"),1,0) -> 1 | AR3: =IF(AND(ISNUMBER(G3),COUNTIF($G:$G,G3)=1),1,0) -> 1 | AS3: {=IF(AND(H3<>"",SUMPRODUCT(--ISNUMBER(FIND({0;1;2;3;4;5;6;7;8;9},H3)))=0),1,0)} -> 1 | AT3: {=IF(AND(I3<>"",SUMPRODUCT(--ISNUMBER(FIND({0;1;2;3;4;5;6;7;8;9},I3)))=0),1,0)} -> 1 | AU3: {=IF(AND(J3<>"",SUMPRODUCT(--ISNUMBER(FIND({0;1;2;3;4;5;6;7;8;9},J3)))=0),1,0)} -> 1 | AV3: =IF(OR(ISBLANK(K3),K3=""),1,IF(ISTEXT(K3),1,0)) -> 1 | AW3: =IF(AND(ISNUMBER(L3),L3<=TODAY()),1,0) -> 1 | AX3: =IF(AND(ISNUMBER(SEARCH("@",M3)),ISNUMBER(SEARCH(".",M3,SEARCH("@",M3)+2)),NOT(ISNUMBER(SEARCH(" ",M3)))),1,0) -> 1 | AY3: =IF(AND(ISNUMBER(N3),LEN(N3)=10),1,0) -> 1 | AZ3: =IF(LEN(TRIM(O3))>=10,1,0) -> 1 | BA3: =IF(OR(ISBLANK(O3),O3=""),1,IF(ISTEXT(O3),1,0)) -> 1 | BB3: =IF(OR(ISBLANK(P3),P3=""),1,IF(ISTEXT(P3),1,0)) -> 1 | BC3: =IF(AND(ISNUMBER(R3),R3<=TODAY()),1,0) -> 1 | BD3: =IF(OR(ISBLANK(S3),S3=""),1,IF(ISTEXT(S3),1,0)) -> 1 | BE3: =IF(OR(ISBLANK(T3),T3=""),1,IF(ISTEXT(T3),1,0)) -> 1 | BF3: =IF(AND(ISNUMBER(U3),U3>0),1,0) -> 1 | BG3: =IF(AND(ISNUMBER(V3),V3<=TODAY()),1,0) -> 1
A4: =IF(AND(W4=1,X4=1),1,0) -> 1 | B4: =IF(AND(Y4=1,Z4=1,AA4=1,AB4=1,AC4=1,AD4=1,AE4=1,AF4=1,AG4=1,AH4=1,AI4=1,AJ4=1,AK4=1,AL4=1,AM4=1,AN4=1,AO4=1),1,0) -> 1 | C4: =IF(AND(AP4=1,AQ4=1,AR4=1,AS4=1,AT4=1,AU4=1,AV4=1,AW4=1,AX4=1,AY4=1,AZ4=1,BA4=1,BB4=1,BC4=1,BD4=1,BE4=1,BF4=1,BG4=1),1,0) -> 1 | D4: =IF(SUM(A4:C4)<3,1,0) -> 0 | E4: AF0003 | F4: CE | G4: 1000000003 | H4: Ana | I4: Perez | J4: Lopez | K4: F | L4: 33163 | M4: ana.perez3@email.com | N4: 3343020752 | O4: Calle 61 #85-33 | P4: Envigado | Q4: Antioquia | R4: 45621 | S4: Retirado | T4: Call Center | U4: 90000 | V4: 45902 | W4: =IF(COUNTIF(E$2:E$201,E4)>1,0,1) -> 1 | X4: =IF(COUNTIF(G$2:G$201,G4)>1,0,1) -> 1 | Y4: =IF(E4="",0,1) -> 1 | Z4: =IF(F4="",0,1) -> 1 | AA4: =IF(G4="",0,1) -> 1 | AB4: =IF(H4="",0,1) -> 1 | AC4: =IF(I4="",0,1) -> 1 | AD4: =IF(K4="",0,1) -> 1 | AE4: =IF(L4="",0,1) -> 1 | AF4: =IF(M4="",0,1) -> 1 | AG4: =IF(N4="",0,1) -> 1 | AH4: =IF(O4="",0,1) -> 1 | AI4: =IF(P4="",0,1) -> 1 | AJ4: =IF(Q4="",0,1) -> 1 | AK4: =IF(R4="",0,1) -> 1 | ... AO4: =IF(V4="",0,1) -> 1 | AP4: =IF(AND(LEFT(E4,2)="AF",LEN(E4)=6),1,0) -> 1 | AQ4: =IF(OR(F4="CC",F4="CE",F4="TI",F4="PAS"),1,0) -> 1 | AR4: =IF(AND(ISNUMBER(G4),COUNTIF($G:$G,G4)=1),1,0) -> 1 | AS4: {=IF(AND(H4<>"",SUMPRODUCT(--ISNUMBER(FIND({0;1;2;3;4;5;6;7;8;9},H4)))=0),1,0)} -> 1 | AT4: {=IF(AND(I4<>"",SUMPRODUCT(--ISNUMBER(FIND({0;1;2;3;4;5;6;7;8;9},I4)))=0),1,0)} -> 1 | AU4: {=IF(AND(J4<>"",SUMPRODUCT(--ISNUMBER(FIND({0;1;2;3;4;5;6;7;8;9},J4)))=0),1,0)} -> 1 | AV4: =IF(OR(ISBLANK(K4),K4=""),1,IF(ISTEXT(K4),1,0)) -> 1 | AW4: =IF(AND(ISNUMBER(L4),L4<=TODAY()),1,0) -> 1 | AX4: =IF(AND(ISNUMBER(SEARCH("@",M4)),ISNUMBER(SEARCH(".",M4,SEARCH("@",M4)+2)),NOT(ISNUMBER(SEARCH(" ",M4)))),1,0) -> 1 | AY4: =IF(AND(ISNUMBER(N4),LEN(N4)=10),1,0) -> 1 | AZ4: =IF(LEN(TRIM(O4))>=10,1,0) -> 1 | BA4: =IF(OR(ISBLANK(O4),O4=""),1,IF(ISTEXT(O4),1,0)) -> 1 | BB4: =IF(OR(ISBLANK(P4),P4=""),1,IF(ISTEXT(P4),1,0)) -> 1 | BC4: =IF(AND(ISNUMBER(R4),R4<=TODAY()),1,0) -> 1 | BD4: =IF(OR(ISBLANK(S4),S4=""),1,IF(ISTEXT(S4),1,0)) -> 1 | BE4: =IF(OR(ISBLANK(T4),T4=""),1,IF(ISTEXT(T4),1,0)) -> 1 | BF4: =IF(AND(ISNUMBER(U4),U4>0),1,0) -> 1 | BG4: =IF(AND(ISNUMBER(V4),V4<=TODAY()),1,0) -> 1
A5: =IF(AND(W5=1,X5=1),1,0) -> 1 | B5: =IF(AND(Y5=1,Z5=1,AA5=1,AB5=1,AC5=1,AD5=1,AE5=1,AF5=1,AG5=1,AH5=1,AI5=1,AJ5=1,AK5=1,AL5=1,AM5=1,AN5=1,AO5=1),1,0) -> 1 | C5: =IF(AND(AP5=1,AQ5=1,AR5=1,AS5=1,AT5=1,AU5=1,AV5=1,AW5=1,AX5=1,AY5=1,AZ5=1,BA5=1,BB5=1,BC5=1,BD5=1,BE5=1,BF5=1,BG5=1),1,0) -> 0 | D5: =IF(SUM(A5:C5)<3,1,0) -> 1 | E5: AF0004 | F5: TI | G5: 1000000004 | H5: Paula | I5: Valencia | J5: Ortiz | K5: F | L5: 35534 | M5: paula.valencia4@email.com | N5: 3806512580 | O5: Calle 43 #16-40 | P5: Manizales | Q5: Caldas | R5: 46105 | S5: Suspendido | T5: Presencial | U5: 85000 | V5: 46447 | W5: =IF(COUNTIF(E$2:E$201,E5)>1,0,1) -> 1 | X5: =IF(COUNTIF(G$2:G$201,G5)>1,0,1) -> 1 | Y5: =IF(E5="",0,1) -> 1 | Z5: =IF(F5="",0,1) -> 1 | AA5: =IF(G5="",0,1) -> 1 | AB5: =IF(H5="",0,1) -> 1 | AC5: =IF(I5="",0,1) -> 1 | AD5: =IF(K5="",0,1) -> 1 | AE5: =IF(L5="",0,1) -> 1 | AF5: =IF(M5="",0,1) -> 1 | AG5: =IF(N5="",0,1) -> 1 | AH5: =IF(O5="",0,1) -> 1 | AI5: =IF(P5="",0,1) -> 1 | AJ5: =IF(Q5="",0,1) -> 1 | AK5: =IF(R5="",0,1) -> 1 | ... AO5: =IF(V5="",0,1) -> 1 | AP5: =IF(AND(LEFT(E5,2)="AF",LEN(E5)=6),1,0) -> 1 | AQ5: =IF(OR(F5="CC",F5="CE",F5="TI",F5="PAS"),1,0) -> 1 | AR5: =IF(AND(ISNUMBER(G5),COUNTIF($G:$G,G5)=1),1,0) -> 1 | AS5: {=IF(AND(H5<>"",SUMPRODUCT(--ISNUMBER(FIND({0;1;2;3;4;5;6;7;8;9},H5)))=0),1,0)} -> 1 | AT5: {=IF(AND(I5<>"",SUMPRODUCT(--ISNUMBER(FIND({0;1;2;3;4;5;6;7;8;9},I5)))=0),1,0)} -> 1 | AU5: {=IF(AND(J5<>"",SUMPRODUCT(--ISNUMBER(FIND({0;1;2;3;4;5;6;7;8;9},J5)))=0),1,0)} -> 1 | AV5: =IF(OR(ISBLANK(K5),K5=""),1,IF(ISTEXT(K5),1,0)) -> 1 | AW5: =IF(AND(ISNUMBER(L5),L5<=TODAY()),1,0) -> 1 | AX5: =IF(AND(ISNUMBER(SEARCH("@",M5)),ISNUMBER(SEARCH(".",M5,SEARCH("@",M5)+2)),NOT(ISNUMBER(SEARCH(" ",M5)))),1,0) -> 1 | AY5: =IF(AND(ISNUMBER(N5),LEN(N5)=10),1,0) -> 1 | AZ5: =IF(LEN(TRIM(O5))>=10,1,0) -> 1 | BA5: =IF(OR(ISBLANK(O5),O5=""),1,IF(ISTEXT(O5),1,0)) -> 1 | BB5: =IF(OR(ISBLANK(P5),P5=""),1,IF(ISTEXT(P5),1,0)) -> 1 | BC5: =IF(AND(ISNUMBER(R5),R5<=TODAY()),1,0) -> 1 | BD5: =IF(OR(ISBLANK(S5),S5=""),1,IF(ISTEXT(S5),1,0)) -> 1 | BE5: =IF(OR(ISBLANK(T5),T5=""),1,IF(ISTEXT(T5),1,0)) -> 1 | BF5: =IF(AND(ISNUMBER(U5),U5>0),1,0) -> 1 | BG5: =IF(AND(ISNUMBER(V5),V5<=TODAY()),1,0) -> 0
A6: =IF(AND(W6=1,X6=1),1,0) -> 1 | B6: =IF(AND(Y6=1,Z6=1,AA6=1,AB6=1,AC6=1,AD6=1,AE6=1,AF6=1,AG6=1,AH6=1,AI6=1,AJ6=1,AK6=1,AL6=1,AM6=1,AN6=1,AO6=1),1,0) -> 1 | C6: =IF(AND(AP6=1,AQ6=1,AR6=1,AS6=1,AT6=1,AU6=1,AV6=1,AW6=1,AX6=1,AY6=1,AZ6=1,BA6=1,BB6=1,BC6=1,BD6=1,BE6=1,BF6=1,BG6=1),1,0) -> 1 | D6: =IF(SUM(A6:C6)<3,1,0) -> 0 | E6: AF0005 | F6: CC | G6: 1000000005 | H6: Laura | I6: Ortiz | J6: Ortiz | K6: F | L6: 37322 | M6: laura.ortiz5@email.com | N6: 3923249330 | O6: Calle 65 #98-44 | P6: Pereira | Q6: Risaralda | R6: 45010 | S6: Retirado | T6: Call Center | U6: 75000 | V6: 45256 | W6: =IF(COUNTIF(E$2:E$201,E6)>1,0,1) -> 1 | X6: =IF(COUNTIF(G$2:G$201,G6)>1,0,1) -> 1 | Y6: =IF(E6="",0,1) -> 1 | Z6: =IF(F6="",0,1) -> 1 | AA6: =IF(G6="",0,1) -> 1 | AB6: =IF(H6="",0,1) -> 1 | AC6: =IF(I6="",0,1) -> 1 | AD6: =IF(K6="",0,1) -> 1 | AE6: =IF(L6="",0,1) -> 1 | AF6: =IF(M6="",0,1) -> 1 | AG6: =IF(N6="",0,1) -> 1 | AH6: =IF(O6="",0,1) -> 1 | AI6: =IF(P6="",0,1) -> 1 | AJ6: =IF(Q6="",0,1) -> 1 | AK6: =IF(R6="",0,1) -> 1 | ... AO6: =IF(V6="",0,1) -> 1 | AP6: =IF(AND(LEFT(E6,2)="AF",LEN(E6)=6),1,0) -> 1 | AQ6: =IF(OR(F6="CC",F6="CE",F6="TI",F6="PAS"),1,0) -> 1 | AR6: =IF(AND(ISNUMBER(G6),COUNTIF($G:$G,G6)=1),1,0) -> 1 | AS6: {=IF(AND(H6<>"",SUMPRODUCT(--ISNUMBER(FIND({0;1;2;3;4;5;6;7;8;9},H6)))=0),1,0)} -> 1 | AT6: {=IF(AND(I6<>"",SUMPRODUCT(--ISNUMBER(FIND({0;1;2;3;4;5;6;7;8;9},I6)))=0),1,0)} -> 1 | AU6: {=IF(AND(J6<>"",SUMPRODUCT(--ISNUMBER(FIND({0;1;2;3;4;5;6;7;8;9},J6)))=0),1,0)} -> 1 | AV6: =IF(OR(ISBLANK(K6),K6=""),1,IF(ISTEXT(K6),1,0)) -> 1 | AW6: =IF(AND(ISNUMBER(L6),L6<=TODAY()),1,0) -> 1 | AX6: =IF(AND(ISNUMBER(SEARCH("@",M6)),ISNUMBER(SEARCH(".",M6,SEARCH("@",M6)+2)),NOT(ISNUMBER(SEARCH(" ",M6)))),1,0) -> 1 | AY6: =IF(AND(ISNUMBER(N6),LEN(N6)=10),1,0) -> 1 | AZ6: =IF(LEN(TRIM(O6))>=10,1,0) -> 1 | BA6: =IF(OR(ISBLANK(O6),O6=""),1,IF(ISTEXT(O6),1,0)) -> 1 | BB6: =IF(OR(ISBLANK(P6),P6=""),1,IF(ISTEXT(P6),1,0)) -> 1 | BC6: =IF(AND(ISNUMBER(R6),R6<=TODAY()),1,0) -> 1 | BD6: =IF(OR(ISBLANK(S6),S6=""),1,IF(ISTEXT(S6),1,0)) -> 1 | BE6: =IF(OR(ISBLANK(T6),T6=""),1,IF(ISTEXT(T6),1,0)) -> 1 | BF6: =IF(AND(ISNUMBER(U6),U6>0),1,0) -> 1 | BG6: =IF(AND(ISNUMBER(V6),V6<=TODAY()),1,0) -> 1
A7: =IF(AND(W7=1,X7=1),1,0) -> 1 | B7: =IF(AND(Y7=1,Z7=1,AA7=1,AB7=1,AC7=1,AD7=1,AE7=1,AF7=1,AG7=1,AH7=1,AI7=1,AJ7=1,AK7=1,AL7=1,AM7=1,AN7=1,AO7=1),1,0) -> 1 | C7: =IF(AND(AP7=1,AQ7=1,AR7=1,AS7=1,AT7=1,AU7=1,AV7=1,AW7=1,AX7=1,AY7=1,AZ7=1,BA7=1,BB7=1,BC7=1,BD7=1,BE7=1,BF7=1,BG7=1),1,0) -> 1 | D7: =IF(SUM(A7:C7)<3,1,0) -> 0 | E7: AF0006 | F7: TI | G7: 1000000006 | H7: Juan | I7: Munoz | J7: Moreno | K7: M | L7: 35956 | M7: juan.munoz6@email.com | N7: 3795548752 | O7: Calle 63 #19-8 | P7: Barranquilla | Q7: Atlántico | R7: 45932 | S7: Suspendido | T7: Web | U7: 90000 | V7: 46011 | W7: =IF(COUNTIF(E$2:E$201,E7)>1,0,1) -> 1 | X7: =IF(COUNTIF(G$2:G$201,G7)>1,0,1) -> 1 | Y7: =IF(E7="",0,1) -> 1 | Z7: =IF(F7="",0,1) -> 1 | AA7: =IF(G7="",0,1) -> 1 | AB7: =IF(H7="",0,1) -> 1 | AC7: =IF(I7="",0,1) -> 1 | AD7: =IF(K7="",0,1) -> 1 | AE7: =IF(L7="",0,1) -> 1 | AF7: =IF(M7="",0,1) -> 1 | AG7: =IF(N7="",0,1) -> 1 | AH7: =IF(O7="",0,1) -> 1 | AI7: =IF(P7="",0,1) -> 1 | AJ7: =IF(Q7="",0,1) -> 1 | AK7: =IF(R7="",0,1) -> 1 | ... AO7: =IF(V7="",0,1) -> 1 | AP7: =IF(AND(LEFT(E7,2)="AF",LEN(E7)=6),1,0) -> 1 | AQ7: =IF(OR(F7="CC",F7="CE",F7="TI",F7="PAS"),1,0) -> 1 | AR7: =IF(AND(ISNUMBER(G7),COUNTIF($G:$G,G7)=1),1,0) -> 1 | AS7: {=IF(AND(H7<>"",SUMPRODUCT(--ISNUMBER(FIND({0;1;2;3;4;5;6;7;8;9},H7)))=0),1,0)} -> 1 | AT7: {=IF(AND(I7<>"",SUMPRODUCT(--ISNUMBER(FIND({0;1;2;3;4;5;6;7;8;9},I7)))=0),1,0)} -> 1 | AU7: {=IF(AND(J7<>"",SUMPRODUCT(--ISNUMBER(FIND({0;1;2;3;4;5;6;7;8;9},J7)))=0),1,0)} -> 1 | AV7: =IF(OR(ISBLANK(K7),K7=""),1,IF(ISTEXT(K7),1,0)) -> 1 | AW7: =IF(AND(ISNUMBER(L7),L7<=TODAY()),1,0) -> 1 | AX7: =IF(AND(ISNUMBER(SEARCH("@",M7)),ISNUMBER(SEARCH(".",M7,SEARCH("@",M7)+2)),NOT(ISNUMBER(SEARCH(" ",M7)))),1,0) -> 1 | AY7: =IF(AND(ISNUMBER(N7),LEN(N7)=10),1,0) -> 1 | AZ7: =IF(LEN(TRIM(O7))>=10,1,0) -> 1 | BA7: =IF(OR(ISBLANK(O7),O7=""),1,IF(ISTEXT(O7),1,0)) -> 1 | BB7: =IF(OR(ISBLANK(P7),P7=""),1,IF(ISTEXT(P7),1,0)) -> 1 | BC7: =IF(AND(ISNUMBER(R7),R7<=TODAY()),1,0) -> 1 | BD7: =IF(OR(ISBLANK(S7),S7=""),1,IF(ISTEXT(S7),1,0)) -> 1 | BE7: =IF(OR(ISBLANK(T7),T7=""),1,IF(ISTEXT(T7),1,0)) -> 1 | BF7: =IF(AND(ISNUMBER(U7),U7>0),1,0) -> 1 | BG7: =IF(AND(ISNUMBER(V7),V7<=TODAY()),1,0) -> 1
A8: =IF(AND(W8=1,X8=1),1,0) -> 1 | B8: =IF(AND(Y8=1,Z8=1,AA8=1,AB8=1,AC8=1,AD8=1,AE8=1,AF8=1,AG8=1,AH8=1,AI8=1,AJ8=1,AK8=1,AL8=1,AM8=1,AN8=1,AO8=1),1,0) -> 1 | C8: =IF(AND(AP8=1,AQ8=1,AR8=1,AS8=1,AT8=1,AU8=1,AV8=1,AW8=1,AX8=1,AY8=1,AZ8=1,BA8=1,BB8=1,BC8=1,BD8=1,BE8=1,BF8=1,BG8=1),1,0) -> 0 | D8: =IF(SUM(A8:C8)<3,1,0) -> 1 | E8: AF0007 | F8: CC | G8: 1000000007 | H8: Felipe | I8: Ortiz | J8: Munoz | K8: M | L8: 31252 | M8: correo_invalido | N8: 3648451309 | O8: Calle 28 #4-83 | P8: Pereira | Q8: Risaralda | R8: 45192 | S8: Retirado | T8: Presencial | U8: 85000 | V8: 45245 | W8: =IF(COUNTIF(E$2:E$201,E8)>1,0,1) -> 1 | X8: =IF(COUNTIF(G$2:G$201,G8)>1,0,1) -> 1 | Y8: =IF(E8="",0,1) -> 1 | Z8: =IF(F8="",0,1) -> 1 | AA8: =IF(G8="",0,1) -> 1 | AB8: =IF(H8="",0,1) -> 1 | AC8: =IF(I8="",0,1) -> 1 | AD8: =IF(K8="",0,1) -> 1 | AE8: =IF(L8="",0,1) -> 1 | AF8: =IF(M8="",0,1) -> 1 | AG8: =IF(N8="",0,1) -> 1 | AH8: =IF(O8="",0,1) -> 1 | AI8: =IF(P8="",0,1) -> 1 | AJ8: =IF(Q8="",0,1) -> 1 | AK8: =IF(R8="",0,1) -> 1 | ... AO8: =IF(V8="",0,1) -> 1 | AP8: =IF(AND(LEFT(E8,2)="AF",LEN(E8)=6),1,0) -> 1 | AQ8: =IF(OR(F8="CC",F8="CE",F8="TI",F8="PAS"),1,0) -> 1 | AR8: =IF(AND(ISNUMBER(G8),COUNTIF($G:$G,G8)=1),1,0) -> 1 | AS8: {=IF(AND(H8<>"",SUMPRODUCT(--ISNUMBER(FIND({0;1;2;3;4;5;6;7;8;9},H8)))=0),1,0)} -> 1 | AT8: {=IF(AND(I8<>"",SUMPRODUCT(--ISNUMBER(FIND({0;1;2;3;4;5;6;7;8;9},I8)))=0),1,0)} -> 1 | AU8: {=IF(AND(J8<>"",SUMPRODUCT(--ISNUMBER(FIND({0;1;2;3;4;5;6;7;8;9},J8)))=0),1,0)} -> 1 | AV8: =IF(OR(ISBLANK(K8),K8=""),1,IF(ISTEXT(K8),1,0)) -> 1 | AW8: =IF(AND(ISNUMBER(L8),L8<=TODAY()),1,0) -> 1 | AX8: =IF(AND(ISNUMBER(SEARCH("@",M8)),ISNUMBER(SEARCH(".",M8,SEARCH("@",M8)+2)),NOT(ISNUMBER(SEARCH(" ",M8)))),1,0) -> 0 | AY8: =IF(AND(ISNUMBER(N8),LEN(N8)=10),1,0) -> 1 | AZ8: =IF(LEN(TRIM(O8))>=10,1,0) -> 1 | BA8: =IF(OR(ISBLANK(O8),O8=""),1,IF(ISTEXT(O8),1,0)) -> 1 | BB8: =IF(OR(ISBLANK(P8),P8=""),1,IF(ISTEXT(P8),1,0)) -> 1 | BC8: =IF(AND(ISNUMBER(R8),R8<=TODAY()),1,0) -> 1 | BD8: =IF(OR(ISBLANK(S8),S8=""),1,IF(ISTEXT(S8),1,0)) -> 1 | BE8: =IF(OR(ISBLANK(T8),T8=""),1,IF(ISTEXT(T8),1,0)) -> 1 | BF8: =IF(AND(ISNUMBER(U8),U8>0),1,0) -> 1 | BG8: =IF(AND(ISNUMBER(V8),V8<=TODAY()),1,0) -> 1
A9: =IF(AND(W9=1,X9=1),1,0) -> 1 | B9: =IF(AND(Y9=1,Z9=1,AA9=1,AB9=1,AC9=1,AD9=1,AE9=1,AF9=1,AG9=1,AH9=1,AI9=1,AJ9=1,AK9=1,AL9=1,AM9=1,AN9=1,AO9=1),1,0) -> 1 | C9: =IF(AND(AP9=1,AQ9=1,AR9=1,AS9=1,AT9=1,AU9=1,AV9=1,AW9=1,AX9=1,AY9=1,AZ9=1,BA9=1,BB9=1,BC9=1,BD9=1,BE9=1,BF9=1,BG9=1),1,0) -> 0 | D9: =IF(SUM(A9:C9)<3,1,0) -> 1 | E9: AF0008 | F9: CC | G9: 1000000008 | H9: Javier | I9: Vargas | J9: Torres | K9: M | L9: 31192 | M9: javier.vargas8@email.com | N9: 3519171267 | O9: Calle 93 #37-63 | P9: Pereira | Q9: Risaralda | R9: 46049 | S9: Retirado | T9: Presencial | U9: 95000 | V9: 46368 | W9: =IF(COUNTIF(E$2:E$201,E9)>1,0,1) -> 1 | X9: =IF(COUNTIF(G$2:G$201,G9)>1,0,1) -> 1 | Y9: =IF(E9="",0,1) -> 1 | Z9: =IF(F9="",0,1) -> 1 | AA9: =IF(G9="",0,1) -> 1 | AB9: =IF(H9="",0,1) -> 1 | AC9: =IF(I9="",0,1) -> 1 | AD9: =IF(K9="",0,1) -> 1 | AE9: =IF(L9="",0,1) -> 1 | AF9: =IF(M9="",0,1) -> 1 | AG9: =IF(N9="",0,1) -> 1 | AH9: =IF(O9="",0,1) -> 1 | AI9: =IF(P9="",0,1) -> 1 | AJ9: =IF(Q9="",0,1) -> 1 | AK9: =IF(R9="",0,1) -> 1 | ... AO9: =IF(V9="",0,1) -> 1 | AP9: =IF(AND(LEFT(E9,2)="AF",LEN(E9)=6),1,0) -> 1 | AQ9: =IF(OR(F9="CC",F9="CE",F9="TI",F9="PAS"),1,0) -> 1 | AR9: =IF(AND(ISNUMBER(G9),COUNTIF($G:$G,G9)=1),1,0) -> 1 | AS9: {=IF(AND(H9<>"",SUMPRODUCT(--ISNUMBER(FIND({0;1;2;3;4;5;6;7;8;9},H9)))=0),1,0)} -> 1 | AT9: {=IF(AND(I9<>"",SUMPRODUCT(--ISNUMBER(FIND({0;1;2;3;4;5;6;7;8;9},I9)))=0),1,0)} -> 1 | AU9: {=IF(AND(J9<>"",SUMPRODUCT(--ISNUMBER(FIND({0;1;2;3;4;5;6;7;8;9},J9)))=0),1,0)} -> 1 | AV9: =IF(OR(ISBLANK(K9),K9=""),1,IF(ISTEXT(K9),1,0)) -> 1 | AW9: =IF(AND(ISNUMBER(L9),L9<=TODAY()),1,0) -> 1 | AX9: =IF(AND(ISNUMBER(SEARCH("@",M9)),ISNUMBER(SEARCH(".",M9,SEARCH("@",M9)+2)),NOT(ISNUMBER(SEARCH(" ",M9)))),1,0) -> 1 | AY9: =IF(AND(ISNUMBER(N9),LEN(N9)=10),1,0) -> 1 | AZ9: =IF(LEN(TRIM(O9))>=10,1,0) -> 1 | BA9: =IF(OR(ISBLANK(O9),O9=""),1,IF(ISTEXT(O9),1,0)) -> 1 | BB9: =IF(OR(ISBLANK(P9),P9=""),1,IF(ISTEXT(P9),1,0)) -> 1 | BC9: =IF(AND(ISNUMBER(R9),R9<=TODAY()),1,0) -> 1 | BD9: =IF(OR(ISBLANK(S9),S9=""),1,IF(ISTEXT(S9),1,0)) -> 1 | BE9: =IF(OR(ISBLANK(T9),T9=""),1,IF(ISTEXT(T9),1,0)) -> 1 | BF9: =IF(AND(ISNUMBER(U9),U9>0),1,0) -> 1 | BG9: =IF(AND(ISNUMBER(V9),V9<=TODAY()),1,0) -> 0
A10: =IF(AND(W10=1,X10=1),1,0) -> 1 | B10: =IF(AND(Y10=1,Z10=1,AA10=1,AB10=1,AC10=1,AD10=1,AE10=1,AF10=1,AG10=1,AH10=1,AI10=1,AJ10=1,AK10=1,AL10=1,AM10=1,AN10=1,AO10=1),1,0) -> 1 | C10: =IF(AND(AP10=1,AQ10=1,AR10=1,AS10=1,AT10=1,AU10=1,AV10=1,AW10=1,AX10=1,AY10=1,AZ10=1,BA10=1,BB10=1,BC10=1,BD10=1,BE10=1,BF10=1,BG10=1),1,0) -> 1 | D10: =IF(SUM(A10:C10)<3,1,0) -> 0 | E10: AF0009 | F10: TI | G10: 1000000009 | H10: Sergio | I10: Munoz | J10: Leon | K10: M | L10: 24289 | M10: sergio.munoz9@email.com | N10: 3647568116 | O10: Calle 106 #87-87 | P10: Medellín | Q10: Antioquia | R10: 44924 | S10: Activo | T10: Presencial | U10: 90000 | V10: 45038 | W10: =IF(COUNTIF(E$2:E$201,E10)>1,0,1) -> 1 | X10: =IF(COUNTIF(G$2:G$201,G10)>1,0,1) -> 1 | Y10: =IF(E10="",0,1) -> 1 | Z10: =IF(F10="",0,1) -> 1 | AA10: =IF(G10="",0,1) -> 1 | AB10: =IF(H10="",0,1) -> 1 | AC10: =IF(I10="",0,1) -> 1 | AD10: =IF(K10="",0,1) -> 1 | AE10: =IF(L10="",0,1) -> 1 | AF10: =IF(M10="",0,1) -> 1 | AG10: =IF(N10="",0,1) -> 1 | AH10: =IF(O10="",0,1) -> 1 | AI10: =IF(P10="",0,1) -> 1 | AJ10: =IF(Q10="",0,1) -> 1 | AK10: =IF(R10="",0,1) -> 1 | ... AO10: =IF(V10="",0,1) -> 1 | AP10: =IF(AND(LEFT(E10,2)="AF",LEN(E10)=6),1,0) -> 1 | AQ10: =IF(OR(F10="CC",F10="CE",F10="TI",F10="PAS"),1,0) -> 1 | AR10: =IF(AND(ISNUMBER(G10),COUNTIF($G:$G,G10)=1),1,0) -> 1 | AS10: {=IF(AND(H10<>"",SUMPRODUCT(--ISNUMBER(FIND({0;1;2;3;4;5;6;7;8;9},H10)))=0),1,0)} -> 1 | AT10: {=IF(AND(I10<>"",SUMPRODUCT(--ISNUMBER(FIND({0;1;2;3;4;5;6;7;8;9},I10)))=0),1,0)} -> 1 | AU10: {=IF(AND(J10<>"",SUMPRODUCT(--ISNUMBER(FIND({0;1;2;3;4;5;6;7;8;9},J10)))=0),1,0)} -> 1 | AV10: =IF(OR(ISBLANK(K10),K10=""),1,IF(ISTEXT(K10),1,0)) -> 1 | AW10: =IF(AND(ISNUMBER(L10),L10<=TODAY()),1,0) -> 1 | AX10: =IF(AND(ISNUMBER(SEARCH("@",M10)),ISNUMBER(SEARCH(".",M10,SEARCH("@",M10)+2)),NOT(ISNUMBER(SEARCH(" ",M10)))),1,0) -> 1 | AY10: =IF(AND(ISNUMBER(N10),LEN(N10)=10),1,0) -> 1 | AZ10: =IF(LEN(TRIM(O10))>=10,1,0) -> 1 | BA10: =IF(OR(ISBLANK(O10),O10=""),1,IF(ISTEXT(O10),1,0)) -> 1 | BB10: =IF(OR(ISBLANK(P10),P10=""),1,IF(ISTEXT(P10),1,0)) -> 1 | BC10: =IF(AND(ISNUMBER(R10),R10<=TODAY()),1,0) -> 1 | BD10: =IF(OR(ISBLANK(S10),S10=""),1,IF(ISTEXT(S10),1,0)) -> 1 | BE10: =IF(OR(ISBLANK(T10),T10=""),1,IF(ISTEXT(T10),1,0)) -> 1 | BF10: =IF(AND(ISNUMBER(U10),U10>0),1,0) -> 1 | BG10: =IF(AND(ISNUMBER(V10),V10<=TODAY()),1,0) -> 1
A11: =IF(AND(W11=1,X11=1),1,0) -> 1 | B11: =IF(AND(Y11=1,Z11=1,AA11=1,AB11=1,AC11=1,AD11=1,AE11=1,AF11=1,AG11=1,AH11=1,AI11=1,AJ11=1,AK11=1,AL11=1,AM11=1,AN11=1,AO11=1),1,0) -> 1 | C11: =IF(AND(AP11=1,AQ11=1,AR11=1,AS11=1,AT11=1,AU11=1,AV11=1,AW11=1,AX11=1,AY11=1,AZ11=1,BA11=1,BB11=1,BC11=1,BD11=1,BE11=1,BF11=1,BG11=1),1,0) -> 1 | D11: =IF(SUM(A11:C11)<3,1,0) -> 0 | E11: AF0010 | F11: TI | G11: 1000000010 | H11: Felipe | I11: Martinez | J11: Munoz | K11: M | L11: 31441 | M11: felipe.martinez10@email.com | N11: 3231368902 | O11: Calle 108 #16-19 | P11: Barranquilla | Q11: Atlántico | R11: 44860 | S11: Retirado | T11: Presencial | U11: 90000 | V11: 45065 | W11: =IF(COUNTIF(E$2:E$201,E11)>1,0,1) -> 1 | X11: =IF(COUNTIF(G$2:G$201,G11)>1,0,1) -> 1 | Y11: =IF(E11="",0,1) -> 1 | Z11: =IF(F11="",0,1) -> 1 | AA11: =IF(G11="",0,1) -> 1 | AB11: =IF(H11="",0,1) -> 1 | AC11: =IF(I11="",0,1) -> 1 | AD11: =IF(K11="",0,1) -> 1 | AE11: =IF(L11="",0,1) -> 1 | AF11: =IF(M11="",0,1) -> 1 | AG11: =IF(N11="",0,1) -> 1 | AH11: =IF(O11="",0,1) -> 1 | AI11: =IF(P11="",0,1) -> 1 | AJ11: =IF(Q11="",0,1) -> 1 | AK11: =IF(R11="",0,1) -> 1 | ... AO11: =IF(V11="",0,1) -> 1 | AP11: =IF(AND(LEFT(E11,2)="AF",LEN(E11)=6),1,0) -> 1 | AQ11: =IF(OR(F11="CC",F11="CE",F11="TI",F11="PAS"),1,0) -> 1 | AR11: =IF(AND(ISNUMBER(G11),COUNTIF($G:$G,G11)=1),1,0) -> 1 | AS11: {=IF(AND(H11<>"",SUMPRODUCT(--ISNUMBER(FIND({0;1;2;3;4;5;6;7;8;9},H11)))=0),1,0)} -> 1 | AT11: {=IF(AND(I11<>"",SUMPRODUCT(--ISNUMBER(FIND({0;1;2;3;4;5;6;7;8;9},I11)))=0),1,0)} -> 1 | AU11: {=IF(AND(J11<>"",SUMPRODUCT(--ISNUMBER(FIND({0;1;2;3;4;5;6;7;8;9},J11)))=0),1,0)} -> 1 | AV11: =IF(OR(ISBLANK(K11),K11=""),1,IF(ISTEXT(K11),1,0)) -> 1 | AW11: =IF(AND(ISNUMBER(L11),L11<=TODAY()),1,0) -> 1 | AX11: =IF(AND(ISNUMBER(SEARCH("@",M11)),ISNUMBER(SEARCH(".",M11,SEARCH("@",M11)+2)),NOT(ISNUMBER(SEARCH(" ",M11)))),1,0) -> 1 | AY11: =IF(AND(ISNUMBER(N11),LEN(N11)=10),1,0) -> 1 | AZ11: =IF(LEN(TRIM(O11))>=10,1,0) -> 1 | BA11: =IF(OR(ISBLANK(O11),O11=""),1,IF(ISTEXT(O11),1,0)) -> 1 | BB11: =IF(OR(ISBLANK(P11),P11=""),1,IF(ISTEXT(P11),1,0)) -> 1 | BC11: =IF(AND(ISNUMBER(R11),R11<=TODAY()),1,0) -> 1 | BD11: =IF(OR(ISBLANK(S11),S11=""),1,IF(ISTEXT(S11),1,0)) -> 1 | BE11: =IF(OR(ISBLANK(T11),T11=""),1,IF(ISTEXT(T11),1,0)) -> 1 | BF11: =IF(AND(ISNUMBER(U11),U11>0),1,0) -> 1 | BG11: =IF(AND(ISNUMBER(V11),V11<=TODAY()),1,0) -> 1
A12: =IF(AND(W12=1,X12=1),1,0) -> 1 | B12: =IF(AND(Y12=1,Z12=1,AA12=1,AB12=1,AC12=1,AD12=1,AE12=1,AF12=1,AG12=1,AH12=1,AI12=1,AJ12=1,AK12=1,AL12=1,AM12=1,AN12=1,AO12=1),1,0) -> 1 | C12: =IF(AND(AP12=1,AQ12=1,AR12=1,AS12=1,AT12=1,AU12=1,AV12=1,AW12=1,AX12=1,AY12=1,AZ12=1,BA12=1,BB12=1,BC12=1,BD12=1,BE12=1,BF12=1,BG12=1),1,0) -> 1 | D12: =IF(SUM(A12:C12)<3,1,0) -> 0 | E12: AF0011 | F12: CE | G12: 1000000011 | H12: Juliana | I12: Torres | J12: Martinez | K12: F | L12: 24906 | M12: juliana.torres11@email.com | N12: 3701522160 | O12: Calle 104 #86-27 | P12: Medellín | Q12: Antioquia | R12: 44964 | S12: Activo | T12: Presencial | U12: 75000 | V12: 45000 | W12: =IF(COUNTIF(E$2:E$201,E12)>1,0,1) -> 1 | X12: =IF(COUNTIF(G$2:G$201,G12)>1,0,1) -> 1 | Y12: =IF(E12="",0,1) -> 1 | Z12: =IF(F12="",0,1) -> 1 | AA12: =IF(G12="",0,1) -> 1 | AB12: =IF(H12="",0,1) -> 1 | AC12: =IF(I12="",0,1) -> 1 | AD12: =IF(K12="",0,1) -> 1 | AE12: =IF(L12="",0,1) -> 1 | AF12: =IF(M12="",0,1) -> 1 | AG12: =IF(N12="",0,1) -> 1 | AH12: =IF(O12="",0,1) -> 1 | AI12: =IF(P12="",0,1) -> 1 | AJ12: =IF(Q12="",0,1) -> 1 | AK12: =IF(R12="",0,1) -> 1 | ... AO12: =IF(V12="",0,1) -> 1 | AP12: =IF(AND(LEFT(E12,2)="AF",LEN(E12)=6),1,0) -> 1 | AQ12: =IF(OR(F12="CC",F12="CE",F12="TI",F12="PAS"),1,0) -> 1 | AR12: =IF(AND(ISNUMBER(G12),COUNTIF($G:$G,G12)=1),1,0) -> 1 | AS12: {=IF(AND(H12<>"",SUMPRODUCT(--ISNUMBER(FIND({0;1;2;3;4;5;6;7;8;9},H12)))=0),1,0)} -> 1 | AT12: {=IF(AND(I12<>"",SUMPRODUCT(--ISNUMBER(FIND({0;1;2;3;4;5;6;7;8;9},I12)))=0),1,0)} -> 1 | AU12: {=IF(AND(J12<>"",SUMPRODUCT(--ISNUMBER(FIND({0;1;2;3;4;5;6;7;8;9},J12)))=0),1,0)} -> 1 | AV12: =IF(OR(ISBLANK(K12),K12=""),1,IF(ISTEXT(K12),1,0)) -> 1 | AW12: =IF(AND(ISNUMBER(L12),L12<=TODAY()),1,0) -> 1 | AX12: =IF(AND(ISNUMBER(SEARCH("@",M12)),ISNUMBER(SEARCH(".",M12,SEARCH("@",M12)+2)),NOT(ISNUMBER(SEARCH(" ",M12)))),1,0) -> 1 | AY12: =IF(AND(ISNUMBER(N12),LEN(N12)=10),1,0) -> 1 | AZ12: =IF(LEN(TRIM(O12))>=10,1,0) -> 1 | BA12: =IF(OR(ISBLANK(O12),O12=""),1,IF(ISTEXT(O12),1,0)) -> 1 | BB12: =IF(OR(ISBLANK(P12),P12=""),1,IF(ISTEXT(P12),1,0)) -> 1 | BC12: =IF(AND(ISNUMBER(R12),R12<=TODAY()),1,0) -> 1 | BD12: =IF(OR(ISBLANK(S12),S12=""),1,IF(ISTEXT(S12),1,0)) -> 1 | BE12: =IF(OR(ISBLANK(T12),T12=""),1,IF(ISTEXT(T12),1,0)) -> 1 | BF12: =IF(AND(ISNUMBER(U12),U12>0),1,0) -> 1 | BG12: =IF(AND(ISNUMBER(V12),V12<=TODAY()),1,0) -> 1
A13: =IF(AND(W13=1,X13=1),1,0) -> 1 | B13: =IF(AND(Y13=1,Z13=1,AA13=1,AB13=1,AC13=1,AD13=1,AE13=1,AF13=1,AG13=1,AH13=1,AI13=1,AJ13=1,AK13=1,AL13=1,AM13=1,AN13=1,AO13=1),1,0) -> 1 | C13: =IF(AND(AP13=1,AQ13=1,AR13=1,AS13=1,AT13=1,AU13=1,AV13=1,AW13=1,AX13=1,AY13=1,AZ13=1,BA13=1,BB13=1,BC13=1,BD13=1,BE13=1,BF13=1,BG13=1),1,0) -> 0 | D13: =IF(SUM(A13:C13)<3,1,0) -> 1 | E13: AF0012 | F13: TI | G13: 1000000012 | H13: Daniela | I13: Restrepo | J13: Restrepo | K13: F | L13: 34311 | M13: correo_invalido | N13: 3441184046 | O13: Calle 110 #77-39 | P13: Barranquilla | Q13: Atlántico | R13: 45827 | S13: Activo | T13: Presencial | U13: 75000 | V13: 45967 | W13: =IF(COUNTIF(E$2:E$201,E13)>1,0,1) -> 1 | X13: =IF(COUNTIF(G$2:G$201,G13)>1,0,1) -> 1 | Y13: =IF(E13="",0,1) -> 1 | Z13: =IF(F13="",0,1) -> 1 | AA13: =IF(G13="",0,1) -> 1 | AB13: =IF(H13="",0,1) -> 1 | AC13: =IF(I13="",0,1) -> 1 | AD13: =IF(K13="",0,1) -> 1 | AE13: =IF(L13="",0,1) -> 1 | AF13: =IF(M13="",0,1) -> 1 | AG13: =IF(N13="",0,1) -> 1 | AH13: =IF(O13="",0,1) -> 1 | AI13: =IF(P13="",0,1) -> 1 | AJ13: =IF(Q13="",0,1) -> 1 | AK13: =IF(R13="",0,1) -> 1 | ... AO13: =IF(V13="",0,1) -> 1 | AP13: =IF(AND(LEFT(E13,2)="AF",LEN(E13)=6),1,0) -> 1 | AQ13: =IF(OR(F13="CC",F13="CE",F13="TI",F13="PAS"),1,0) -> 1 | AR13: =IF(AND(ISNUMBER(G13),COUNTIF($G:$G,G13)=1),1,0) -> 1 | AS13: {=IF(AND(H13<>"",SUMPRODUCT(--ISNUMBER(FIND({0;1;2;3;4;5;6;7;8;9},H13)))=0),1,0)} -> 1 | AT13: {=IF(AND(I13<>"",SUMPRODUCT(--ISNUMBER(FIND({0;1;2;3;4;5;6;7;8;9},I13)))=0),1,0)} -> 1 | AU13: {=IF(AND(J13<>"",SUMPRODUCT(--ISNUMBER(FIND({0;1;2;3;4;5;6;7;8;9},J13)))=0),1,0)} -> 1 | AV13: =IF(OR(ISBLANK(K13),K13=""),1,IF(ISTEXT(K13),1,0)) -> 1 | AW13: =IF(AND(ISNUMBER(L13),L13<=TODAY()),1,0) -> 1 | AX13: =IF(AND(ISNUMBER(SEARCH("@",M13)),ISNUMBER(SEARCH(".",M13,SEARCH("@",M13)+2)),NOT(ISNUMBER(SEARCH(" ",M13)))),1,0) -> 0 | AY13: =IF(AND(ISNUMBER(N13),LEN(N13)=10),1,0) -> 1 | AZ13: =IF(LEN(TRIM(O13))>=10,1,0) -> 1 | BA13: =IF(OR(ISBLANK(O13),O13=""),1,IF(ISTEXT(O13),1,0)) -> 1 | BB13: =IF(OR(ISBLANK(P13),P13=""),1,IF(ISTEXT(P13),1,0)) -> 1 | BC13: =IF(AND(ISNUMBER(R13),R13<=TODAY()),1,0) -> 1 | BD13: =IF(OR(ISBLANK(S13),S13=""),1,IF(ISTEXT(S13),1,0)) -> 1 | BE13: =IF(OR(ISBLANK(T13),T13=""),1,IF(ISTEXT(T13),1,0)) -> 1 | BF13: =IF(AND(ISNUMBER(U13),U13>0),1,0) -> 1 | BG13: =IF(AND(ISNUMBER(V13),V13<=TODAY()),1,0) -> 1
... A32: =IF(AND(W32=1,X32=1),1,0) -> 1 | B32: =IF(AND(Y32=1,Z32=1,AA32=1,AB32=1,AC32=1,AD32=1,AE32=1,AF32=1,AG32=1,AH32=1,AI32=1,AJ32=1,AK32=1,AL32=1,AM32=1,AN32=1,AO32=1),1,0) -> 1 | C32: =IF(AND(AP32=1,AQ32=1,AR32=1,AS32=1,AT32=1,AU32=1,AV32=1,AW32=1,AX32=1,AY32=1,AZ32=1,BA32=1,BB32=1,BC32=1,BD32=1,BE32=1,BF32=1,BG32=1),1,0) -> 1 | D32: =IF(SUM(A32:C32)<3,1,0) -> 0 | E32: AF0031 | F32: CC | G32: 1000000031 | H32: Laura | I32: Ortiz | J32: Ortiz | K32: F | L32: 36956 | M32: laura.ortiz31@email.com | N32: 3196453482 | O32: Calle 29 #46-83 | P32: Bucaramanga | Q32: Santander | R32: 44597 | S32: Suspendido | T32: Presencial | U32: 90000 | V32: 44945 | W32: =IF(COUNTIF(E$2:E$201,E32)>1,0,1) -> 1 | X32: =IF(COUNTIF(G$2:G$201,G32)>1,0,1) -> 1 | Y32: =IF(E32="",0,1) -> 1 | Z32: =IF(F32="",0,1) -> 1 | AA32: =IF(G32="",0,1) -> 1 | AB32: =IF(H32="",0,1) -> 1 | AC32: =IF(I32="",0,1) -> 1 | AD32: =IF(K32="",0,1) -> 1 | AE32: =IF(L32="",0,1) -> 1 | AF32: =IF(M32="",0,1) -> 1 | AG32: =IF(N32="",0,1) -> 1 | AH32: =IF(O32="",0,1) -> 1 | AI32: =IF(P32="",0,1) -> 1 | AJ32: =IF(Q32="",0,1) -> 1 | AK32: =IF(R32="",0,1) -> 1 | ... AO32: =IF(V32="",0,1) -> 1 | AP32: =IF(AND(LEFT(E32,2)="AF",LEN(E32)=6),1,0) -> 1 | AQ32: =IF(OR(F32="CC",F32="CE",F32="TI",F32="PAS"),1,0) -> 1 | AR32: =IF(AND(ISNUMBER(G32),COUNTIF($G:$G,G32)=1),1,0) -> 1 | AS32: {=IF(AND(H32<>"",SUMPRODUCT(--ISNUMBER(FIND({0;1;2;3;4;5;6;7;8;9},H32)))=0),1,0)} -> 1 | AT32: {=IF(AND(I32<>"",SUMPRODUCT(--ISNUMBER(FIND({0;1;2;3;4;5;6;7;8;9},I32)))=0),1,0)} -> 1 | AU32: {=IF(AND(J32<>"",SUMPRODUCT(--ISNUMBER(FIND({0;1;2;3;4;5;6;7;8;9},J32)))=0),1,0)} -> 1 | AV32: =IF(OR(ISBLANK(K32),K32=""),1,IF(ISTEXT(K32),1,0)) -> 1 | AW32: =IF(AND(ISNUMBER(L32),L32<=TODAY()),1,0) -> 1 | AX32: =IF(AND(ISNUMBER(SEARCH("@",M32)),ISNUMBER(SEARCH(".",M32,SEARCH("@",M32)+2)),NOT(ISNUMBER(SEARCH(" ",M32)))),1,0) -> 1 | AY32: =IF(AND(ISNUMBER(N32),LEN(N32)=10),1,0) -> 1 | AZ32: =IF(LEN(TRIM(O32))>=10,1,0) -> 1 | BA32: =IF(OR(ISBLANK(O32),O32=""),1,IF(ISTEXT(O32),1,0)) -> 1 | BB32: =IF(OR(ISBLANK(P32),P32=""),1,IF(ISTEXT(P32),1,0)) -> 1 | BC32: =IF(AND(ISNUMBER(R32),R32<=TODAY()),1,0) -> 1 | BD32: =IF(OR(ISBLANK(S32),S32=""),1,IF(ISTEXT(S32),1,0)) -> 1 | BE32: =IF(OR(ISBLANK(T32),T32=""),1,IF(ISTEXT(T32),1,0)) -> 1 | BF32: =IF(AND(ISNUMBER(U32),U32>0),1,0) -> 1 | BG32: =IF(AND(ISNUMBER(V32),V32<=TODAY()),1,0) -> 1
A33: =IF(AND(W33=1,X33=1),1,0) -> 1 | B33: =IF(AND(Y33=1,Z33=1,AA33=1,AB33=1,AC33=1,AD33=1,AE33=1,AF33=1,AG33=1,AH33=1,AI33=1,AJ33=1,AK33=1,AL33=1,AM33=1,AN33=1,AO33=1),1,0) -> 0 | C33: =IF(AND(AP33=1,AQ33=1,AR33=1,AS33=1,AT33=1,AU33=1,AV33=1,AW33=1,AX33=1,AY33=1,AZ33=1,BA33=1,BB33=1,BC33=1,BD33=1,BE33=1,BF33=1,BG33=1),1,0) -> 0 | D33: =IF(SUM(A33:C33)<3,1,0) -> 1 | E33: AF0032 | F33: CE | G33: 1000000032 | I33: Ortiz | J33: Herrera | K33: F | L33: 26752 | M33: diana.ortiz32@email.com | N33: 3678279836 | O33: Calle 86 #20-64 | P33: Bucaramanga | Q33: Santander | R33: 45980 | S33: Retirado | T33: Call Center | U33: 85000 | V33: 46189 | W33: =IF(COUNTIF(E$2:E$201,E33)>1,0,1) -> 1 | X33: =IF(COUNTIF(G$2:G$201,G33)>1,0,1) -> 1 | Y33: =IF(E33="",0,1) -> 1 | Z33: =IF(F33="",0,1) -> 1 | AA33: =IF(G33="",0,1) -> 1 | AB33: =IF(H33="",0,1) -> 0 | AC33: =IF(I33="",0,1) -> 1 | AD33: =IF(K33="",0,1) -> 1 | AE33: =IF(L33="",0,1) -> 1 | AF33: =IF(M33="",0,1) -> 1 | AG33: =IF(N33="",0,1) -> 1 | AH33: =IF(O33="",0,1) -> 1 | AI33: =IF(P33="",0,1) -> 1 | AJ33: =IF(Q33="",0,1) -> 1 | AK33: =IF(R33="",0,1) -> 1 | ... AO33: =IF(V33="",0,1) -> 1 | AP33: =IF(AND(LEFT(E33,2)="AF",LEN(E33)=6),1,0) -> 1 | AQ33: =IF(OR(F33="CC",F33="CE",F33="TI",F33="PAS"),1,0) -> 1 | AR33: =IF(AND(ISNUMBER(G33),COUNTIF($G:$G,G33)=1),1,0) -> 1 | AS33: {=IF(AND(H33<>"",SUMPRODUCT(--ISNUMBER(FIND({0;1;2;3;4;5;6;7;8;9},H33)))=0),1,0)} -> 0 | AT33: {=IF(AND(I33<>"",SUMPRODUCT(--ISNUMBER(FIND({0;1;2;3;4;5;6;7;8;9},I33)))=0),1,0)} -> 1 | AU33: {=IF(AND(J33<>"",SUMPRODUCT(--ISNUMBER(FIND({0;1;2;3;4;5;6;7;8;9},J33)))=0),1,0)} -> 1 | AV33: =IF(OR(ISBLANK(K33),K33=""),1,IF(ISTEXT(K33),1,0)) -> 1 | AW33: =IF(AND(ISNUMBER(L33),L33<=TODAY()),1,0) -> 1 | AX33: =IF(AND(ISNUMBER(SEARCH("@",M33)),ISNUMBER(SEARCH(".",M33,SEARCH("@",M33)+2)),NOT(ISNUMBER(SEARCH(" ",M33)))),1,0) -> 1 | AY33: =IF(AND(ISNUMBER(N33),LEN(N33)=10),1,0) -> 1 | AZ33: =IF(LEN(TRIM(O33))>=10,1,0) -> 1 | BA33: =IF(OR(ISBLANK(O33),O33=""),1,IF(ISTEXT(O33),1,0)) -> 1 | BB33: =IF(OR(ISBLANK(P33),P33=""),1,IF(ISTEXT(P33),1,0)) -> 1 | BC33: =IF(AND(ISNUMBER(R33),R33<=TODAY()),1,0) -> 1 | BD33: =IF(OR(ISBLANK(S33),S33=""),1,IF(ISTEXT(S33),1,0)) -> 1 | BE33: =IF(OR(ISBLANK(T33),T33=""),1,IF(ISTEXT(T33),1,0)) -> 1 | BF33: =IF(AND(ISNUMBER(U33),U33>0),1,0) -> 1 | BG33: =IF(AND(ISNUMBER(V33),V33<=TODAY()),1,0) -> 0
A34: =IF(AND(W34=1,X34=1),1,0) -> 1 | B34: =IF(AND(Y34=1,Z34=1,AA34=1,AB34=1,AC34=1,AD34=1,AE34=1,AF34=1,AG34=1,AH34=1,AI34=1,AJ34=1,AK34=1,AL34=1,AM34=1,AN34=1,AO34=1),1,0) -> 1 | C34: =IF(AND(AP34=1,AQ34=1,AR34=1,AS34=1,AT34=1,AU34=1,AV34=1,AW34=1,AX34=1,AY34=1,AZ34=1,BA34=1,BB34=1,BC34=1,BD34=1,BE34=1,BF34=1,BG34=1),1,0) -> 0 | D34: =IF(SUM(A34:C34)<3,1,0) -> 1 | E34: AF0033 | F34: CC | G34: 1000000033 | H34: Carlos | I34: Herrera | J34: Herrera | K34: M | L34: 35352 | M34: correo_invalido | N34: 3713333937 | O34: Calle 8 #85-19 | P34: Bucaramanga | Q34: Santander | R34: 44678 | S34: Retirado | T34: Presencial | U34: 85000 | V34: 44913 | W34: =IF(COUNTIF(E$2:E$201,E34)>1,0,1) -> 1 | X34: =IF(COUNTIF(G$2:G$201,G34)>1,0,1) -> 1 | Y34: =IF(E34="",0,1) -> 1 | Z34: =IF(F34="",0,1) -> 1 | AA34: =IF(G34="",0,1) -> 1 | AB34: =IF(H34="",0,1) -> 1 | AC34: =IF(I34="",0,1) -> 1 | AD34: =IF(K34="",0,1) -> 1 | AE34: =IF(L34="",0,1) -> 1 | AF34: =IF(M34="",0,1) -> 1 | AG34: =IF(N34="",0,1) -> 1 | AH34: =IF(O34="",0,1) -> 1 | AI34: =IF(P34="",0,1) -> 1 | AJ34: =IF(Q34="",0,1) -> 1 | AK34: =IF(R34="",0,1) -> 1 | ... AO34: =IF(V34="",0,1) -> 1 | AP34: =IF(AND(LEFT(E34,2)="AF",LEN(E34)=6),1,0) -> 1 | AQ34: =IF(OR(F34="CC",F34="CE",F34="TI",F34="PAS"),1,0) -> 1 | AR34: =IF(AND(ISNUMBER(G34),COUNTIF($G:$G,G34)=1),1,0) -> 1 | AS34: {=IF(AND(H34<>"",SUMPRODUCT(--ISNUMBER(FIND({0;1;2;3;4;5;6;7;8;9},H34)))=0),1,0)} -> 1 | AT34: {=IF(AND(I34<>"",SUMPRODUCT(--ISNUMBER(FIND({0;1;2;3;4;5;6;7;8;9},I34)))=0),1,0)} -> 1 | AU34: {=IF(AND(J34<>"",SUMPRODUCT(--ISNUMBER(FIND({0;1;2;3;4;5;6;7;8;9},J34)))=0),1,0)} -> 1 | AV34: =IF(OR(ISBLANK(K34),K34=""),1,IF(ISTEXT(K34),1,0)) -> 1 | AW34: =IF(AND(ISNUMBER(L34),L34<=TODAY()),1,0) -> 1 | AX34: =IF(AND(ISNUMBER(SEARCH("@",M34)),ISNUMBER(SEARCH(".",M34,SEARCH("@",M34)+2)),NOT(ISNUMBER(SEARCH(" ",M34)))),1,0) -> 0 | AY34: =IF(AND(ISNUMBER(N34),LEN(N34)=10),1,0) -> 1 | AZ34: =IF(LEN(TRIM(O34))>=10,1,0) -> 1 | BA34: =IF(OR(ISBLANK(O34),O34=""),1,IF(ISTEXT(O34),1,0)) -> 1 | BB34: =IF(OR(ISBLANK(P34),P34=""),1,IF(ISTEXT(P34),1,0)) -> 1 | BC34: =IF(AND(ISNUMBER(R34),R34<=TODAY()),1,0) -> 1 | BD34: =IF(OR(ISBLANK(S34),S34=""),1,IF(ISTEXT(S34),1,0)) -> 1 | BE34: =IF(OR(ISBLANK(T34),T34=""),1,IF(ISTEXT(T34),1,0)) -> 1 | BF34: =IF(AND(ISNUMBER(U34),U34>0),1,0) -> 1 | BG34: =IF(AND(ISNUMBER(V34),V34<=TODAY()),1,0) -> 1
A35: =IF(AND(W35=1,X35=1),1,0) -> 1 | B35: =IF(AND(Y35=1,Z35=1,AA35=1,AB35=1,AC35=1,AD35=1,AE35=1,AF35=1,AG35=1,AH35=1,AI35=1,AJ35=1,AK35=1,AL35=1,AM35=1,AN35=1,AO35=1),1,0) -> 1 | C35: =IF(AND(AP35=1,AQ35=1,AR35=1,AS35=1,AT35=1,AU35=1,AV35=1,AW35=1,AX35=1,AY35=1,AZ35=1,BA35=1,BB35=1,BC35=1,BD35=1,BE35=1,BF35=1,BG35=1),1,0) -> 1 | D35: =IF(SUM(A35:C35)<3,1,0) -> 0 | E35: AF0034 | F35: CC | G35: 1000000034 | H35: Paula | I35: Diaz | J35: Ramirez | K35: F | L35: 37034 | M35: paula.diaz34@email.com | N35: 3309866083 | O35: Calle 78 #56-82 | P35: Barranquilla | Q35: Atlántico | R35: 45001 | S35: Activo | T35: Call Center | U35: 95000 | V35: 45192 | W35: =IF(COUNTIF(E$2:E$201,E35)>1,0,1) -> 1 | X35: =IF(COUNTIF(G$2:G$201,G35)>1,0,1) -> 1 | Y35: =IF(E35="",0,1) -> 1 | Z35: =IF(F35="",0,1) -> 1 | AA35: =IF(G35="",0,1) -> 1 | AB35: =IF(H35="",0,1) -> 1 | AC35: =IF(I35="",0,1) -> 1 | AD35: =IF(K35="",0,1) -> 1 | AE35: =IF(L35="",0,1) -> 1 | AF35: =IF(M35="",0,1) -> 1 | AG35: =IF(N35="",0,1) -> 1 | AH35: =IF(O35="",0,1) -> 1 | AI35: =IF(P35="",0,1) -> 1 | AJ35: =IF(Q35="",0,1) -> 1 | AK35: =IF(R35="",0,1) -> 1 | ... AO35: =IF(V35="",0,1) -> 1 | AP35: =IF(AND(LEFT(E35,2)="AF",LEN(E35)=6),1,0) -> 1 | AQ35: =IF(OR(F35="CC",F35="CE",F35="TI",F35="PAS"),1,0) -> 1 | AR35: =IF(AND(ISNUMBER(G35),COUNTIF($G:$G,G35)=1),1,0) -> 1 | AS35: {=IF(AND(H35<>"",SUMPRODUCT(--ISNUMBER(FIND({0;1;2;3;4;5;6;7;8;9},H35)))=0),1,0)} -> 1 | AT35: {=IF(AND(I35<>"",SUMPRODUCT(--ISNUMBER(FIND({0;1;2;3;4;5;6;7;8;9},I35)))=0),1,0)} -> 1 | AU35: {=IF(AND(J35<>"",SUMPRODUCT(--ISNUMBER(FIND({0;1;2;3;4;5;6;7;8;9},J35)))=0),1,0)} -> 1 | AV35: =IF(OR(ISBLANK(K35),K35=""),1,IF(ISTEXT(K35),1,0)) -> 1 | AW35: =IF(AND(ISNUMBER(L35),L35<=TODAY()),1,0) -> 1 | AX35: =IF(AND(ISNUMBER(SEARCH("@",M35)),ISNUMBER(SEARCH(".",M35,SEARCH("@",M35)+2)),NOT(ISNUMBER(SEARCH(" ",M35)))),1,0) -> 1 | AY35: =IF(AND(ISNUMBER(N35),LEN(N35)=10),1,0) -> 1 | AZ35: =IF(LEN(TRIM(O35))>=10,1,0) -> 1 | BA35: =IF(OR(ISBLANK(O35),O35=""),1,IF(ISTEXT(O35),1,0)) -> 1 | BB35: =IF(OR(ISBLANK(P35),P35=""),1,IF(ISTEXT(P35),1,0)) -> 1 | BC35: =IF(AND(ISNUMBER(R35),R35<=TODAY()),1,0) -> 1 | BD35: =IF(OR(ISBLANK(S35),S35=""),1,IF(ISTEXT(S35),1,0)) -> 1 | BE35: =IF(OR(ISBLANK(T35),T35=""),1,IF(ISTEXT(T35),1,0)) -> 1 | BF35: =IF(AND(ISNUMBER(U35),U35>0),1,0) -> 1 | BG35: =IF(AND(ISNUMBER(V35),V35<=TODAY()),1,0) -> 1
A36: =IF(AND(W36=1,X36=1),1,0) -> 1 | B36: =IF(AND(Y36=1,Z36=1,AA36=1,AB36=1,AC36=1,AD36=1,AE36=1,AF36=1,AG36=1,AH36=1,AI36=1,AJ36=1,AK36=1,AL36=1,AM36=1,AN36=1,AO36=1),1,0) -> 1 | C36: =IF(AND(AP36=1,AQ36=1,AR36=1,AS36=1,AT36=1,AU36=1,AV36=1,AW36=1,AX36=1,AY36=1,AZ36=1,BA36=1,BB36=1,BC36=1,BD36=1,BE36=1,BF36=1,BG36=1),1,0) -> 0 | D36: =IF(SUM(A36:C36)<3,1,0) -> 1 | E36: AF0035 | F36: CC | G36: 1000000035 | H36: Juliana | I36: Martinez | J36: Salazar | K36: F | L36: 28043 | M36: juliana.martinez35@email.com | N36: 3733457725 | O36: Calle 45 #52-41 | P36: Envigado | Q36: Antioquia | R36: 46099 | S36: Activo | T36: Web | U36: 85000 | V36: 46389 | W36: =IF(COUNTIF(E$2:E$201,E36)>1,0,1) -> 1 | X36: =IF(COUNTIF(G$2:G$201,G36)>1,0,1) -> 1 | Y36: =IF(E36="",0,1) -> 1 | Z36: =IF(F36="",0,1) -> 1 | AA36: =IF(G36="",0,1) -> 1 | AB36: =IF(H36="",0,1) -> 1 | AC36: =IF(I36="",0,1) -> 1 | AD36: =IF(K36="",0,1) -> 1 | AE36: =IF(L36="",0,1) -> 1 | AF36: =IF(M36="",0,1) -> 1 | AG36: =IF(N36="",0,1) -> 1 | AH36: =IF(O36="",0,1) -> 1 | AI36: =IF(P36="",0,1) -> 1 | AJ36: =IF(Q36="",0,1) -> 1 | AK36: =IF(R36="",0,1) -> 1 | ... AO36: =IF(V36="",0,1) -> 1 | AP36: =IF(AND(LEFT(E36,2)="AF",LEN(E36)=6),1,0) -> 1 | AQ36: =IF(OR(F36="CC",F36="CE",F36="TI",F36="PAS"),1,0) -> 1 | AR36: =IF(AND(ISNUMBER(G36),COUNTIF($G:$G,G36)=1),1,0) -> 1 | AS36: {=IF(AND(H36<>"",SUMPRODUCT(--ISNUMBER(FIND({0;1;2;3;4;5;6;7;8;9},H36)))=0),1,0)} -> 1 | AT36: {=IF(AND(I36<>"",SUMPRODUCT(--ISNUMBER(FIND({0;1;2;3;4;5;6;7;8;9},I36)))=0),1,0)} -> 1 | AU36: {=IF(AND(J36<>"",SUMPRODUCT(--ISNUMBER(FIND({0;1;2;3;4;5;6;7;8;9},J36)))=0),1,0)} -> 1 | AV36: =IF(OR(ISBLANK(K36),K36=""),1,IF(ISTEXT(K36),1,0)) -> 1 | AW36: =IF(AND(ISNUMBER(L36),L36<=TODAY()),1,0) -> 1 | AX36: =IF(AND(ISNUMBER(SEARCH("@",M36)),ISNUMBER(SEARCH(".",M36,SEARCH("@",M36)+2)),NOT(ISNUMBER(SEARCH(" ",M36)))),1,0) -> 1 | AY36: =IF(AND(ISNUMBER(N36),LEN(N36)=10),1,0) -> 1 | AZ36: =IF(LEN(TRIM(O36))>=10,1,0) -> 1 | BA36: =IF(OR(ISBLANK(O36),O36=""),1,IF(ISTEXT(O36),1,0)) -> 1 | BB36: =IF(OR(ISBLANK(P36),P36=""),1,IF(ISTEXT(P36),1,0)) -> 1 | BC36: =IF(AND(ISNUMBER(R36),R36<=TODAY()),1,0) -> 1 | BD36: =IF(OR(ISBLANK(S36),S36=""),1,IF(ISTEXT(S36),1,0)) -> 1 | BE36: =IF(OR(ISBLANK(T36),T36=""),1,IF(ISTEXT(T36),1,0)) -> 1 | BF36: =IF(AND(ISNUMBER(U36),U36>0),1,0) -> 1 | BG36: =IF(AND(ISNUMBER(V36),V36<=TODAY()),1,0) -> 0
A37: =IF(AND(W37=1,X37=1),1,0) -> 1 | B37: =IF(AND(Y37=1,Z37=1,AA37=1,AB37=1,AC37=1,AD37=1,AE37=1,AF37=1,AG37=1,AH37=1,AI37=1,AJ37=1,AK37=1,AL37=1,AM37=1,AN37=1,AO37=1),1,0) -> 1 | C37: =IF(AND(AP37=1,AQ37=1,AR37=1,AS37=1,AT37=1,AU37=1,AV37=1,AW37=1,AX37=1,AY37=1,AZ37=1,BA37=1,BB37=1,BC37=1,BD37=1,BE37=1,BF37=1,BG37=1),1,0) -> 1 | D37: =IF(SUM(A37:C37)<3,1,0) -> 0 | E37: AF0036 | F37: TI | G37: 1000000036 | H37: Paula | I37: Torres | J37: Restrepo | K37: F | L37: 32741 | M37: paula.torres36@email.com | N37: 3730613146 | O37: Calle 102 #71-54 | P37: Barranquilla | Q37: Atlántico | R37: 45661 | S37: Suspendido | T37: Presencial | U37: 95000 | V37: 45762 | W37: =IF(COUNTIF(E$2:E$201,E37)>1,0,1) -> 1 | X37: =IF(COUNTIF(G$2:G$201,G37)>1,0,1) -> 1 | Y37: =IF(E37="",0,1) -> 1 | Z37: =IF(F37="",0,1) -> 1 | AA37: =IF(G37="",0,1) -> 1 | AB37: =IF(H37="",0,1) -> 1 | AC37: =IF(I37="",0,1) -> 1 | AD37: =IF(K37="",0,1) -> 1 | AE37: =IF(L37="",0,1) -> 1 | AF37: =IF(M37="",0,1) -> 1 | AG37: =IF(N37="",0,1) -> 1 | AH37: =IF(O37="",0,1) -> 1 | AI37: =IF(P37="",0,1) -> 1 | AJ37: =IF(Q37="",0,1) -> 1 | AK37: =IF(R37="",0,1) -> 1 | ... AO37: =IF(V37="",0,1) -> 1 | AP37: =IF(AND(LEFT(E37,2)="AF",LEN(E37)=6),1,0) -> 1 | AQ37: =IF(OR(F37="CC",F37="CE",F37="TI",F37="PAS"),1,0) -> 1 | AR37: =IF(AND(ISNUMBER(G37),COUNTIF($G:$G,G37)=1),1,0) -> 1 | AS37: {=IF(AND(H37<>"",SUMPRODUCT(--ISNUMBER(FIND({0;1;2;3;4;5;6;7;8;9},H37)))=0),1,0)} -> 1 | AT37: {=IF(AND(I37<>"",SUMPRODUCT(--ISNUMBER(FIND({0;1;2;3;4;5;6;7;8;9},I37)))=0),1,0)} -> 1 | AU37: {=IF(AND(J37<>"",SUMPRODUCT(--ISNUMBER(FIND({0;1;2;3;4;5;6;7;8;9},J37)))=0),1,0)} -> 1 | AV37: =IF(OR(ISBLANK(K37),K37=""),1,IF(ISTEXT(K37),1,0)) -> 1 | AW37: =IF(AND(ISNUMBER(L37),L37<=TODAY()),1,0) -> 1 | AX37: =IF(AND(ISNUMBER(SEARCH("@",M37)),ISNUMBER(SEARCH(".",M37,SEARCH("@",M37)+2)),NOT(ISNUMBER(SEARCH(" ",M37)))),1,0) -> 1 | AY37: =IF(AND(ISNUMBER(N37),LEN(N37)=10),1,0) -> 1 | AZ37: =IF(LEN(TRIM(O37))>=10,1,0) -> 1 | BA37: =IF(OR(ISBLANK(O37),O37=""),1,IF(ISTEXT(O37),1,0)) -> 1 | BB37: =IF(OR(ISBLANK(P37),P37=""),1,IF(ISTEXT(P37),1,0)) -> 1 | BC37: =IF(AND(ISNUMBER(R37),R37<=TODAY()),1,0) -> 1 | BD37: =IF(OR(ISBLANK(S37),S37=""),1,IF(ISTEXT(S37),1,0)) -> 1 | BE37: =IF(OR(ISBLANK(T37),T37=""),1,IF(ISTEXT(T37),1,0)) -> 1 | BF37: =IF(AND(ISNUMBER(U37),U37>0),1,0) -> 1 | BG37: =IF(AND(ISNUMBER(V37),V37<=TODAY()),1,0) -> 1
A38: =IF(AND(W38=1,X38=1),1,0) -> 1 | B38: =IF(AND(Y38=1,Z38=1,AA38=1,AB38=1,AC38=1,AD38=1,AE38=1,AF38=1,AG38=1,AH38=1,AI38=1,AJ38=1,AK38=1,AL38=1,AM38=1,AN38=1,AO38=1),1,0) -> 0 | C38: =IF(AND(AP38=1,AQ38=1,AR38=1,AS38=1,AT38=1,AU38=1,AV38=1,AW38=1,AX38=1,AY38=1,AZ38=1,BA38=1,BB38=1,BC38=1,BD38=1,BE38=1,BF38=1,BG38=1),1,0) -> 0 | D38: =IF(SUM(A38:C38)<3,1,0) -> 1 | E38: AF0037 | F38: CC | G38: 1000000037 | I38: Moreno | J38: Herrera | K38: M | L38: 28165 | M38: javier.moreno37@email.com | N38: 3449274980 | O38: Calle 41 #19-11 | P38: Envigado | Q38: Antioquia | R38: 46033 | S38: Retirado | T38: Web | U38: 90000 | V38: 46297 | W38: =IF(COUNTIF(E$2:E$201,E38)>1,0,1) -> 1 | X38: =IF(COUNTIF(G$2:G$201,G38)>1,0,1) -> 1 | Y38: =IF(E38="",0,1) -> 1 | Z38: =IF(F38="",0,1) -> 1 | AA38: =IF(G38="",0,1) -> 1 | AB38: =IF(H38="",0,1) -> 0 | AC38: =IF(I38="",0,1) -> 1 | AD38: =IF(K38="",0,1) -> 1 | AE38: =IF(L38="",0,1) -> 1 | AF38: =IF(M38="",0,1) -> 1 | AG38: =IF(N38="",0,1) -> 1 | AH38: =IF(O38="",0,1) -> 1 | AI38: =IF(P38="",0,1) -> 1 | AJ38: =IF(Q38="",0,1) -> 1 | AK38: =IF(R38="",0,1) -> 1 | ... AO38: =IF(V38="",0,1) -> 1 | AP38: =IF(AND(LEFT(E38,2)="AF",LEN(E38)=6),1,0) -> 1 | AQ38: =IF(OR(F38="CC",F38="CE",F38="TI",F38="PAS"),1,0) -> 1 | AR38: =IF(AND(ISNUMBER(G38),COUNTIF($G:$G,G38)=1),1,0) -> 1 | AS38: {=IF(AND(H38<>"",SUMPRODUCT(--ISNUMBER(FIND({0;1;2;3;4;5;6;7;8;9},H38)))=0),1,0)} -> 0 | AT38: {=IF(AND(I38<>"",SUMPRODUCT(--ISNUMBER(FIND({0;1;2;3;4;5;6;7;8;9},I38)))=0),1,0)} -> 1 | AU38: {=IF(AND(J38<>"",SUMPRODUCT(--ISNUMBER(FIND({0;1;2;3;4;5;6;7;8;9},J38)))=0),1,0)} -> 1 | AV38: =IF(OR(ISBLANK(K38),K38=""),1,IF(ISTEXT(K38),1,0)) -> 1 | AW38: =IF(AND(ISNUMBER(L38),L38<=TODAY()),1,0) -> 1 | AX38: =IF(AND(ISNUMBER(SEARCH("@",M38)),ISNUMBER(SEARCH(".",M38,SEARCH("@",M38)+2)),NOT(ISNUMBER(SEARCH(" ",M38)))),1,0) -> 1 | AY38: =IF(AND(ISNUMBER(N38),LEN(N38)=10),1,0) -> 1 | AZ38: =IF(LEN(TRIM(O38))>=10,1,0) -> 1 | BA38: =IF(OR(ISBLANK(O38),O38=""),1,IF(ISTEXT(O38),1,0)) -> 1 | BB38: =IF(OR(ISBLANK(P38),P38=""),1,IF(ISTEXT(P38),1,0)) -> 1 | BC38: =IF(AND(ISNUMBER(R38),R38<=TODAY()),1,0) -> 1 | BD38: =IF(OR(ISBLANK(S38),S38=""),1,IF(ISTEXT(S38),1,0)) -> 1 | BE38: =IF(OR(ISBLANK(T38),T38=""),1,IF(ISTEXT(T38),1,0)) -> 1 | BF38: =IF(AND(ISNUMBER(U38),U38>0),1,0) -> 1 | BG38: =IF(AND(ISNUMBER(V38),V38<=TODAY()),1,0) -> 0
A39: =IF(AND(W39=1,X39=1),1,0) -> 1 | B39: =IF(AND(Y39=1,Z39=1,AA39=1,AB39=1,AC39=1,AD39=1,AE39=1,AF39=1,AG39=1,AH39=1,AI39=1,AJ39=1,AK39=1,AL39=1,AM39=1,AN39=1,AO39=1),1,0) -> 1 | C39: =IF(AND(AP39=1,AQ39=1,AR39=1,AS39=1,AT39=1,AU39=1,AV39=1,AW39=1,AX39=1,AY39=1,AZ39=1,BA39=1,BB39=1,BC39=1,BD39=1,BE39=1,BF39=1,BG39=1),1,0) -> 1 | D39: =IF(SUM(A39:C39)<3,1,0) -> 0 | E39: AF0038 | F39: CC | G39: 1000000038 | H39: Diana | I39: Leon | J39: Castro | K39: F | L39: 34717 | M39: diana.leon38@email.com | N39: 3363938275 | O39: Calle 81 #29-57 | P39: Barranquilla | Q39: Atlántico | R39: 45175 | S39: Suspendido | T39: Web | U39: 90000 | V39: 45439 | W39: =IF(COUNTIF(E$2:E$201,E39)>1,0,1) -> 1 | X39: =IF(COUNTIF(G$2:G$201,G39)>1,0,1) -> 1 | Y39: =IF(E39="",0,1) -> 1 | Z39: =IF(F39="",0,1) -> 1 | AA39: =IF(G39="",0,1) -> 1 | AB39: =IF(H39="",0,1) -> 1 | AC39: =IF(I39="",0,1) -> 1 | AD39: =IF(K39="",0,1) -> 1 | AE39: =IF(L39="",0,1) -> 1 | AF39: =IF(M39="",0,1) -> 1 | AG39: =IF(N39="",0,1) -> 1 | AH39: =IF(O39="",0,1) -> 1 | AI39: =IF(P39="",0,1) -> 1 | AJ39: =IF(Q39="",0,1) -> 1 | AK39: =IF(R39="",0,1) -> 1 | ... AO39: =IF(V39="",0,1) -> 1 | AP39: =IF(AND(LEFT(E39,2)="AF",LEN(E39)=6),1,0) -> 1 | AQ39: =IF(OR(F39="CC",F39="CE",F39="TI",F39="PAS"),1,0) -> 1 | AR39: =IF(AND(ISNUMBER(G39),COUNTIF($G:$G,G39)=1),1,0) -> 1 | AS39: {=IF(AND(H39<>"",SUMPRODUCT(--ISNUMBER(FIND({0;1;2;3;4;5;6;7;8;9},H39)))=0),1,0)} -> 1 | AT39: {=IF(AND(I39<>"",SUMPRODUCT(--ISNUMBER(FIND({0;1;2;3;4;5;6;7;8;9},I39)))=0),1,0)} -> 1 | AU39: {=IF(AND(J39<>"",SUMPRODUCT(--ISNUMBER(FIND({0;1;2;3;4;5;6;7;8;9},J39)))=0),1,0)} -> 1 | AV39: =IF(OR(ISBLANK(K39),K39=""),1,IF(ISTEXT(K39),1,0)) -> 1 | AW39: =IF(AND(ISNUMBER(L39),L39<=TODAY()),1,0) -> 1 | AX39: =IF(AND(ISNUMBER(SEARCH("@",M39)),ISNUMBER(SEARCH(".",M39,SEARCH("@",M39)+2)),NOT(ISNUMBER(SEARCH(" ",M39)))),1,0) -> 1 | AY39: =IF(AND(ISNUMBER(N39),LEN(N39)=10),1,0) -> 1 | AZ39: =IF(LEN(TRIM(O39))>=10,1,0) -> 1 | BA39: =IF(OR(ISBLANK(O39),O39=""),1,IF(ISTEXT(O39),1,0)) -> 1 | BB39: =IF(OR(ISBLANK(P39),P39=""),1,IF(ISTEXT(P39),1,0)) -> 1 | BC39: =IF(AND(ISNUMBER(R39),R39<=TODAY()),1,0) -> 1 | BD39: =IF(OR(ISBLANK(S39),S39=""),1,IF(ISTEXT(S39),1,0)) -> 1 | BE39: =IF(OR(ISBLANK(T39),T39=""),1,IF(ISTEXT(T39),1,0)) -> 1 | BF39: =IF(AND(ISNUMBER(U39),U39>0),1,0) -> 1 | BG39: =IF(AND(ISNUMBER(V39),V39<=TODAY()),1,0) -> 1
A40: =IF(AND(W40=1,X40=1),1,0) -> 1 | B40: =IF(AND(Y40=1,Z40=1,AA40=1,AB40=1,AC40=1,AD40=1,AE40=1,AF40=1,AG40=1,AH40=1,AI40=1,AJ40=1,AK40=1,AL40=1,AM40=1,AN40=1,AO40=1),1,0) -> 1 | C40: =IF(AND(AP40=1,AQ40=1,AR40=1,AS40=1,AT40=1,AU40=1,AV40=1,AW40=1,AX40=1,AY40=1,AZ40=1,BA40=1,BB40=1,BC40=1,BD40=1,BE40=1,BF40=1,BG40=1),1,0) -> 1 | D40: =IF(SUM(A40:C40)<3,1,0) -> 0 | E40: AF0039 | F40: CC | G40: 1000000039 | H40: Ana | I40: Munoz | J40: Vargas | K40: F | L40: 30858 | M40: ana.munoz39@email.com | N40: 3831258313 | O40: Calle 60 #22-8 | P40: Bucaramanga | Q40: Santander | R40: 45806 | S40: Suspendido | T40: Web | U40: 90000 | V40: 46140 | W40: =IF(COUNTIF(E$2:E$201,E40)>1,0,1) -> 1 | X40: =IF(COUNTIF(G$2:G$201,G40)>1,0,1) -> 1 | Y40: =IF(E40="",0,1) -> 1 | Z40: =IF(F40="",0,1) -> 1 | AA40: =IF(G40="",0,1) -> 1 | AB40: =IF(H40="",0,1) -> 1 | AC40: =IF(I40="",0,1) -> 1 | AD40: =IF(K40="",0,1) -> 1 | AE40: =IF(L40="",0,1) -> 1 | AF40: =IF(M40="",0,1) -> 1 | AG40: =IF(N40="",0,1) -> 1 | AH40: =IF(O40="",0,1) -> 1 | AI40: =IF(P40="",0,1) -> 1 | AJ40: =IF(Q40="",0,1) -> 1 | AK40: =IF(R40="",0,1) -> 1 | ... AO40: =IF(V40="",0,1) -> 1 | AP40: =IF(AND(LEFT(E40,2)="AF",LEN(E40)=6),1,0) -> 1 | AQ40: =IF(OR(F40="CC",F40="CE",F40="TI",F40="PAS"),1,0) -> 1 | AR40: =IF(AND(ISNUMBER(G40),COUNTIF($G:$G,G40)=1),1,0) -> 1 | AS40: {=IF(AND(H40<>"",SUMPRODUCT(--ISNUMBER(FIND({0;1;2;3;4;5;6;7;8;9},H40)))=0),1,0)} -> 1 | AT40: {=IF(AND(I40<>"",SUMPRODUCT(--ISNUMBER(FIND({0;1;2;3;4;5;6;7;8;9},I40)))=0),1,0)} -> 1 | AU40: {=IF(AND(J40<>"",SUMPRODUCT(--ISNUMBER(FIND({0;1;2;3;4;5;6;7;8;9},J40)))=0),1,0)} -> 1 | AV40: =IF(OR(ISBLANK(K40),K40=""),1,IF(ISTEXT(K40),1,0)) -> 1 | AW40: =IF(AND(ISNUMBER(L40),L40<=TODAY()),1,0) -> 1 | AX40: =IF(AND(ISNUMBER(SEARCH("@",M40)),ISNUMBER(SEARCH(".",M40,SEARCH("@",M40)+2)),NOT(ISNUMBER(SEARCH(" ",M40)))),1,0) -> 1 | AY40: =IF(AND(ISNUMBER(N40),LEN(N40)=10),1,0) -> 1 | AZ40: =IF(LEN(TRIM(O40))>=10,1,0) -> 1 | BA40: =IF(OR(ISBLANK(O40),O40=""),1,IF(ISTEXT(O40),1,0)) -> 1 | BB40: =IF(OR(ISBLANK(P40),P40=""),1,IF(ISTEXT(P40),1,0)) -> 1 | BC40: =IF(AND(ISNUMBER(R40),R40<=TODAY()),1,0) -> 1 | BD40: =IF(OR(ISBLANK(S40),S40=""),1,IF(ISTEXT(S40),1,0)) -> 1 | BE40: =IF(OR(ISBLANK(T40),T40=""),1,IF(ISTEXT(T40),1,0)) -> 1 | BF40: =IF(AND(ISNUMBER(U40),U40>0),1,0) -> 1 | BG40: =IF(AND(ISNUMBER(V40),V40<=TODAY()),1,0) -> 1
A41: =IF(AND(W41=1,X41=1),1,0) -> 1 | B41: =IF(AND(Y41=1,Z41=1,AA41=1,AB41=1,AC41=1,AD41=1,AE41=1,AF41=1,AG41=1,AH41=1,AI41=1,AJ41=1,AK41=1,AL41=1,AM41=1,AN41=1,AO41=1),1,0) -> 1 | C41: =IF(AND(AP41=1,AQ41=1,AR41=1,AS41=1,AT41=1,AU41=1,AV41=1,AW41=1,AX41=1,AY41=1,AZ41=1,BA41=1,BB41=1,BC41=1,BD41=1,BE41=1,BF41=1,BG41=1),1,0) -> 1 | D41: =IF(SUM(A41:C41)<3,1,0) -> 0 | E41: AF0040 | F41: TI | G41: 1000000040 | H41: Sergio | I41: Rodriguez | J41: Moreno | K41: M | L41: 29224 | M41: sergio.rodriguez40@email.com | N41: 3251980719 | O41: Calle 63 #98-59 | P41: Manizales | Q41: Caldas | R41: 45730 | S41: Activo | T41: Web | U41: 85000 | V41: 45759 | W41: =IF(COUNTIF(E$2:E$201,E41)>1,0,1) -> 1 | X41: =IF(COUNTIF(G$2:G$201,G41)>1,0,1) -> 1 | Y41: =IF(E41="",0,1) -> 1 | Z41: =IF(F41="",0,1) -> 1 | AA41: =IF(G41="",0,1) -> 1 | AB41: =IF(H41="",0,1) -> 1 | AC41: =IF(I41="",0,1) -> 1 | AD41: =IF(K41="",0,1) -> 1 | AE41: =IF(L41="",0,1) -> 1 | AF41: =IF(M41="",0,1) -> 1 | AG41: =IF(N41="",0,1) -> 1 | AH41: =IF(O41="",0,1) -> 1 | AI41: =IF(P41="",0,1) -> 1 | AJ41: =IF(Q41="",0,1) -> 1 | AK41: =IF(R41="",0,1) -> 1 | ... AO41: =IF(V41="",0,1) -> 1 | AP41: =IF(AND(LEFT(E41,2)="AF",LEN(E41)=6),1,0) -> 1 | AQ41: =IF(OR(F41="CC",F41="CE",F41="TI",F41="PAS"),1,0) -> 1 | AR41: =IF(AND(ISNUMBER(G41),COUNTIF($G:$G,G41)=1),1,0) -> 1 | AS41: {=IF(AND(H41<>"",SUMPRODUCT(--ISNUMBER(FIND({0;1;2;3;4;5;6;7;8;9},H41)))=0),1,0)} -> 1 | AT41: {=IF(AND(I41<>"",SUMPRODUCT(--ISNUMBER(FIND({0;1;2;3;4;5;6;7;8;9},I41)))=0),1,0)} -> 1 | AU41: {=IF(AND(J41<>"",SUMPRODUCT(--ISNUMBER(FIND({0;1;2;3;4;5;6;7;8;9},J41)))=0),1,0)} -> 1 | AV41: =IF(OR(ISBLANK(K41),K41=""),1,IF(ISTEXT(K41),1,0)) -> 1 | AW41: =IF(AND(ISNUMBER(L41),L41<=TODAY()),1,0) -> 1 | AX41: =IF(AND(ISNUMBER(SEARCH("@",M41)),ISNUMBER(SEARCH(".",M41,SEARCH("@",M41)+2)),NOT(ISNUMBER(SEARCH(" ",M41)))),1,0) -> 1 | AY41: =IF(AND(ISNUMBER(N41),LEN(N41)=10),1,0) -> 1 | AZ41: =IF(LEN(TRIM(O41))>=10,1,0) -> 1 | BA41: =IF(OR(ISBLANK(O41),O41=""),1,IF(ISTEXT(O41),1,0)) -> 1 | BB41: =IF(OR(ISBLANK(P41),P41=""),1,IF(ISTEXT(P41),1,0)) -> 1 | BC41: =IF(AND(ISNUMBER(R41),R41<=TODAY()),1,0) -> 1 | BD41: =IF(OR(ISBLANK(S41),S41=""),1,IF(ISTEXT(S41),1,0)) -> 1 | BE41: =IF(OR(ISBLANK(T41),T41=""),1,IF(ISTEXT(T41),1,0)) -> 1 | BF41: =IF(AND(ISNUMBER(U41),U41>0),1,0) -> 1 | BG41: =IF(AND(ISNUMBER(V41),V41<=TODAY()),1,0) -> 1
A42: =IF(AND(W42=1,X42=1),1,0) -> 1 | B42: =IF(AND(Y42=1,Z42=1,AA42=1,AB42=1,AC42=1,AD42=1,AE42=1,AF42=1,AG42=1,AH42=1,AI42=1,AJ42=1,AK42=1,AL42=1,AM42=1,AN42=1,AO42=1),1,0) -> 1 | C42: =IF(AND(AP42=1,AQ42=1,AR42=1,AS42=1,AT42=1,AU42=1,AV42=1,AW42=1,AX42=1,AY42=1,AZ42=1,BA42=1,BB42=1,BC42=1,BD42=1,BE42=1,BF42=1,BG42=1),1,0) -> 1 | D42: =IF(SUM(A42:C42)<3,1,0) -> 0 | E42: AF0041 | F42: CC | G42: 1000000041 | H42: Laura | I42: Leon | J42: Herrera | K42: F | L42: 36008 | M42: laura.leon41@email.com | N42: 3697916326 | O42: Calle 24 #43-49 | P42: Bucaramanga | Q42: Santander | R42: 45155 | S42: Retirado | T42: Presencial | U42: 75000 | V42: 45230 | W42: =IF(COUNTIF(E$2:E$201,E42)>1,0,1) -> 1 | X42: =IF(COUNTIF(G$2:G$201,G42)>1,0,1) -> 1 | Y42: =IF(E42="",0,1) -> 1 | Z42: =IF(F42="",0,1) -> 1 | AA42: =IF(G42="",0,1) -> 1 | AB42: =IF(H42="",0,1) -> 1 | AC42: =IF(I42="",0,1) -> 1 | AD42: =IF(K42="",0,1) -> 1 | AE42: =IF(L42="",0,1) -> 1 | AF42: =IF(M42="",0,1) -> 1 | AG42: =IF(N42="",0,1) -> 1 | AH42: =IF(O42="",0,1) -> 1 | AI42: =IF(P42="",0,1) -> 1 | AJ42: =IF(Q42="",0,1) -> 1 | AK42: =IF(R42="",0,1) -> 1 | ... AO42: =IF(V42="",0,1) -> 1 | AP42: =IF(AND(LEFT(E42,2)="AF",LEN(E42)=6),1,0) -> 1 | AQ42: =IF(OR(F42="CC",F42="CE",F42="TI",F42="PAS"),1,0) -> 1 | AR42: =IF(AND(ISNUMBER(G42),COUNTIF($G:$G,G42)=1),1,0) -> 1 | AS42: {=IF(AND(H42<>"",SUMPRODUCT(--ISNUMBER(FIND({0;1;2;3;4;5;6;7;8;9},H42)))=0),1,0)} -> 1 | AT42: {=IF(AND(I42<>"",SUMPRODUCT(--ISNUMBER(FIND({0;1;2;3;4;5;6;7;8;9},I42)))=0),1,0)} -> 1 | AU42: {=IF(AND(J42<>"",SUMPRODUCT(--ISNUMBER(FIND({0;1;2;3;4;5;6;7;8;9},J42)))=0),1,0)} -> 1 | AV42: =IF(OR(ISBLANK(K42),K42=""),1,IF(ISTEXT(K42),1,0)) -> 1 | AW42: =IF(AND(ISNUMBER(L42),L42<=TODAY()),1,0) -> 1 | AX42: =IF(AND(ISNUMBER(SEARCH("@",M42)),ISNUMBER(SEARCH(".",M42,SEARCH("@",M42)+2)),NOT(ISNUMBER(SEARCH(" ",M42)))),1,0) -> 1 | AY42: =IF(AND(ISNUMBER(N42),LEN(N42)=10),1,0) -> 1 | AZ42: =IF(LEN(TRIM(O42))>=10,1,0) -> 1 | BA42: =IF(OR(ISBLANK(O42),O42=""),1,IF(ISTEXT(O42),1,0)) -> 1 | BB42: =IF(OR(ISBLANK(P42),P42=""),1,IF(ISTEXT(P42),1,0)) -> 1 | BC42: =IF(AND(ISNUMBER(R42),R42<=TODAY()),1,0) -> 1 | BD42: =IF(OR(ISBLANK(S42),S42=""),1,IF(ISTEXT(S42),1,0)) -> 1 | BE42: =IF(OR(ISBLANK(T42),T42=""),1,IF(ISTEXT(T42),1,0)) -> 1 | BF42: =IF(AND(ISNUMBER(U42),U42>0),1,0) -> 1 | BG42: =IF(AND(ISNUMBER(V42),V42<=TODAY()),1,0) -> 1
A43: =IF(AND(W43=1,X43=1),1,0) -> 1 | B43: =IF(AND(Y43=1,Z43=1,AA43=1,AB43=1,AC43=1,AD43=1,AE43=1,AF43=1,AG43=1,AH43=1,AI43=1,AJ43=1,AK43=1,AL43=1,AM43=1,AN43=1,AO43=1),1,0) -> 1 | C43: =IF(AND(AP43=1,AQ43=1,AR43=1,AS43=1,AT43=1,AU43=1,AV43=1,AW43=1,AX43=1,AY43=1,AZ43=1,BA43=1,BB43=1,BC43=1,BD43=1,BE43=1,BF43=1,BG43=1),1,0) -> 0 | D43: =IF(SUM(A43:C43)<3,1,0) -> 1 | E43: AF0042 | F43: CE | G43: 1000000042 | H43: Ricardo | I43: Moreno | J43: Leon | K43: M | L43: 30872 | M43: ricardo.moreno42@email.com | N43: 12345 | O43: Calle 56 #88-84 | P43: Medellín | Q43: Antioquia | R43: 45789 | S43: Retirado | T43: Web | U43: 85000 | V43: 46041 | W43: =IF(COUNTIF(E$2:E$201,E43)>1,0,1) -> 1 | X43: =IF(COUNTIF(G$2:G$201,G43)>1,0,1) -> 1 | Y43: =IF(E43="",0,1) -> 1 | Z43: =IF(F43="",0,1) -> 1 | AA43: =IF(G43="",0,1) -> 1 | AB43: =IF(H43="",0,1) -> 1 | AC43: =IF(I43="",0,1) -> 1 | AD43: =IF(K43="",0,1) -> 1 | AE43: =IF(L43="",0,1) -> 1 | AF43: =IF(M43="",0,1) -> 1 | AG43: =IF(N43="",0,1) -> 1 | AH43: =IF(O43="",0,1) -> 1 | AI43: =IF(P43="",0,1) -> 1 | AJ43: =IF(Q43="",0,1) -> 1 | AK43: =IF(R43="",0,1) -> 1 | ... AO43: =IF(V43="",0,1) -> 1 | AP43: =IF(AND(LEFT(E43,2)="AF",LEN(E43)=6),1,0) -> 1 | AQ43: =IF(OR(F43="CC",F43="CE",F43="TI",F43="PAS"),1,0) -> 1 | AR43: =IF(AND(ISNUMBER(G43),COUNTIF($G:$G,G43)=1),1,0) -> 1 | AS43: {=IF(AND(H43<>"",SUMPRODUCT(--ISNUMBER(FIND({0;1;2;3;4;5;6;7;8;9},H43)))=0),1,0)} -> 1 | AT43: {=IF(AND(I43<>"",SUMPRODUCT(--ISNUMBER(FIND({0;1;2;3;4;5;6;7;8;9},I43)))=0),1,0)} -> 1 | AU43: {=IF(AND(J43<>"",SUMPRODUCT(--ISNUMBER(FIND({0;1;2;3;4;5;6;7;8;9},J43)))=0),1,0)} -> 1 | AV43: =IF(OR(ISBLANK(K43),K43=""),1,IF(ISTEXT(K43),1,0)) -> 1 | AW43: =IF(AND(ISNUMBER(L43),L43<=TODAY()),1,0) -> 1 | AX43: =IF(AND(ISNUMBER(SEARCH("@",M43)),ISNUMBER(SEARCH(".",M43,SEARCH("@",M43)+2)),NOT(ISNUMBER(SEARCH(" ",M43)))),1,0) -> 1 | AY43: =IF(AND(ISNUMBER(N43),LEN(N43)=10),1,0) -> 0 | AZ43: =IF(LEN(TRIM(O43))>=10,1,0) -> 1 | BA43: =IF(OR(ISBLANK(O43),O43=""),1,IF(ISTEXT(O43),1,0)) -> 1 | BB43: =IF(OR(ISBLANK(P43),P43=""),1,IF(ISTEXT(P43),1,0)) -> 1 | BC43: =IF(AND(ISNUMBER(R43),R43<=TODAY()),1,0) -> 1 | BD43: =IF(OR(ISBLANK(S43),S43=""),1,IF(ISTEXT(S43),1,0)) -> 1 | BE43: =IF(OR(ISBLANK(T43),T43=""),1,IF(ISTEXT(T43),1,0)) -> 1 | BF43: =IF(AND(ISNUMBER(U43),U43>0),1,0) -> 1 | BG43: =IF(AND(ISNUMBER(V43),V43<=TODAY()),1,0) -> 1
A44: =IF(AND(W44=1,X44=1),1,0) -> 1 | B44: =IF(AND(Y44=1,Z44=1,AA44=1,AB44=1,AC44=1,AD44=1,AE44=1,AF44=1,AG44=1,AH44=1,AI44=1,AJ44=1,AK44=1,AL44=1,AM44=1,AN44=1,AO44=1),1,0) -> 1 | C44: =IF(AND(AP44=1,AQ44=1,AR44=1,AS44=1,AT44=1,AU44=1,AV44=1,AW44=1,AX44=1,AY44=1,AZ44=1,BA44=1,BB44=1,BC44=1,BD44=1,BE44=1,BF44=1,BG44=1),1,0) -> 1 | D44: =IF(SUM(A44:C44)<3,1,0) -> 0 | E44: AF0043 | F44: CC | G44: 1000000043 | H44: Miguel | I44: Ortiz | J44: Valencia | K44: M | L44: 29452 | M44: miguel.ortiz43@email.com | N44: 3450132719 | O44: Calle 99 #23-17 | P44: Envigado | Q44: Antioquia | R44: 44952 | S44: Activo | T44: Presencial | U44: 90000 | V44: 45062 | W44: =IF(COUNTIF(E$2:E$201,E44)>1,0,1) -> 1 | X44: =IF(COUNTIF(G$2:G$201,G44)>1,0,1) -> 1 | Y44: =IF(E44="",0,1) -> 1 | Z44: =IF(F44="",0,1) -> 1 | AA44: =IF(G44="",0,1) -> 1 | AB44: =IF(H44="",0,1) -> 1 | AC44: =IF(I44="",0,1) -> 1 | AD44: =IF(K44="",0,1) -> 1 | AE44: =IF(L44="",0,1) -> 1 | AF44: =IF(M44="",0,1) -> 1 | AG44: =IF(N44="",0,1) -> 1 | AH44: =IF(O44="",0,1) -> 1 | AI44: =IF(P44="",0,1) -> 1 | AJ44: =IF(Q44="",0,1) -> 1 | AK44: =IF(R44="",0,1) -> 1 | ... AO44: =IF(V44="",0,1) -> 1 | AP44: =IF(AND(LEFT(E44,2)="AF",LEN(E44)=6),1,0) -> 1 | AQ44: =IF(OR(F44="CC",F44="CE",F44="TI",F44="PAS"),1,0) -> 1 | AR44: =IF(AND(ISNUMBER(G44),COUNTIF($G:$G,G44)=1),1,0) -> 1 | AS44: {=IF(AND(H44<>"",SUMPRODUCT(--ISNUMBER(FIND({0;1;2;3;4;5;6;7;8;9},H44)))=0),1,0)} -> 1 | AT44: {=IF(AND(I44<>"",SUMPRODUCT(--ISNUMBER(FIND({0;1;2;3;4;5;6;7;8;9},I44)))=0),1,0)} -> 1 | AU44: {=IF(AND(J44<>"",SUMPRODUCT(--ISNUMBER(FIND({0;1;2;3;4;5;6;7;8;9},J44)))=0),1,0)} -> 1 | AV44: =IF(OR(ISBLANK(K44),K44=""),1,IF(ISTEXT(K44),1,0)) -> 1 | AW44: =IF(AND(ISNUMBER(L44),L44<=TODAY()),1,0) -> 1 | AX44: =IF(AND(ISNUMBER(SEARCH("@",M44)),ISNUMBER(SEARCH(".",M44,SEARCH("@",M44)+2)),NOT(ISNUMBER(SEARCH(" ",M44)))),1,0) -> 1 | AY44: =IF(AND(ISNUMBER(N44),LEN(N44)=10),1,0) -> 1 | AZ44: =IF(LEN(TRIM(O44))>=10,1,0) -> 1 | BA44: =IF(OR(ISBLANK(O44),O44=""),1,IF(ISTEXT(O44),1,0)) -> 1 | BB44: =IF(OR(ISBLANK(P44),P44=""),1,IF(ISTEXT(P44),1,0)) -> 1 | BC44: =IF(AND(ISNUMBER(R44),R44<=TODAY()),1,0) -> 1 | BD44: =IF(OR(ISBLANK(S44),S44=""),1,IF(ISTEXT(S44),1,0)) -> 1 | BE44: =IF(OR(ISBLANK(T44),T44=""),1,IF(ISTEXT(T44),1,0)) -> 1 | BF44: =IF(AND(ISNUMBER(U44),U44>0),1,0) -> 1 | BG44: =IF(AND(ISNUMBER(V44),V44<=TODAY()),1,0) -> 1
A45: =IF(AND(W45=1,X45=1),1,0) -> 1 | B45: =IF(AND(Y45=1,Z45=1,AA45=1,AB45=1,AC45=1,AD45=1,AE45=1,AF45=1,AG45=1,AH45=1,AI45=1,AJ45=1,AK45=1,AL45=1,AM45=1,AN45=1,AO45=1),1,0) -> 1 | C45: =IF(AND(AP45=1,AQ45=1,AR45=1,AS45=1,AT45=1,AU45=1,AV45=1,AW45=1,AX45=1,AY45=1,AZ45=1,BA45=1,BB45=1,BC45=1,BD45=1,BE45=1,BF45=1,BG45=1),1,0) -> 1 | D45: =IF(SUM(A45:C45)<3,1,0) -> 0 | E45: AF0044 | F45: TI | G45: 1000000044 | H45: Felipe | I45: Castro | J45: Munoz | K45: M | L45: 31396 | M45: felipe.castro44@email.com | N45: 3893163899 | O45: Calle 94 #14-14 | P45: Bucaramanga | Q45: Santander | R45: 44730 | S45: Activo | T45: Web | U45: 90000 | V45: 44882 | W45: =IF(COUNTIF(E$2:E$201,E45)>1,0,1) -> 1 | X45: =IF(COUNTIF(G$2:G$201,G45)>1,0,1) -> 1 | Y45: =IF(E45="",0,1) -> 1 | Z45: =IF(F45="",0,1) -> 1 | AA45: =IF(G45="",0,1) -> 1 | AB45: =IF(H45="",0,1) -> 1 | AC45: =IF(I45="",0,1) -> 1 | AD45: =IF(K45="",0,1) -> 1 | AE45: =IF(L45="",0,1) -> 1 | AF45: =IF(M45="",0,1) -> 1 | AG45: =IF(N45="",0,1) -> 1 | AH45: =IF(O45="",0,1) -> 1 | AI45: =IF(P45="",0,1) -> 1 | AJ45: =IF(Q45="",0,1) -> 1 | AK45: =IF(R45="",0,1) -> 1 | ... AO45: =IF(V45="",0,1) -> 1 | AP45: =IF(AND(LEFT(E45,2)="AF",LEN(E45)=6),1,0) -> 1 | AQ45: =IF(OR(F45="CC",F45="CE",F45="TI",F45="PAS"),1,0) -> 1 | AR45: =IF(AND(ISNUMBER(G45),COUNTIF($G:$G,G45)=1),1,0) -> 1 | AS45: {=IF(AND(H45<>"",SUMPRODUCT(--ISNUMBER(FIND({0;1;2;3;4;5;6;7;8;9},H45)))=0),1,0)} -> 1 | AT45: {=IF(AND(I45<>"",SUMPRODUCT(--ISNUMBER(FIND({0;1;2;3;4;5;6;7;8;9},I45)))=0),1,0)} -> 1 | AU45: {=IF(AND(J45<>"",SUMPRODUCT(--ISNUMBER(FIND({0;1;2;3;4;5;6;7;8;9},J45)))=0),1,0)} -> 1 | AV45: =IF(OR(ISBLANK(K45),K45=""),1,IF(ISTEXT(K45),1,0)) -> 1 | AW45: =IF(AND(ISNUMBER(L45),L45<=TODAY()),1,0) -> 1 | AX45: =IF(AND(ISNUMBER(SEARCH("@",M45)),ISNUMBER(SEARCH(".",M45,SEARCH("@",M45)+2)),NOT(ISNUMBER(SEARCH(" ",M45)))),1,0) -> 1 | AY45: =IF(AND(ISNUMBER(N45),LEN(N45)=10),1,0) -> 1 | AZ45: =IF(LEN(TRIM(O45))>=10,1,0) -> 1 | BA45: =IF(OR(ISBLANK(O45),O45=""),1,IF(ISTEXT(O45),1,0)) -> 1 | BB45: =IF(OR(ISBLANK(P45),P45=""),1,IF(ISTEXT(P45),1,0)) -> 1 | BC45: =IF(AND(ISNUMBER(R45),R45<=TODAY()),1,0) -> 1 | BD45: =IF(OR(ISBLANK(S45),S45=""),1,IF(ISTEXT(S45),1,0)) -> 1 | BE45: =IF(OR(ISBLANK(T45),T45=""),1,IF(ISTEXT(T45),1,0)) -> 1 | BF45: =IF(AND(ISNUMBER(U45),U45>0),1,0) -> 1 | BG45: =IF(AND(ISNUMBER(V45),V45<=TODAY()),1,0) -> 1
A46: =IF(AND(W46=1,X46=1),1,0) -> 1 | B46: =IF(AND(Y46=1,Z46=1,AA46=1,AB46=1,AC46=1,AD46=1,AE46=1,AF46=1,AG46=1,AH46=1,AI46=1,AJ46=1,AK46=1,AL46=1,AM46=1,AN46=1,AO46=1),1,0) -> 1 | C46: =IF(AND(AP46=1,AQ46=1,AR46=1,AS46=1,AT46=1,AU46=1,AV46=1,AW46=1,AX46=1,AY46=1,AZ46=1,BA46=1,BB46=1,BC46=1,BD46=1,BE46=1,BF46=1,BG46=1),1,0) -> 1 | D46: =IF(SUM(A46:C46)<3,1,0) -> 0 | E46: AF0045 | F46: TI | G46: 1000000045 | H46: Juan | I46: Martinez | J46: Valencia | K46: M | L46: 26781 | M46: juan.martinez45@email.com | N46: 3491649554 | O46: Calle 45 #4-22 | P46: Bogotá | Q46: Cundinamarca | R46: 45748 | S46: Activo | T46: Call Center | U46: 90000 | V46: 46008 | W46: =IF(COUNTIF(E$2:E$201,E46)>1,0,1) -> 1 | X46: =IF(COUNTIF(G$2:G$201,G46)>1,0,1) -> 1 | Y46: =IF(E46="",0,1) -> 1 | Z46: =IF(F46="",0,1) -> 1 | AA46: =IF(G46="",0,1) -> 1 | AB46: =IF(H46="",0,1) -> 1 | AC46: =IF(I46="",0,1) -> 1 | AD46: =IF(K46="",0,1) -> 1 | AE46: =IF(L46="",0,1) -> 1 | AF46: =IF(M46="",0,1) -> 1 | AG46: =IF(N46="",0,1) -> 1 | AH46: =IF(O46="",0,1) -> 1 | AI46: =IF(P46="",0,1) -> 1 | AJ46: =IF(Q46="",0,1) -> 1 | AK46: =IF(R46="",0,1) -> 1 | ... AO46: =IF(V46="",0,1) -> 1 | AP46: =IF(AND(LEFT(E46,2)="AF",LEN(E46)=6),1,0) -> 1 | AQ46: =IF(OR(F46="CC",F46="CE",F46="TI",F46="PAS"),1,0) -> 1 | AR46: =IF(AND(ISNUMBER(G46),COUNTIF($G:$G,G46)=1),1,0) -> 1 | AS46: {=IF(AND(H46<>"",SUMPRODUCT(--ISNUMBER(FIND({0;1;2;3;4;5;6;7;8;9},H46)))=0),1,0)} -> 1 | AT46: {=IF(AND(I46<>"",SUMPRODUCT(--ISNUMBER(FIND({0;1;2;3;4;5;6;7;8;9},I46)))=0),1,0)} -> 1 | AU46: {=IF(AND(J46<>"",SUMPRODUCT(--ISNUMBER(FIND({0;1;2;3;4;5;6;7;8;9},J46)))=0),1,0)} -> 1 | AV46: =IF(OR(ISBLANK(K46),K46=""),1,IF(ISTEXT(K46),1,0)) -> 1 | AW46: =IF(AND(ISNUMBER(L46),L46<=TODAY()),1,0) -> 1 | AX46: =IF(AND(ISNUMBER(SEARCH("@",M46)),ISNUMBER(SEARCH(".",M46,SEARCH("@",M46)+2)),NOT(ISNUMBER(SEARCH(" ",M46)))),1,0) -> 1 | AY46: =IF(AND(ISNUMBER(N46),LEN(N46)=10),1,0) -> 1 | AZ46: =IF(LEN(TRIM(O46))>=10,1,0) -> 1 | BA46: =IF(OR(ISBLANK(O46),O46=""),1,IF(ISTEXT(O46),1,0)) -> 1 | BB46: =IF(OR(ISBLANK(P46),P46=""),1,IF(ISTEXT(P46),1,0)) -> 1 | BC46: =IF(AND(ISNUMBER(R46),R46<=TODAY()),1,0) -> 1 | BD46: =IF(OR(ISBLANK(S46),S46=""),1,IF(ISTEXT(S46),1,0)) -> 1 | BE46: =IF(OR(ISBLANK(T46),T46=""),1,IF(ISTEXT(T46),1,0)) -> 1 | BF46: =IF(AND(ISNUMBER(U46),U46>0),1,0) -> 1 | BG46: =IF(AND(ISNUMBER(V46),V46<=TODAY()),1,0) -> 1
A47: =IF(AND(W47=1,X47=1),1,0) -> 1 | B47: =IF(AND(Y47=1,Z47=1,AA47=1,AB47=1,AC47=1,AD47=1,AE47=1,AF47=1,AG47=1,AH47=1,AI47=1,AJ47=1,AK47=1,AL47=1,AM47=1,AN47=1,AO47=1),1,0) -> 1 | C47: =IF(AND(AP47=1,AQ47=1,AR47=1,AS47=1,AT47=1,AU47=1,AV47=1,AW47=1,AX47=1,AY47=1,AZ47=1,BA47=1,BB47=1,BC47=1,BD47=1,BE47=1,BF47=1,BG47=1),1,0) -> 1 | D47: =IF(SUM(A47:C47)<3,1,0) -> 0 | E47: AF0046 | F47: CC | G47: 1000000046 | H47: Javier | I47: Munoz | J47: Torres | K47: M | L47: 24953 | M47: javier.munoz46@email.com | N47: 3470417293 | O47: Calle 74 #87-87 | P47: Manizales | Q47: Caldas | R47: 45389 | S47: Activo | T47: Web | U47: 75000 | V47: 45406 | W47: =IF(COUNTIF(E$2:E$201,E47)>1,0,1) -> 1 | X47: =IF(COUNTIF(G$2:G$201,G47)>1,0,1) -> 1 | Y47: =IF(E47="",0,1) -> 1 | Z47: =IF(F47="",0,1) -> 1 | AA47: =IF(G47="",0,1) -> 1 | AB47: =IF(H47="",0,1) -> 1 | AC47: =IF(I47="",0,1) -> 1 | AD47: =IF(K47="",0,1) -> 1 | AE47: =IF(L47="",0,1) -> 1 | AF47: =IF(M47="",0,1) -> 1 | AG47: =IF(N47="",0,1) -> 1 | AH47: =IF(O47="",0,1) -> 1 | AI47: =IF(P47="",0,1) -> 1 | AJ47: =IF(Q47="",0,1) -> 1 | AK47: =IF(R47="",0,1) -> 1 | ... AO47: =IF(V47="",0,1) -> 1 | AP47: =IF(AND(LEFT(E47,2)="AF",LEN(E47)=6),1,0) -> 1 | AQ47: =IF(OR(F47="CC",F47="CE",F47="TI",F47="PAS"),1,0) -> 1 | AR47: =IF(AND(ISNUMBER(G47),COUNTIF($G:$G,G47)=1),1,0) -> 1 | AS47: {=IF(AND(H47<>"",SUMPRODUCT(--ISNUMBER(FIND({0;1;2;3;4;5;6;7;8;9},H47)))=0),1,0)} -> 1 | AT47: {=IF(AND(I47<>"",SUMPRODUCT(--ISNUMBER(FIND({0;1;2;3;4;5;6;7;8;9},I47)))=0),1,0)} -> 1 | AU47: {=IF(AND(J47<>"",SUMPRODUCT(--ISNUMBER(FIND({0;1;2;3;4;5;6;7;8;9},J47)))=0),1,0)} -> 1 | AV47: =IF(OR(ISBLANK(K47),K47=""),1,IF(ISTEXT(K47),1,0)) -> 1 | AW47: =IF(AND(ISNUMBER(L47),L47<=TODAY()),1,0) -> 1 | AX47: =IF(AND(ISNUMBER(SEARCH("@",M47)),ISNUMBER(SEARCH(".",M47,SEARCH("@",M47)+2)),NOT(ISNUMBER(SEARCH(" ",M47)))),1,0) -> 1 | AY47: =IF(AND(ISNUMBER(N47),LEN(N47)=10),1,0) -> 1 | AZ47: =IF(LEN(TRIM(O47))>=10,1,0) -> 1 | BA47: =IF(OR(ISBLANK(O47),O47=""),1,IF(ISTEXT(O47),1,0)) -> 1 | BB47: =IF(OR(ISBLANK(P47),P47=""),1,IF(ISTEXT(P47),1,0)) -> 1 | BC47: =IF(AND(ISNUMBER(R47),R47<=TODAY()),1,0) -> 1 | BD47: =IF(OR(ISBLANK(S47),S47=""),1,IF(ISTEXT(S47),1,0)) -> 1 | BE47: =IF(OR(ISBLANK(T47),T47=""),1,IF(ISTEXT(T47),1,0)) -> 1 | BF47: =IF(AND(ISNUMBER(U47),U47>0),1,0) -> 1 | BG47: =IF(AND(ISNUMBER(V47),V47<=TODAY()),1,0) -> 1
A48: =IF(AND(W48=1,X48=1),1,0) -> 1 | B48: =IF(AND(Y48=1,Z48=1,AA48=1,AB48=1,AC48=1,AD48=1,AE48=1,AF48=1,AG48=1,AH48=1,AI48=1,AJ48=1,AK48=1,AL48=1,AM48=1,AN48=1,AO48=1),1,0) -> 1 | C48: =IF(AND(AP48=1,AQ48=1,AR48=1,AS48=1,AT48=1,AU48=1,AV48=1,AW48=1,AX48=1,AY48=1,AZ48=1,BA48=1,BB48=1,BC48=1,BD48=1,BE48=1,BF48=1,BG48=1),1,0) -> 1 | D48: =IF(SUM(A48:C48)<3,1,0) -> 0 | E48: AF0047 | F48: CE | G48: 1000000047 | H48: Pedro | I48: Salazar | J48: Castillo | K48: M | L48: 30638 | M48: pedro.salazar47@email.com | N48: 3688390292 | O48: Calle 18 #23-15 | P48: Barranquilla | Q48: Atlántico | R48: 45733 | S48: Suspendido | T48: Call Center | U48: 85000 | V48: 45781 | W48: =IF(COUNTIF(E$2:E$201,E48)>1,0,1) -> 1 | X48: =IF(COUNTIF(G$2:G$201,G48)>1,0,1) -> 1 | Y48: =IF(E48="",0,1) -> 1 | Z48: =IF(F48="",0,1) -> 1 | AA48: =IF(G48="",0,1) -> 1 | AB48: =IF(H48="",0,1) -> 1 | AC48: =IF(I48="",0,1) -> 1 | AD48: =IF(K48="",0,1) -> 1 | AE48: =IF(L48="",0,1) -> 1 | AF48: =IF(M48="",0,1) -> 1 | AG48: =IF(N48="",0,1) -> 1 | AH48: =IF(O48="",0,1) -> 1 | AI48: =IF(P48="",0,1) -> 1 | AJ48: =IF(Q48="",0,1) -> 1 | AK48: =IF(R48="",0,1) -> 1 | ... AO48: =IF(V48="",0,1) -> 1 | AP48: =IF(AND(LEFT(E48,2)="AF",LEN(E48)=6),1,0) -> 1 | AQ48: =IF(OR(F48="CC",F48="CE",F48="TI",F48="PAS"),1,0) -> 1 | AR48: =IF(AND(ISNUMBER(G48),COUNTIF($G:$G,G48)=1),1,0) -> 1 | AS48: {=IF(AND(H48<>"",SUMPRODUCT(--ISNUMBER(FIND({0;1;2;3;4;5;6;7;8;9},H48)))=0),1,0)} -> 1 | AT48: {=IF(AND(I48<>"",SUMPRODUCT(--ISNUMBER(FIND({0;1;2;3;4;5;6;7;8;9},I48)))=0),1,0)} -> 1 | AU48: {=IF(AND(J48<>"",SUMPRODUCT(--ISNUMBER(FIND({0;1;2;3;4;5;6;7;8;9},J48)))=0),1,0)} -> 1 | AV48: =IF(OR(ISBLANK(K48),K48=""),1,IF(ISTEXT(K48),1,0)) -> 1 | AW48: =IF(AND(ISNUMBER(L48),L48<=TODAY()),1,0) -> 1 | AX48: =IF(AND(ISNUMBER(SEARCH("@",M48)),ISNUMBER(SEARCH(".",M48,SEARCH("@",M48)+2)),NOT(ISNUMBER(SEARCH(" ",M48)))),1,0) -> 1 | AY48: =IF(AND(ISNUMBER(N48),LEN(N48)=10),1,0) -> 1 | AZ48: =IF(LEN(TRIM(O48))>=10,1,0) -> 1 | BA48: =IF(OR(ISBLANK(O48),O48=""),1,IF(ISTEXT(O48),1,0)) -> 1 | BB48: =IF(OR(ISBLANK(P48),P48=""),1,IF(ISTEXT(P48),1,0)) -> 1 | BC48: =IF(AND(ISNUMBER(R48),R48<=TODAY()),1,0) -> 1 | BD48: =IF(OR(ISBLANK(S48),S48=""),1,IF(ISTEXT(S48),1,0)) -> 1 | BE48: =IF(OR(ISBLANK(T48),T48=""),1,IF(ISTEXT(T48),1,0)) -> 1 | BF48: =IF(AND(ISNUMBER(U48),U48>0),1,0) -> 1 | BG48: =IF(AND(ISNUMBER(V48),V48<=TODAY()),1,0) -> 1
A49: =IF(AND(W49=1,X49=1),1,0) -> 1 | B49: =IF(AND(Y49=1,Z49=1,AA49=1,AB49=1,AC49=1,AD49=1,AE49=1,AF49=1,AG49=1,AH49=1,AI49=1,AJ49=1,AK49=1,AL49=1,AM49=1,AN49=1,AO49=1),1,0) -> 1 | C49: =IF(AND(AP49=1,AQ49=1,AR49=1,AS49=1,AT49=1,AU49=1,AV49=1,AW49=1,AX49=1,AY49=1,AZ49=1,BA49=1,BB49=1,BC49=1,BD49=1,BE49=1,BF49=1,BG49=1),1,0) -> 1 | D49: =IF(SUM(A49:C49)<3,1,0) -> 0 | E49: AF0048 | F49: TI | G49: 1000000048 | H49: Nicolas | I49: Vargas | J49: Restrepo | K49: M | L49: 33452 | M49: nicolas.vargas48@email.com | N49: 3890885282 | O49: Calle 108 #57-12 | P49: Bucaramanga | Q49: Santander | R49: 45618 | S49: Retirado | T49: Call Center | U49: 75000 | V49: 45727 | W49: =IF(COUNTIF(E$2:E$201,E49)>1,0,1) -> 1 | X49: =IF(COUNTIF(G$2:G$201,G49)>1,0,1) -> 1 | Y49: =IF(E49="",0,1) -> 1 | Z49: =IF(F49="",0,1) -> 1 | AA49: =IF(G49="",0,1) -> 1 | AB49: =IF(H49="",0,1) -> 1 | AC49: =IF(I49="",0,1) -> 1 | AD49: =IF(K49="",0,1) -> 1 | AE49: =IF(L49="",0,1) -> 1 | AF49: =IF(M49="",0,1) -> 1 | AG49: =IF(N49="",0,1) -> 1 | AH49: =IF(O49="",0,1) -> 1 | AI49: =IF(P49="",0,1) -> 1 | AJ49: =IF(Q49="",0,1) -> 1 | AK49: =IF(R49="",0,1) -> 1 | ... AO49: =IF(V49="",0,1) -> 1 | AP49: =IF(AND(LEFT(E49,2)="AF",LEN(E49)=6),1,0) -> 1 | AQ49: =IF(OR(F49="CC",F49="CE",F49="TI",F49="PAS"),1,0) -> 1 | AR49: =IF(AND(ISNUMBER(G49),COUNTIF($G:$G,G49)=1),1,0) -> 1 | AS49: {=IF(AND(H49<>"",SUMPRODUCT(--ISNUMBER(FIND({0;1;2;3;4;5;6;7;8;9},H49)))=0),1,0)} -> 1 | AT49: {=IF(AND(I49<>"",SUMPRODUCT(--ISNUMBER(FIND({0;1;2;3;4;5;6;7;8;9},I49)))=0),1,0)} -> 1 | AU49: {=IF(AND(J49<>"",SUMPRODUCT(--ISNUMBER(FIND({0;1;2;3;4;5;6;7;8;9},J49)))=0),1,0)} -> 1 | AV49: =IF(OR(ISBLANK(K49),K49=""),1,IF(ISTEXT(K49),1,0)) -> 1 | AW49: =IF(AND(ISNUMBER(L49),L49<=TODAY()),1,0) -> 1 | AX49: =IF(AND(ISNUMBER(SEARCH("@",M49)),ISNUMBER(SEARCH(".",M49,SEARCH("@",M49)+2)),NOT(ISNUMBER(SEARCH(" ",M49)))),1,0) -> 1 | AY49: =IF(AND(ISNUMBER(N49),LEN(N49)=10),1,0) -> 1 | AZ49: =IF(LEN(TRIM(O49))>=10,1,0) -> 1 | BA49: =IF(OR(ISBLANK(O49),O49=""),1,IF(ISTEXT(O49),1,0)) -> 1 | BB49: =IF(OR(ISBLANK(P49),P49=""),1,IF(ISTEXT(P49),1,0)) -> 1 | BC49: =IF(AND(ISNUMBER(R49),R49<=TODAY()),1,0) -> 1 | BD49: =IF(OR(ISBLANK(S49),S49=""),1,IF(ISTEXT(S49),1,0)) -> 1 | BE49: =IF(OR(ISBLANK(T49),T49=""),1,IF(ISTEXT(T49),1,0)) -> 1 | BF49: =IF(AND(ISNUMBER(U49),U49>0),1,0) -> 1 | BG49: =IF(AND(ISNUMBER(V49),V49<=TODAY()),1,0) -> 1
A50: =IF(AND(W50=1,X50=1),1,0) -> 1 | B50: =IF(AND(Y50=1,Z50=1,AA50=1,AB50=1,AC50=1,AD50=1,AE50=1,AF50=1,AG50=1,AH50=1,AI50=1,AJ50=1,AK50=1,AL50=1,AM50=1,AN50=1,AO50=1),1,0) -> 1 | C50: =IF(AND(AP50=1,AQ50=1,AR50=1,AS50=1,AT50=1,AU50=1,AV50=1,AW50=1,AX50=1,AY50=1,AZ50=1,BA50=1,BB50=1,BC50=1,BD50=1,BE50=1,BF50=1,BG50=1),1,0) -> 1 | D50: =IF(SUM(A50:C50)<3,1,0) -> 0 | E50: AF0049 | F50: CC | G50: 1000000049 | H50: Nicolas | I50: Munoz | J50: Martinez | K50: M | L50: 37620 | M50: nicolas.munoz49@email.com | N50: 3346121033 | O50: Calle 70 #88-8 | P50: Pereira | Q50: Risaralda | R50: 44860 | S50: Suspendido | T50: Presencial | U50: 90000 | V50: 45040 | W50: =IF(COUNTIF(E$2:E$201,E50)>1,0,1) -> 1 | X50: =IF(COUNTIF(G$2:G$201,G50)>1,0,1) -> 1 | Y50: =IF(E50="",0,1) -> 1 | Z50: =IF(F50="",0,1) -> 1 | AA50: =IF(G50="",0,1) -> 1 | AB50: =IF(H50="",0,1) -> 1 | AC50: =IF(I50="",0,1) -> 1 | AD50: =IF(K50="",0,1) -> 1 | AE50: =IF(L50="",0,1) -> 1 | AF50: =IF(M50="",0,1) -> 1 | AG50: =IF(N50="",0,1) -> 1 | AH50: =IF(O50="",0,1) -> 1 | AI50: =IF(P50="",0,1) -> 1 | AJ50: =IF(Q50="",0,1) -> 1 | AK50: =IF(R50="",0,1) -> 1 | ... AO50: =IF(V50="",0,1) -> 1 | AP50: =IF(AND(LEFT(E50,2)="AF",LEN(E50)=6),1,0) -> 1 | AQ50: =IF(OR(F50="CC",F50="CE",F50="TI",F50="PAS"),1,0) -> 1 | AR50: =IF(AND(ISNUMBER(G50),COUNTIF($G:$G,G50)=1),1,0) -> 1 | AS50: {=IF(AND(H50<>"",SUMPRODUCT(--ISNUMBER(FIND({0;1;2;3;4;5;6;7;8;9},H50)))=0),1,0)} -> 1 | AT50: {=IF(AND(I50<>"",SUMPRODUCT(--ISNUMBER(FIND({0;1;2;3;4;5;6;7;8;9},I50)))=0),1,0)} -> 1 | AU50: {=IF(AND(J50<>"",SUMPRODUCT(--ISNUMBER(FIND({0;1;2;3;4;5;6;7;8;9},J50)))=0),1,0)} -> 1 | AV50: =IF(OR(ISBLANK(K50),K50=""),1,IF(ISTEXT(K50),1,0)) -> 1 | AW50: =IF(AND(ISNUMBER(L50),L50<=TODAY()),1,0) -> 1 | AX50: =IF(AND(ISNUMBER(SEARCH("@",M50)),ISNUMBER(SEARCH(".",M50,SEARCH("@",M50)+2)),NOT(ISNUMBER(SEARCH(" ",M50)))),1,0) -> 1 | AY50: =IF(AND(ISNUMBER(N50),LEN(N50)=10),1,0) -> 1 | AZ50: =IF(LEN(TRIM(O50))>=10,1,0) -> 1 | BA50: =IF(OR(ISBLANK(O50),O50=""),1,IF(ISTEXT(O50),1,0)) -> 1 | BB50: =IF(OR(ISBLANK(P50),P50=""),1,IF(ISTEXT(P50),1,0)) -> 1 | BC50: =IF(AND(ISNUMBER(R50),R50<=TODAY()),1,0) -> 1 | BD50: =IF(OR(ISBLANK(S50),S50=""),1,IF(ISTEXT(S50),1,0)) -> 1 | BE50: =IF(OR(ISBLANK(T50),T50=""),1,IF(ISTEXT(T50),1,0)) -> 1 | BF50: =IF(AND(ISNUMBER(U50),U50>0),1,0) -> 1 | BG50: =IF(AND(ISNUMBER(V50),V50<=TODAY()),1,0) -> 1
... A90: =IF(AND(W90=1,X90=1),1,0) -> 1 | B90: =IF(AND(Y90=1,Z90=1,AA90=1,AB90=1,AC90=1,AD90=1,AE90=1,AF90=1,AG90=1,AH90=1,AI90=1,AJ90=1,AK90=1,AL90=1,AM90=1,AN90=1,AO90=1),1,0) -> 1 | C90: =IF(AND(AP90=1,AQ90=1,AR90=1,AS90=1,AT90=1,AU90=1,AV90=1,AW90=1,AX90=1,AY90=1,AZ90=1,BA90=1,BB90=1,BC90=1,BD90=1,BE90=1,BF90=1,BG90=1),1,0) -> 0 | D90: =IF(SUM(A90:C90)<3,1,0) -> 1 | E90: AF0089 | F90: TI | G90: 1000000089 | H90: Andres | I90: Leon | J90: Ortiz | K90: M | L90: 29907 | M90: andres.leon89@email.com | N90: 3371547788 | O90: Calle 14 #49-25 | P90: Barranquilla | Q90: Atlántico | R90: 45887 | S90: Retirado | T90: Call Center | U90: 90000 | V90: 46206 | W90: =IF(COUNTIF(E$2:E$201,E90)>1,0,1) -> 1 | X90: =IF(COUNTIF(G$2:G$201,G90)>1,0,1) -> 1 | Y90: =IF(E90="",0,1) -> 1 | Z90: =IF(F90="",0,1) -> 1 | AA90: =IF(G90="",0,1) -> 1 | AB90: =IF(H90="",0,1) -> 1 | AC90: =IF(I90="",0,1) -> 1 | AD90: =IF(K90="",0,1) -> 1 | AE90: =IF(L90="",0,1) -> 1 | AF90: =IF(M90="",0,1) -> 1 | AG90: =IF(N90="",0,1) -> 1 | AH90: =IF(O90="",0,1) -> 1 | AI90: =IF(P90="",0,1) -> 1 | AJ90: =IF(Q90="",0,1) -> 1 | AK90: =IF(R90="",0,1) -> 1 | ... AO90: =IF(V90="",0,1) -> 1 | AP90: =IF(AND(LEFT(E90,2)="AF",LEN(E90)=6),1,0) -> 1 | AQ90: =IF(OR(F90="CC",F90="CE",F90="TI",F90="PAS"),1,0) -> 1 | AR90: =IF(AND(ISNUMBER(G90),COUNTIF($G:$G,G90)=1),1,0) -> 1 | AS90: {=IF(AND(H90<>"",SUMPRODUCT(--ISNUMBER(FIND({0;1;2;3;4;5;6;7;8;9},H90)))=0),1,0)} -> 1 | AT90: {=IF(AND(I90<>"",SUMPRODUCT(--ISNUMBER(FIND({0;1;2;3;4;5;6;7;8;9},I90)))=0),1,0)} -> 1 | AU90: {=IF(AND(J90<>"",SUMPRODUCT(--ISNUMBER(FIND({0;1;2;3;4;5;6;7;8;9},J90)))=0),1,0)} -> 1 | AV90: =IF(OR(ISBLANK(K90),K90=""),1,IF(ISTEXT(K90),1,0)) -> 1 | AW90: =IF(AND(ISNUMBER(L90),L90<=TODAY()),1,0) -> 1 | AX90: =IF(AND(ISNUMBER(SEARCH("@",M90)),ISNUMBER(SEARCH(".",M90,SEARCH("@",M90)+2)),NOT(ISNUMBER(SEARCH(" ",M90)))),1,0) -> 1 | AY90: =IF(AND(ISNUMBER(N90),LEN(N90)=10),1,0) -> 1 | AZ90: =IF(LEN(TRIM(O90))>=10,1,0) -> 1 | BA90: =IF(OR(ISBLANK(O90),O90=""),1,IF(ISTEXT(O90),1,0)) -> 1 | BB90: =IF(OR(ISBLANK(P90),P90=""),1,IF(ISTEXT(P90),1,0)) -> 1 | BC90: =IF(AND(ISNUMBER(R90),R90<=TODAY()),1,0) -> 1 | BD90: =IF(OR(ISBLANK(S90),S90=""),1,IF(ISTEXT(S90),1,0)) -> 1 | BE90: =IF(OR(ISBLANK(T90),T90=""),1,IF(ISTEXT(T90),1,0)) -> 1 | BF90: =IF(AND(ISNUMBER(U90),U90>0),1,0) -> 1 | BG90: =IF(AND(ISNUMBER(V90),V90<=TODAY()),1,0) -> 0
A91: =IF(AND(W91=1,X91=1),1,0) -> 1 | B91: =IF(AND(Y91=1,Z91=1,AA91=1,AB91=1,AC91=1,AD91=1,AE91=1,AF91=1,AG91=1,AH91=1,AI91=1,AJ91=1,AK91=1,AL91=1,AM91=1,AN91=1,AO91=1),1,0) -> 0 | C91: =IF(AND(AP91=1,AQ91=1,AR91=1,AS91=1,AT91=1,AU91=1,AV91=1,AW91=1,AX91=1,AY91=1,AZ91=1,BA91=1,BB91=1,BC91=1,BD91=1,BE91=1,BF91=1,BG91=1),1,0) -> 0 | D91: =IF(SUM(A91:C91)<3,1,0) -> 1 | E91: AF0090 | F91: TI | G91: 1000000090 | I91: Herrera | J91: Restrepo | K91: F | L91: 27963 | M91: juliana.herrera90@email.com | N91: 3650087664 | O91: Calle 92 #15-26 | P91: Medellín | Q91: Antioquia | R91: 45958 | S91: Activo | T91: Web | U91: 85000 | V91: 46009 | W91: =IF(COUNTIF(E$2:E$201,E91)>1,0,1) -> 1 | X91: =IF(COUNTIF(G$2:G$201,G91)>1,0,1) -> 1 | Y91: =IF(E91="",0,1) -> 1 | Z91: =IF(F91="",0,1) -> 1 | AA91: =IF(G91="",0,1) -> 1 | AB91: =IF(H91="",0,1) -> 0 | AC91: =IF(I91="",0,1) -> 1 | AD91: =IF(K91="",0,1) -> 1 | AE91: =IF(L91="",0,1) -> 1 | AF91: =IF(M91="",0,1) -> 1 | AG91: =IF(N91="",0,1) -> 1 | AH91: =IF(O91="",0,1) -> 1 | AI91: =IF(P91="",0,1) -> 1 | AJ91: =IF(Q91="",0,1) -> 1 | AK91: =IF(R91="",0,1) -> 1 | ... AO91: =IF(V91="",0,1) -> 1 | AP91: =IF(AND(LEFT(E91,2)="AF",LEN(E91)=6),1,0) -> 1 | AQ91: =IF(OR(F91="CC",F91="CE",F91="TI",F91="PAS"),1,0) -> 1 | AR91: =IF(AND(ISNUMBER(G91),COUNTIF($G:$G,G91)=1),1,0) -> 1 | AS91: {=IF(AND(H91<>"",SUMPRODUCT(--ISNUMBER(FIND({0;1;2;3;4;5;6;7;8;9},H91)))=0),1,0)} -> 0 | AT91: {=IF(AND(I91<>"",SUMPRODUCT(--ISNUMBER(FIND({0;1;2;3;4;5;6;7;8;9},I91)))=0),1,0)} -> 1 | AU91: {=IF(AND(J91<>"",SUMPRODUCT(--ISNUMBER(FIND({0;1;2;3;4;5;6;7;8;9},J91)))=0),1,0)} -> 1 | AV91: =IF(OR(ISBLANK(K91),K91=""),1,IF(ISTEXT(K91),1,0)) -> 1 | AW91: =IF(AND(ISNUMBER(L91),L91<=TODAY()),1,0) -> 1 | AX91: =IF(AND(ISNUMBER(SEARCH("@",M91)),ISNUMBER(SEARCH(".",M91,SEARCH("@",M91)+2)),NOT(ISNUMBER(SEARCH(" ",M91)))),1,0) -> 1 | AY91: =IF(AND(ISNUMBER(N91),LEN(N91)=10),1,0) -> 1 | AZ91: =IF(LEN(TRIM(O91))>=10,1,0) -> 1 | BA91: =IF(OR(ISBLANK(O91),O91=""),1,IF(ISTEXT(O91),1,0)) -> 1 | BB91: =IF(OR(ISBLANK(P91),P91=""),1,IF(ISTEXT(P91),1,0)) -> 1 | BC91: =IF(AND(ISNUMBER(R91),R91<=TODAY()),1,0) -> 1 | BD91: =IF(OR(ISBLANK(S91),S91=""),1,IF(ISTEXT(S91),1,0)) -> 1 | BE91: =IF(OR(ISBLANK(T91),T91=""),1,IF(ISTEXT(T91),1,0)) -> 1 | BF91: =IF(AND(ISNUMBER(U91),U91>0),1,0) -> 1 | BG91: =IF(AND(ISNUMBER(V91),V91<=TODAY()),1,0) -> 1
A92: =IF(AND(W92=1,X92=1),1,0) -> 1 | B92: =IF(AND(Y92=1,Z92=1,AA92=1,AB92=1,AC92=1,AD92=1,AE92=1,AF92=1,AG92=1,AH92=1,AI92=1,AJ92=1,AK92=1,AL92=1,AM92=1,AN92=1,AO92=1),1,0) -> 1 | C92: =IF(AND(AP92=1,AQ92=1,AR92=1,AS92=1,AT92=1,AU92=1,AV92=1,AW92=1,AX92=1,AY92=1,AZ92=1,BA92=1,BB92=1,BC92=1,BD92=1,BE92=1,BF92=1,BG92=1),1,0) -> 1 | D92: =IF(SUM(A92:C92)<3,1,0) -> 0 | E92: AF0091 | F92: TI | G92: 1000000091 | H92: Camila | I92: Castro | J92: Vargas | K92: F | L92: 33689 | M92: camila.castro91@email.com | N92: 3774148110 | O92: Calle 72 #23-73 | P92: Medellín | Q92: Antioquia | R92: 45899 | S92: Retirado | T92: Call Center | U92: 75000 | V92: 45965 | W92: =IF(COUNTIF(E$2:E$201,E92)>1,0,1) -> 1 | X92: =IF(COUNTIF(G$2:G$201,G92)>1,0,1) -> 1 | Y92: =IF(E92="",0,1) -> 1 | Z92: =IF(F92="",0,1) -> 1 | AA92: =IF(G92="",0,1) -> 1 | AB92: =IF(H92="",0,1) -> 1 | AC92: =IF(I92="",0,1) -> 1 | AD92: =IF(K92="",0,1) -> 1 | AE92: =IF(L92="",0,1) -> 1 | AF92: =IF(M92="",0,1) -> 1 | AG92: =IF(N92="",0,1) -> 1 | AH92: =IF(O92="",0,1) -> 1 | AI92: =IF(P92="",0,1) -> 1 | AJ92: =IF(Q92="",0,1) -> 1 | AK92: =IF(R92="",0,1) -> 1 | ... AO92: =IF(V92="",0,1) -> 1 | AP92: =IF(AND(LEFT(E92,2)="AF",LEN(E92)=6),1,0) -> 1 | AQ92: =IF(OR(F92="CC",F92="CE",F92="TI",F92="PAS"),1,0) -> 1 | AR92: =IF(AND(ISNUMBER(G92),COUNTIF($G:$G,G92)=1),1,0) -> 1 | AS92: {=IF(AND(H92<>"",SUMPRODUCT(--ISNUMBER(FIND({0;1;2;3;4;5;6;7;8;9},H92)))=0),1,0)} -> 1 | AT92: {=IF(AND(I92<>"",SUMPRODUCT(--ISNUMBER(FIND({0;1;2;3;4;5;6;7;8;9},I92)))=0),1,0)} -> 1 | AU92: {=IF(AND(J92<>"",SUMPRODUCT(--ISNUMBER(FIND({0;1;2;3;4;5;6;7;8;9},J92)))=0),1,0)} -> 1 | AV92: =IF(OR(ISBLANK(K92),K92=""),1,IF(ISTEXT(K92),1,0)) -> 1 | AW92: =IF(AND(ISNUMBER(L92),L92<=TODAY()),1,0) -> 1 | AX92: =IF(AND(ISNUMBER(SEARCH("@",M92)),ISNUMBER(SEARCH(".",M92,SEARCH("@",M92)+2)),NOT(ISNUMBER(SEARCH(" ",M92)))),1,0) -> 1 | AY92: =IF(AND(ISNUMBER(N92),LEN(N92)=10),1,0) -> 1 | AZ92: =IF(LEN(TRIM(O92))>=10,1,0) -> 1 | BA92: =IF(OR(ISBLANK(O92),O92=""),1,IF(ISTEXT(O92),1,0)) -> 1 | BB92: =IF(OR(ISBLANK(P92),P92=""),1,IF(ISTEXT(P92),1,0)) -> 1 | BC92: =IF(AND(ISNUMBER(R92),R92<=TODAY()),1,0) -> 1 | BD92: =IF(OR(ISBLANK(S92),S92=""),1,IF(ISTEXT(S92),1,0)) -> 1 | BE92: =IF(OR(ISBLANK(T92),T92=""),1,IF(ISTEXT(T92),1,0)) -> 1 | BF92: =IF(AND(ISNUMBER(U92),U92>0),1,0) -> 1 | BG92: =IF(AND(ISNUMBER(V92),V92<=TODAY()),1,0) -> 1
A93: =IF(AND(W93=1,X93=1),1,0) -> 1 | B93: =IF(AND(Y93=1,Z93=1,AA93=1,AB93=1,AC93=1,AD93=1,AE93=1,AF93=1,AG93=1,AH93=1,AI93=1,AJ93=1,AK93=1,AL93=1,AM93=1,AN93=1,AO93=1),1,0) -> 1 | C93: =IF(AND(AP93=1,AQ93=1,AR93=1,AS93=1,AT93=1,AU93=1,AV93=1,AW93=1,AX93=1,AY93=1,AZ93=1,BA93=1,BB93=1,BC93=1,BD93=1,BE93=1,BF93=1,BG93=1),1,0) -> 1 | D93: =IF(SUM(A93:C93)<3,1,0) -> 0 | E93: AF0092 | F93: TI | G93: 1000000092 | H93: Natalia | I93: Gomez | J93: Martinez | K93: F | L93: 38590 | M93: natalia.gomez92@email.com | N93: 3745757052 | O93: Calle 61 #73-11 | P93: Manizales | Q93: Caldas | R93: 45387 | S93: Activo | T93: Presencial | U93: 85000 | V93: 45602 | W93: =IF(COUNTIF(E$2:E$201,E93)>1,0,1) -> 1 | X93: =IF(COUNTIF(G$2:G$201,G93)>1,0,1) -> 1 | Y93: =IF(E93="",0,1) -> 1 | Z93: =IF(F93="",0,1) -> 1 | AA93: =IF(G93="",0,1) -> 1 | AB93: =IF(H93="",0,1) -> 1 | AC93: =IF(I93="",0,1) -> 1 | AD93: =IF(K93="",0,1) -> 1 | AE93: =IF(L93="",0,1) -> 1 | AF93: =IF(M93="",0,1) -> 1 | AG93: =IF(N93="",0,1) -> 1 | AH93: =IF(O93="",0,1) -> 1 | AI93: =IF(P93="",0,1) -> 1 | AJ93: =IF(Q93="",0,1) -> 1 | AK93: =IF(R93="",0,1) -> 1 | ... AO93: =IF(V93="",0,1) -> 1 | AP93: =IF(AND(LEFT(E93,2)="AF",LEN(E93)=6),1,0) -> 1 | AQ93: =IF(OR(F93="CC",F93="CE",F93="TI",F93="PAS"),1,0) -> 1 | AR93: =IF(AND(ISNUMBER(G93),COUNTIF($G:$G,G93)=1),1,0) -> 1 | AS93: {=IF(AND(H93<>"",SUMPRODUCT(--ISNUMBER(FIND({0;1;2;3;4;5;6;7;8;9},H93)))=0),1,0)} -> 1 | AT93: {=IF(AND(I93<>"",SUMPRODUCT(--ISNUMBER(FIND({0;1;2;3;4;5;6;7;8;9},I93)))=0),1,0)} -> 1 | AU93: {=IF(AND(J93<>"",SUMPRODUCT(--ISNUMBER(FIND({0;1;2;3;4;5;6;7;8;9},J93)))=0),1,0)} -> 1 | AV93: =IF(OR(ISBLANK(K93),K93=""),1,IF(ISTEXT(K93),1,0)) -> 1 | AW93: =IF(AND(ISNUMBER(L93),L93<=TODAY()),1,0) -> 1 | AX93: =IF(AND(ISNUMBER(SEARCH("@",M93)),ISNUMBER(SEARCH(".",M93,SEARCH("@",M93)+2)),NOT(ISNUMBER(SEARCH(" ",M93)))),1,0) -> 1 | AY93: =IF(AND(ISNUMBER(N93),LEN(N93)=10),1,0) -> 1 | AZ93: =IF(LEN(TRIM(O93))>=10,1,0) -> 1 | BA93: =IF(OR(ISBLANK(O93),O93=""),1,IF(ISTEXT(O93),1,0)) -> 1 | BB93: =IF(OR(ISBLANK(P93),P93=""),1,IF(ISTEXT(P93),1,0)) -> 1 | BC93: =IF(AND(ISNUMBER(R93),R93<=TODAY()),1,0) -> 1 | BD93: =IF(OR(ISBLANK(S93),S93=""),1,IF(ISTEXT(S93),1,0)) -> 1 | BE93: =IF(OR(ISBLANK(T93),T93=""),1,IF(ISTEXT(T93),1,0)) -> 1 | BF93: =IF(AND(ISNUMBER(U93),U93>0),1,0) -> 1 | BG93: =IF(AND(ISNUMBER(V93),V93<=TODAY()),1,0) -> 1
A94: =IF(AND(W94=1,X94=1),1,0) -> 1 | B94: =IF(AND(Y94=1,Z94=1,AA94=1,AB94=1,AC94=1,AD94=1,AE94=1,AF94=1,AG94=1,AH94=1,AI94=1,AJ94=1,AK94=1,AL94=1,AM94=1,AN94=1,AO94=1),1,0) -> 1 | C94: =IF(AND(AP94=1,AQ94=1,AR94=1,AS94=1,AT94=1,AU94=1,AV94=1,AW94=1,AX94=1,AY94=1,AZ94=1,BA94=1,BB94=1,BC94=1,BD94=1,BE94=1,BF94=1,BG94=1),1,0) -> 0 | D94: =IF(SUM(A94:C94)<3,1,0) -> 1 | E94: AF0093 | F94: CC | G94: 1000000093 | H94: Paula | I94: Lopez | J94: Valencia | K94: F | L94: 34282 | M94: paula.lopez93@email.com | N94: 3167383306 | O94: Calle 68 #22-52 | P94: Manizales | Q94: Caldas | R94: 46151 | S94: Suspendido | T94: Call Center | U94: 85000 | V94: 46395 | W94: =IF(COUNTIF(E$2:E$201,E94)>1,0,1) -> 1 | X94: =IF(COUNTIF(G$2:G$201,G94)>1,0,1) -> 1 | Y94: =IF(E94="",0,1) -> 1 | Z94: =IF(F94="",0,1) -> 1 | AA94: =IF(G94="",0,1) -> 1 | AB94: =IF(H94="",0,1) -> 1 | AC94: =IF(I94="",0,1) -> 1 | AD94: =IF(K94="",0,1) -> 1 | AE94: =IF(L94="",0,1) -> 1 | AF94: =IF(M94="",0,1) -> 1 | AG94: =IF(N94="",0,1) -> 1 | AH94: =IF(O94="",0,1) -> 1 | AI94: =IF(P94="",0,1) -> 1 | AJ94: =IF(Q94="",0,1) -> 1 | AK94: =IF(R94="",0,1) -> 1 | ... AO94: =IF(V94="",0,1) -> 1 | AP94: =IF(AND(LEFT(E94,2)="AF",LEN(E94)=6),1,0) -> 1 | AQ94: =IF(OR(F94="CC",F94="CE",F94="TI",F94="PAS"),1,0) -> 1 | AR94: =IF(AND(ISNUMBER(G94),COUNTIF($G:$G,G94)=1),1,0) -> 1 | AS94: {=IF(AND(H94<>"",SUMPRODUCT(--ISNUMBER(FIND({0;1;2;3;4;5;6;7;8;9},H94)))=0),1,0)} -> 1 | AT94: {=IF(AND(I94<>"",SUMPRODUCT(--ISNUMBER(FIND({0;1;2;3;4;5;6;7;8;9},I94)))=0),1,0)} -> 1 | AU94: {=IF(AND(J94<>"",SUMPRODUCT(--ISNUMBER(FIND({0;1;2;3;4;5;6;7;8;9},J94)))=0),1,0)} -> 1 | AV94: =IF(OR(ISBLANK(K94),K94=""),1,IF(ISTEXT(K94),1,0)) -> 1 | AW94: =IF(AND(ISNUMBER(L94),L94<=TODAY()),1,0) -> 1 | AX94: =IF(AND(ISNUMBER(SEARCH("@",M94)),ISNUMBER(SEARCH(".",M94,SEARCH("@",M94)+2)),NOT(ISNUMBER(SEARCH(" ",M94)))),1,0) -> 1 | AY94: =IF(AND(ISNUMBER(N94),LEN(N94)=10),1,0) -> 1 | AZ94: =IF(LEN(TRIM(O94))>=10,1,0) -> 1 | BA94: =IF(OR(ISBLANK(O94),O94=""),1,IF(ISTEXT(O94),1,0)) -> 1 | BB94: =IF(OR(ISBLANK(P94),P94=""),1,IF(ISTEXT(P94),1,0)) -> 1 | BC94: =IF(AND(ISNUMBER(R94),R94<=TODAY()),1,0) -> 1 | BD94: =IF(OR(ISBLANK(S94),S94=""),1,IF(ISTEXT(S94),1,0)) -> 1 | BE94: =IF(OR(ISBLANK(T94),T94=""),1,IF(ISTEXT(T94),1,0)) -> 1 | BF94: =IF(AND(ISNUMBER(U94),U94>0),1,0) -> 1 | BG94: =IF(AND(ISNUMBER(V94),V94<=TODAY()),1,0) -> 0
A95: =IF(AND(W95=1,X95=1),1,0) -> 1 | B95: =IF(AND(Y95=1,Z95=1,AA95=1,AB95=1,AC95=1,AD95=1,AE95=1,AF95=1,AG95=1,AH95=1,AI95=1,AJ95=1,AK95=1,AL95=1,AM95=1,AN95=1,AO95=1),1,0) -> 1 | C95: =IF(AND(AP95=1,AQ95=1,AR95=1,AS95=1,AT95=1,AU95=1,AV95=1,AW95=1,AX95=1,AY95=1,AZ95=1,BA95=1,BB95=1,BC95=1,BD95=1,BE95=1,BF95=1,BG95=1),1,0) -> 1 | D95: =IF(SUM(A95:C95)<3,1,0) -> 0 | E95: AF0094 | F95: TI | G95: 1000000094 | H95: Paula | I95: Rodriguez | J95: Herrera | K95: F | L95: 33700 | M95: paula.rodriguez94@email.com | N95: 3440356008 | O95: Calle 111 #10-99 | P95: Manizales | Q95: Caldas | R95: 45143 | S95: Retirado | T95: Web | U95: 75000 | V95: 45153 | W95: =IF(COUNTIF(E$2:E$201,E95)>1,0,1) -> 1 | X95: =IF(COUNTIF(G$2:G$201,G95)>1,0,1) -> 1 | Y95: =IF(E95="",0,1) -> 1 | Z95: =IF(F95="",0,1) -> 1 | AA95: =IF(G95="",0,1) -> 1 | AB95: =IF(H95="",0,1) -> 1 | AC95: =IF(I95="",0,1) -> 1 | AD95: =IF(K95="",0,1) -> 1 | AE95: =IF(L95="",0,1) -> 1 | AF95: =IF(M95="",0,1) -> 1 | AG95: =IF(N95="",0,1) -> 1 | AH95: =IF(O95="",0,1) -> 1 | AI95: =IF(P95="",0,1) -> 1 | AJ95: =IF(Q95="",0,1) -> 1 | AK95: =IF(R95="",0,1) -> 1 | ... AO95: =IF(V95="",0,1) -> 1 | AP95: =IF(AND(LEFT(E95,2)="AF",LEN(E95)=6),1,0) -> 1 | AQ95: =IF(OR(F95="CC",F95="CE",F95="TI",F95="PAS"),1,0) -> 1 | AR95: =IF(AND(ISNUMBER(G95),COUNTIF($G:$G,G95)=1),1,0) -> 1 | AS95: {=IF(AND(H95<>"",SUMPRODUCT(--ISNUMBER(FIND({0;1;2;3;4;5;6;7;8;9},H95)))=0),1,0)} -> 1 | AT95: {=IF(AND(I95<>"",SUMPRODUCT(--ISNUMBER(FIND({0;1;2;3;4;5;6;7;8;9},I95)))=0),1,0)} -> 1 | AU95: {=IF(AND(J95<>"",SUMPRODUCT(--ISNUMBER(FIND({0;1;2;3;4;5;6;7;8;9},J95)))=0),1,0)} -> 1 | AV95: =IF(OR(ISBLANK(K95),K95=""),1,IF(ISTEXT(K95),1,0)) -> 1 | AW95: =IF(AND(ISNUMBER(L95),L95<=TODAY()),1,0) -> 1 | AX95: =IF(AND(ISNUMBER(SEARCH("@",M95)),ISNUMBER(SEARCH(".",M95,SEARCH("@",M95)+2)),NOT(ISNUMBER(SEARCH(" ",M95)))),1,0) -> 1 | AY95: =IF(AND(ISNUMBER(N95),LEN(N95)=10),1,0) -> 1 | AZ95: =IF(LEN(TRIM(O95))>=10,1,0) -> 1 | BA95: =IF(OR(ISBLANK(O95),O95=""),1,IF(ISTEXT(O95),1,0)) -> 1 | BB95: =IF(OR(ISBLANK(P95),P95=""),1,IF(ISTEXT(P95),1,0)) -> 1 | BC95: =IF(AND(ISNUMBER(R95),R95<=TODAY()),1,0) -> 1 | BD95: =IF(OR(ISBLANK(S95),S95=""),1,IF(ISTEXT(S95),1,0)) -> 1 | BE95: =IF(OR(ISBLANK(T95),T95=""),1,IF(ISTEXT(T95),1,0)) -> 1 | BF95: =IF(AND(ISNUMBER(U95),U95>0),1,0) -> 1 | BG95: =IF(AND(ISNUMBER(V95),V95<=TODAY()),1,0) -> 1
A96: =IF(AND(W96=1,X96=1),1,0) -> 1 | B96: =IF(AND(Y96=1,Z96=1,AA96=1,AB96=1,AC96=1,AD96=1,AE96=1,AF96=1,AG96=1,AH96=1,AI96=1,AJ96=1,AK96=1,AL96=1,AM96=1,AN96=1,AO96=1),1,0) -> 1 | C96: =IF(AND(AP96=1,AQ96=1,AR96=1,AS96=1,AT96=1,AU96=1,AV96=1,AW96=1,AX96=1,AY96=1,AZ96=1,BA96=1,BB96=1,BC96=1,BD96=1,BE96=1,BF96=1,BG96=1),1,0) -> 1 | D96: =IF(SUM(A96:C96)<3,1,0) -> 0 | E96: AF0095 | F96: CC | G96: 1000000095 | H96: Juan | I96: Gomez | J96: Valencia | K96: M | L96: 32421 | M96: juan.gomez95@email.com | N96: 3175554455 | O96: Calle 103 #76-50 | P96: Bogotá | Q96: Cundinamarca | R96: 45037 | S96: Suspendido | T96: Presencial | U96: 85000 | V96: 45399 | W96: =IF(COUNTIF(E$2:E$201,E96)>1,0,1) -> 1 | X96: =IF(COUNTIF(G$2:G$201,G96)>1,0,1) -> 1 | Y96: =IF(E96="",0,1) -> 1 | Z96: =IF(F96="",0,1) -> 1 | AA96: =IF(G96="",0,1) -> 1 | AB96: =IF(H96="",0,1) -> 1 | AC96: =IF(I96="",0,1) -> 1 | AD96: =IF(K96="",0,1) -> 1 | AE96: =IF(L96="",0,1) -> 1 | AF96: =IF(M96="",0,1) -> 1 | AG96: =IF(N96="",0,1) -> 1 | AH96: =IF(O96="",0,1) -> 1 | AI96: =IF(P96="",0,1) -> 1 | AJ96: =IF(Q96="",0,1) -> 1 | AK96: =IF(R96="",0,1) -> 1 | ... AO96: =IF(V96="",0,1) -> 1 | AP96: =IF(AND(LEFT(E96,2)="AF",LEN(E96)=6),1,0) -> 1 | AQ96: =IF(OR(F96="CC",F96="CE",F96="TI",F96="PAS"),1,0) -> 1 | AR96: =IF(AND(ISNUMBER(G96),COUNTIF($G:$G,G96)=1),1,0) -> 1 | AS96: {=IF(AND(H96<>"",SUMPRODUCT(--ISNUMBER(FIND({0;1;2;3;4;5;6;7;8;9},H96)))=0),1,0)} -> 1 | AT96: {=IF(AND(I96<>"",SUMPRODUCT(--ISNUMBER(FIND({0;1;2;3;4;5;6;7;8;9},I96)))=0),1,0)} -> 1 | AU96: {=IF(AND(J96<>"",SUMPRODUCT(--ISNUMBER(FIND({0;1;2;3;4;5;6;7;8;9},J96)))=0),1,0)} -> 1 | AV96: =IF(OR(ISBLANK(K96),K96=""),1,IF(ISTEXT(K96),1,0)) -> 1 | AW96: =IF(AND(ISNUMBER(L96),L96<=TODAY()),1,0) -> 1 | AX96: =IF(AND(ISNUMBER(SEARCH("@",M96)),ISNUMBER(SEARCH(".",M96,SEARCH("@",M96)+2)),NOT(ISNUMBER(SEARCH(" ",M96)))),1,0) -> 1 | AY96: =IF(AND(ISNUMBER(N96),LEN(N96)=10),1,0) -> 1 | AZ96: =IF(LEN(TRIM(O96))>=10,1,0) -> 1 | BA96: =IF(OR(ISBLANK(O96),O96=""),1,IF(ISTEXT(O96),1,0)) -> 1 | BB96: =IF(OR(ISBLANK(P96),P96=""),1,IF(ISTEXT(P96),1,0)) -> 1 | BC96: =IF(AND(ISNUMBER(R96),R96<=TODAY()),1,0) -> 1 | BD96: =IF(OR(ISBLANK(S96),S96=""),1,IF(ISTEXT(S96),1,0)) -> 1 | BE96: =IF(OR(ISBLANK(T96),T96=""),1,IF(ISTEXT(T96),1,0)) -> 1 | BF96: =IF(AND(ISNUMBER(U96),U96>0),1,0) -> 1 | BG96: =IF(AND(ISNUMBER(V96),V96<=TODAY()),1,0) -> 1
A97: =IF(AND(W97=1,X97=1),1,0) -> 1 | B97: =IF(AND(Y97=1,Z97=1,AA97=1,AB97=1,AC97=1,AD97=1,AE97=1,AF97=1,AG97=1,AH97=1,AI97=1,AJ97=1,AK97=1,AL97=1,AM97=1,AN97=1,AO97=1),1,0) -> 1 | C97: =IF(AND(AP97=1,AQ97=1,AR97=1,AS97=1,AT97=1,AU97=1,AV97=1,AW97=1,AX97=1,AY97=1,AZ97=1,BA97=1,BB97=1,BC97=1,BD97=1,BE97=1,BF97=1,BG97=1),1,0) -> 1 | D97: =IF(SUM(A97:C97)<3,1,0) -> 0 | E97: AF0096 | F97: CC | G97: 1000000096 | H97: Nicolas | I97: Castro | J97: Sanchez | K97: M | L97: 24439 | M97: nicolas.castro96@email.com | N97: 3888014073 | O97: Calle 77 #79-10 | P97: Envigado | Q97: Antioquia | R97: 44879 | S97: Suspendido | T97: Call Center | U97: 75000 | V97: 44942 | W97: =IF(COUNTIF(E$2:E$201,E97)>1,0,1) -> 1 | X97: =IF(COUNTIF(G$2:G$201,G97)>1,0,1) -> 1 | Y97: =IF(E97="",0,1) -> 1 | Z97: =IF(F97="",0,1) -> 1 | AA97: =IF(G97="",0,1) -> 1 | AB97: =IF(H97="",0,1) -> 1 | AC97: =IF(I97="",0,1) -> 1 | AD97: =IF(K97="",0,1) -> 1 | AE97: =IF(L97="",0,1) -> 1 | AF97: =IF(M97="",0,1) -> 1 | AG97: =IF(N97="",0,1) -> 1 | AH97: =IF(O97="",0,1) -> 1 | AI97: =IF(P97="",0,1) -> 1 | AJ97: =IF(Q97="",0,1) -> 1 | AK97: =IF(R97="",0,1) -> 1 | ... AO97: =IF(V97="",0,1) -> 1 | AP97: =IF(AND(LEFT(E97,2)="AF",LEN(E97)=6),1,0) -> 1 | AQ97: =IF(OR(F97="CC",F97="CE",F97="TI",F97="PAS"),1,0) -> 1 | AR97: =IF(AND(ISNUMBER(G97),COUNTIF($G:$G,G97)=1),1,0) -> 1 | AS97: {=IF(AND(H97<>"",SUMPRODUCT(--ISNUMBER(FIND({0;1;2;3;4;5;6;7;8;9},H97)))=0),1,0)} -> 1 | AT97: {=IF(AND(I97<>"",SUMPRODUCT(--ISNUMBER(FIND({0;1;2;3;4;5;6;7;8;9},I97)))=0),1,0)} -> 1 | AU97: {=IF(AND(J97<>"",SUMPRODUCT(--ISNUMBER(FIND({0;1;2;3;4;5;6;7;8;9},J97)))=0),1,0)} -> 1 | AV97: =IF(OR(ISBLANK(K97),K97=""),1,IF(ISTEXT(K97),1,0)) -> 1 | AW97: =IF(AND(ISNUMBER(L97),L97<=TODAY()),1,0) -> 1 | AX97: =IF(AND(ISNUMBER(SEARCH("@",M97)),ISNUMBER(SEARCH(".",M97,SEARCH("@",M97)+2)),NOT(ISNUMBER(SEARCH(" ",M97)))),1,0) -> 1 | AY97: =IF(AND(ISNUMBER(N97),LEN(N97)=10),1,0) -> 1 | AZ97: =IF(LEN(TRIM(O97))>=10,1,0) -> 1 | BA97: =IF(OR(ISBLANK(O97),O97=""),1,IF(ISTEXT(O97),1,0)) -> 1 | BB97: =IF(OR(ISBLANK(P97),P97=""),1,IF(ISTEXT(P97),1,0)) -> 1 | BC97: =IF(AND(ISNUMBER(R97),R97<=TODAY()),1,0) -> 1 | BD97: =IF(OR(ISBLANK(S97),S97=""),1,IF(ISTEXT(S97),1,0)) -> 1 | BE97: =IF(OR(ISBLANK(T97),T97=""),1,IF(ISTEXT(T97),1,0)) -> 1 | BF97: =IF(AND(ISNUMBER(U97),U97>0),1,0) -> 1 | BG97: =IF(AND(ISNUMBER(V97),V97<=TODAY()),1,0) -> 1
A98: =IF(AND(W98=1,X98=1),1,0) -> 1 | B98: =IF(AND(Y98=1,Z98=1,AA98=1,AB98=1,AC98=1,AD98=1,AE98=1,AF98=1,AG98=1,AH98=1,AI98=1,AJ98=1,AK98=1,AL98=1,AM98=1,AN98=1,AO98=1),1,0) -> 1 | C98: =IF(AND(AP98=1,AQ98=1,AR98=1,AS98=1,AT98=1,AU98=1,AV98=1,AW98=1,AX98=1,AY98=1,AZ98=1,BA98=1,BB98=1,BC98=1,BD98=1,BE98=1,BF98=1,BG98=1),1,0) -> 1 | D98: =IF(SUM(A98:C98)<3,1,0) -> 0 | E98: AF0097 | F98: TI | G98: 1000000097 | H98: Andres | I98: Leon | J98: Restrepo | K98: M | L98: 34973 | M98: andres.leon97@email.com | N98: 3532297982 | O98: Calle 120 #32-16 | P98: Bogotá | Q98: Cundinamarca | R98: 45410 | S98: Retirado | T98: Call Center | U98: 95000 | V98: 45589 | W98: =IF(COUNTIF(E$2:E$201,E98)>1,0,1) -> 1 | X98: =IF(COUNTIF(G$2:G$201,G98)>1,0,1) -> 1 | Y98: =IF(E98="",0,1) -> 1 | Z98: =IF(F98="",0,1) -> 1 | AA98: =IF(G98="",0,1) -> 1 | AB98: =IF(H98="",0,1) -> 1 | AC98: =IF(I98="",0,1) -> 1 | AD98: =IF(K98="",0,1) -> 1 | AE98: =IF(L98="",0,1) -> 1 | AF98: =IF(M98="",0,1) -> 1 | AG98: =IF(N98="",0,1) -> 1 | AH98: =IF(O98="",0,1) -> 1 | AI98: =IF(P98="",0,1) -> 1 | AJ98: =IF(Q98="",0,1) -> 1 | AK98: =IF(R98="",0,1) -> 1 | ... AO98: =IF(V98="",0,1) -> 1 | AP98: =IF(AND(LEFT(E98,2)="AF",LEN(E98)=6),1,0) -> 1 | AQ98: =IF(OR(F98="CC",F98="CE",F98="TI",F98="PAS"),1,0) -> 1 | AR98: =IF(AND(ISNUMBER(G98),COUNTIF($G:$G,G98)=1),1,0) -> 1 | AS98: {=IF(AND(H98<>"",SUMPRODUCT(--ISNUMBER(FIND({0;1;2;3;4;5;6;7;8;9},H98)))=0),1,0)} -> 1 | AT98: {=IF(AND(I98<>"",SUMPRODUCT(--ISNUMBER(FIND({0;1;2;3;4;5;6;7;8;9},I98)))=0),1,0)} -> 1 | AU98: {=IF(AND(J98<>"",SUMPRODUCT(--ISNUMBER(FIND({0;1;2;3;4;5;6;7;8;9},J98)))=0),1,0)} -> 1 | AV98: =IF(OR(ISBLANK(K98),K98=""),1,IF(ISTEXT(K98),1,0)) -> 1 | AW98: =IF(AND(ISNUMBER(L98),L98<=TODAY()),1,0) -> 1 | AX98: =IF(AND(ISNUMBER(SEARCH("@",M98)),ISNUMBER(SEARCH(".",M98,SEARCH("@",M98)+2)),NOT(ISNUMBER(SEARCH(" ",M98)))),1,0) -> 1 | AY98: =IF(AND(ISNUMBER(N98),LEN(N98)=10),1,0) -> 1 | AZ98: =IF(LEN(TRIM(O98))>=10,1,0) -> 1 | BA98: =IF(OR(ISBLANK(O98),O98=""),1,IF(ISTEXT(O98),1,0)) -> 1 | BB98: =IF(OR(ISBLANK(P98),P98=""),1,IF(ISTEXT(P98),1,0)) -> 1 | BC98: =IF(AND(ISNUMBER(R98),R98<=TODAY()),1,0) -> 1 | BD98: =IF(OR(ISBLANK(S98),S98=""),1,IF(ISTEXT(S98),1,0)) -> 1 | BE98: =IF(OR(ISBLANK(T98),T98=""),1,IF(ISTEXT(T98),1,0)) -> 1 | BF98: =IF(AND(ISNUMBER(U98),U98>0),1,0) -> 1 | BG98: =IF(AND(ISNUMBER(V98),V98<=TODAY()),1,0) -> 1
A99: =IF(AND(W99=1,X99=1),1,0) -> 1 | B99: =IF(AND(Y99=1,Z99=1,AA99=1,AB99=1,AC99=1,AD99=1,AE99=1,AF99=1,AG99=1,AH99=1,AI99=1,AJ99=1,AK99=1,AL99=1,AM99=1,AN99=1,AO99=1),1,0) -> 1 | C99: =IF(AND(AP99=1,AQ99=1,AR99=1,AS99=1,AT99=1,AU99=1,AV99=1,AW99=1,AX99=1,AY99=1,AZ99=1,BA99=1,BB99=1,BC99=1,BD99=1,BE99=1,BF99=1,BG99=1),1,0) -> 1 | D99: =IF(SUM(A99:C99)<3,1,0) -> 0 | E99: AF0098 | F99: CE | G99: 1000000098 | H99: Camila | I99: Torres | J99: Salazar | K99: F | L99: 33258 | M99: camila.torres98@email.com | N99: 3200980240 | O99: Calle 68 #79-21 | P99: Manizales | Q99: Caldas | R99: 44700 | S99: Retirado | T99: Web | U99: 85000 | V99: 44880 | W99: =IF(COUNTIF(E$2:E$201,E99)>1,0,1) -> 1 | X99: =IF(COUNTIF(G$2:G$201,G99)>1,0,1) -> 1 | Y99: =IF(E99="",0,1) -> 1 | Z99: =IF(F99="",0,1) -> 1 | AA99: =IF(G99="",0,1) -> 1 | AB99: =IF(H99="",0,1) -> 1 | AC99: =IF(I99="",0,1) -> 1 | AD99: =IF(K99="",0,1) -> 1 | AE99: =IF(L99="",0,1) -> 1 | AF99: =IF(M99="",0,1) -> 1 | AG99: =IF(N99="",0,1) -> 1 | AH99: =IF(O99="",0,1) -> 1 | AI99: =IF(P99="",0,1) -> 1 | AJ99: =IF(Q99="",0,1) -> 1 | AK99: =IF(R99="",0,1) -> 1 | ... AO99: =IF(V99="",0,1) -> 1 | AP99: =IF(AND(LEFT(E99,2)="AF",LEN(E99)=6),1,0) -> 1 | AQ99: =IF(OR(F99="CC",F99="CE",F99="TI",F99="PAS"),1,0) -> 1 | AR99: =IF(AND(ISNUMBER(G99),COUNTIF($G:$G,G99)=1),1,0) -> 1 | AS99: {=IF(AND(H99<>"",SUMPRODUCT(--ISNUMBER(FIND({0;1;2;3;4;5;6;7;8;9},H99)))=0),1,0)} -> 1 | AT99: {=IF(AND(I99<>"",SUMPRODUCT(--ISNUMBER(FIND({0;1;2;3;4;5;6;7;8;9},I99)))=0),1,0)} -> 1 | AU99: {=IF(AND(J99<>"",SUMPRODUCT(--ISNUMBER(FIND({0;1;2;3;4;5;6;7;8;9},J99)))=0),1,0)} -> 1 | AV99: =IF(OR(ISBLANK(K99),K99=""),1,IF(ISTEXT(K99),1,0)) -> 1 | AW99: =IF(AND(ISNUMBER(L99),L99<=TODAY()),1,0) -> 1 | AX99: =IF(AND(ISNUMBER(SEARCH("@",M99)),ISNUMBER(SEARCH(".",M99,SEARCH("@",M99)+2)),NOT(ISNUMBER(SEARCH(" ",M99)))),1,0) -> 1 | AY99: =IF(AND(ISNUMBER(N99),LEN(N99)=10),1,0) -> 1 | AZ99: =IF(LEN(TRIM(O99))>=10,1,0) -> 1 | BA99: =IF(OR(ISBLANK(O99),O99=""),1,IF(ISTEXT(O99),1,0)) -> 1 | BB99: =IF(OR(ISBLANK(P99),P99=""),1,IF(ISTEXT(P99),1,0)) -> 1 | BC99: =IF(AND(ISNUMBER(R99),R99<=TODAY()),1,0) -> 1 | BD99: =IF(OR(ISBLANK(S99),S99=""),1,IF(ISTEXT(S99),1,0)) -> 1 | BE99: =IF(OR(ISBLANK(T99),T99=""),1,IF(ISTEXT(T99),1,0)) -> 1 | BF99: =IF(AND(ISNUMBER(U99),U99>0),1,0) -> 1 | BG99: =IF(AND(ISNUMBER(V99),V99<=TODAY()),1,0) -> 1
A100: =IF(AND(W100=1,X100=1),1,0) -> 1 | B100: =IF(AND(Y100=1,Z100=1,AA100=1,AB100=1,AC100=1,AD100=1,AE100=1,AF100=1,AG100=1,AH100=1,AI100=1,AJ100=1,AK100=1,AL100=1,AM100=1,AN100=1,AO100=1),1,0) -> 1 | C100: =IF(AND(AP100=1,AQ100=1,AR100=1,AS100=1,AT100=1,AU100=1,AV100=1,AW100=1,AX100=1,AY100=1,AZ100=1,BA100=1,BB100=1,BC100=1,BD100=1,BE100=1,BF100=1,BG100=1),1,0) -> 1 | D100: =IF(SUM(A100:C100)<3,1,0) -> 0 | E100: AF0099 | F100: TI | G100: 1000000099 | H100: Paula | I100: Ramirez | J100: Salazar | K100: F | L100: 23946 | M100: paula.ramirez99@email.com | N100: 3668867468 | O100: Calle 80 #73-15 | P100: Manizales | Q100: Caldas | R100: 44811 | S100: Suspendido | T100: Web | U100: 95000 | V100: 44942 | W100: =IF(COUNTIF(E$2:E$201,E100)>1,0,1) -> 1 | X100: =IF(COUNTIF(G$2:G$201,G100)>1,0,1) -> 1 | Y100: =IF(E100="",0,1) -> 1 | Z100: =IF(F100="",0,1) -> 1 | AA100: =IF(G100="",0,1) -> 1 | AB100: =IF(H100="",0,1) -> 1 | AC100: =IF(I100="",0,1) -> 1 | AD100: =IF(K100="",0,1) -> 1 | AE100: =IF(L100="",0,1) -> 1 | AF100: =IF(M100="",0,1) -> 1 | AG100: =IF(N100="",0,1) -> 1 | AH100: =IF(O100="",0,1) -> 1 | AI100: =IF(P100="",0,1) -> 1 | AJ100: =IF(Q100="",0,1) -> 1 | AK100: =IF(R100="",0,1) -> 1 | ... AO100: =IF(V100="",0,1) -> 1 | AP100: =IF(AND(LEFT(E100,2)="AF",LEN(E100)=6),1,0) -> 1 | AQ100: =IF(OR(F100="CC",F100="CE",F100="TI",F100="PAS"),1,0) -> 1 | AR100: =IF(AND(ISNUMBER(G100),COUNTIF($G:$G,G100)=1),1,0) -> 1 | AS100: {=IF(AND(H100<>"",SUMPRODUCT(--ISNUMBER(FIND({0;1;2;3;4;5;6;7;8;9},H100)))=0),1,0)} -> 1 | AT100: {=IF(AND(I100<>"",SUMPRODUCT(--ISNUMBER(FIND({0;1;2;3;4;5;6;7;8;9},I100)))=0),1,0)} -> 1 | AU100: {=IF(AND(J100<>"",SUMPRODUCT(--ISNUMBER(FIND({0;1;2;3;4;5;6;7;8;9},J100)))=0),1,0)} -> 1 | AV100: =IF(OR(ISBLANK(K100),K100=""),1,IF(ISTEXT(K100),1,0)) -> 1 | AW100: =IF(AND(ISNUMBER(L100),L100<=TODAY()),1,0) -> 1 | AX100: =IF(AND(ISNUMBER(SEARCH("@",M100)),ISNUMBER(SEARCH(".",M100,SEARCH("@",M100)+2)),NOT(ISNUMBER(SEARCH(" ",M100)))),1,0) -> 1 | AY100: =IF(AND(ISNUMBER(N100),LEN(N100)=10),1,0) -> 1 | AZ100: =IF(LEN(TRIM(O100))>=10,1,0) -> 1 | BA100: =IF(OR(ISBLANK(O100),O100=""),1,IF(ISTEXT(O100),1,0)) -> 1 | BB100: =IF(OR(ISBLANK(P100),P100=""),1,IF(ISTEXT(P100),1,0)) -> 1 | BC100: =IF(AND(ISNUMBER(R100),R100<=TODAY()),1,0) -> 1 | BD100: =IF(OR(ISBLANK(S100),S100=""),1,IF(ISTEXT(S100),1,0)) -> 1 | BE100: =IF(OR(ISBLANK(T100),T100=""),1,IF(ISTEXT(T100),1,0)) -> 1 | BF100: =IF(AND(ISNUMBER(U100),U100>0),1,0) -> 1 | BG100: =IF(AND(ISNUMBER(V100),V100<=TODAY()),1,0) -> 1
A101: =IF(AND(W101=1,X101=1),1,0) -> 1 | B101: =IF(AND(Y101=1,Z101=1,AA101=1,AB101=1,AC101=1,AD101=1,AE101=1,AF101=1,AG101=1,AH101=1,AI101=1,AJ101=1,AK101=1,AL101=1,AM101=1,AN101=1,AO101=1),1,0) -> 1 | C101: =IF(AND(AP101=1,AQ101=1,AR101=1,AS101=1,AT101=1,AU101=1,AV101=1,AW101=1,AX101=1,AY101=1,AZ101=1,BA101=1,BB101=1,BC101=1,BD101=1,BE101=1,BF101=1,BG101=1),1,0) -> 1 | D101: =IF(SUM(A101:C101)<3,1,0) -> 0 | E101: AF0100 | F101: CE | G101: 1000000100 | H101: Nicolas | I101: Herrera | J101: Ramirez | K101: M | L101: 24551 | M101: nicolas.herrera100@email.com | N101: 3461859528 | O101: Calle 64 #82-57 | P101: Bogotá | Q101: Cundinamarca | R101: 44642 | S101: Retirado | T101: Call Center | U101: 85000 | V101: 44747 | W101: =IF(COUNTIF(E$2:E$201,E101)>1,0,1) -> 1 | X101: =IF(COUNTIF(G$2:G$201,G101)>1,0,1) -> 1 | Y101: =IF(E101="",0,1) -> 1 | Z101: =IF(F101="",0,1) -> 1 | AA101: =IF(G101="",0,1) -> 1 | AB101: =IF(H101="",0,1) -> 1 | AC101: =IF(I101="",0,1) -> 1 | AD101: =IF(K101="",0,1) -> 1 | AE101: =IF(L101="",0,1) -> 1 | AF101: =IF(M101="",0,1) -> 1 | AG101: =IF(N101="",0,1) -> 1 | AH101: =IF(O101="",0,1) -> 1 | AI101: =IF(P101="",0,1) -> 1 | AJ101: =IF(Q101="",0,1) -> 1 | AK101: =IF(R101="",0,1) -> 1 | ... AO101: =IF(V101="",0,1) -> 1 | AP101: =IF(AND(LEFT(E101,2)="AF",LEN(E101)=6),1,0) -> 1 | AQ101: =IF(OR(F101="CC",F101="CE",F101="TI",F101="PAS"),1,0) -> 1 | AR101: =IF(AND(ISNUMBER(G101),COUNTIF($G:$G,G101)=1),1,0) -> 1 | AS101: {=IF(AND(H101<>"",SUMPRODUCT(--ISNUMBER(FIND({0;1;2;3;4;5;6;7;8;9},H101)))=0),1,0)} -> 1 | AT101: {=IF(AND(I101<>"",SUMPRODUCT(--ISNUMBER(FIND({0;1;2;3;4;5;6;7;8;9},I101)))=0),1,0)} -> 1 | AU101: {=IF(AND(J101<>"",SUMPRODUCT(--ISNUMBER(FIND({0;1;2;3;4;5;6;7;8;9},J101)))=0),1,0)} -> 1 | AV101: =IF(OR(ISBLANK(K101),K101=""),1,IF(ISTEXT(K101),1,0)) -> 1 | AW101: =IF(AND(ISNUMBER(L101),L101<=TODAY()),1,0) -> 1 | AX101: =IF(AND(ISNUMBER(SEARCH("@",M101)),ISNUMBER(SEARCH(".",M101,SEARCH("@",M101)+2)),NOT(ISNUMBER(SEARCH(" ",M101)))),1,0) -> 1 | AY101: =IF(AND(ISNUMBER(N101),LEN(N101)=10),1,0) -> 1 | AZ101: =IF(LEN(TRIM(O101))>=10,1,0) -> 1 | BA101: =IF(OR(ISBLANK(O101),O101=""),1,IF(ISTEXT(O101),1,0)) -> 1 | BB101: =IF(OR(ISBLANK(P101),P101=""),1,IF(ISTEXT(P101),1,0)) -> 1 | BC101: =IF(AND(ISNUMBER(R101),R101<=TODAY()),1,0) -> 1 | BD101: =IF(OR(ISBLANK(S101),S101=""),1,IF(ISTEXT(S101),1,0)) -> 1 | BE101: =IF(OR(ISBLANK(T101),T101=""),1,IF(ISTEXT(T101),1,0)) -> 1 | BF101: =IF(AND(ISNUMBER(U101),U101>0),1,0) -> 1 | BG101: =IF(AND(ISNUMBER(V101),V101<=TODAY()),1,0) -> 1
A102: =IF(AND(W102=1,X102=1),1,0) -> 1 | B102: =IF(AND(Y102=1,Z102=1,AA102=1,AB102=1,AC102=1,AD102=1,AE102=1,AF102=1,AG102=1,AH102=1,AI102=1,AJ102=1,AK102=1,AL102=1,AM102=1,AN102=1,AO102=1),1,0) -> 1 | C102: =IF(AND(AP102=1,AQ102=1,AR102=1,AS102=1,AT102=1,AU102=1,AV102=1,AW102=1,AX102=1,AY102=1,AZ102=1,BA102=1,BB102=1,BC102=1,BD102=1,BE102=1,BF102=1,BG102=1),1,0) -> 1 | D102: =IF(SUM(A102:C102)<3,1,0) -> 0 | E102: AF0101 | F102: CC | G102: 1000000101 | H102: Daniela | I102: Lopez | J102: Torres | K102: F | L102: 31311 | M102: daniela.lopez101@email.com | N102: 3643062452 | O102: Calle 109 #8-89 | P102: Cali | Q102: Valle del Cauca | R102: 45853 | S102: Retirado | T102: Presencial | U102: 95000 | V102: 46036 | W102: =IF(COUNTIF(E$2:E$201,E102)>1,0,1) -> 1 | X102: =IF(COUNTIF(G$2:G$201,G102)>1,0,1) -> 1 | Y102: =IF(E102="",0,1) -> 1 | Z102: =IF(F102="",0,1) -> 1 | AA102: =IF(G102="",0,1) -> 1 | AB102: =IF(H102="",0,1) -> 1 | AC102: =IF(I102="",0,1) -> 1 | AD102: =IF(K102="",0,1) -> 1 | AE102: =IF(L102="",0,1) -> 1 | AF102: =IF(M102="",0,1) -> 1 | AG102: =IF(N102="",0,1) -> 1 | AH102: =IF(O102="",0,1) -> 1 | AI102: =IF(P102="",0,1) -> 1 | AJ102: =IF(Q102="",0,1) -> 1 | AK102: =IF(R102="",0,1) -> 1 | ... AO102: =IF(V102="",0,1) -> 1 | AP102: =IF(AND(LEFT(E102,2)="AF",LEN(E102)=6),1,0) -> 1 | AQ102: =IF(OR(F102="CC",F102="CE",F102="TI",F102="PAS"),1,0) -> 1 | AR102: =IF(AND(ISNUMBER(G102),COUNTIF($G:$G,G102)=1),1,0) -> 1 | AS102: {=IF(AND(H102<>"",SUMPRODUCT(--ISNUMBER(FIND({0;1;2;3;4;5;6;7;8;9},H102)))=0),1,0)} -> 1 | AT102: {=IF(AND(I102<>"",SUMPRODUCT(--ISNUMBER(FIND({0;1;2;3;4;5;6;7;8;9},I102)))=0),1,0)} -> 1 | AU102: {=IF(AND(J102<>"",SUMPRODUCT(--ISNUMBER(FIND({0;1;2;3;4;5;6;7;8;9},J102)))=0),1,0)} -> 1 | AV102: =IF(OR(ISBLANK(K102),K102=""),1,IF(ISTEXT(K102),1,0)) -> 1 | AW102: =IF(AND(ISNUMBER(L102),L102<=TODAY()),1,0) -> 1 | AX102: =IF(AND(ISNUMBER(SEARCH("@",M102)),ISNUMBER(SEARCH(".",M102,SEARCH("@",M102)+2)),NOT(ISNUMBER(SEARCH(" ",M102)))),1,0) -> 1 | AY102: =IF(AND(ISNUMBER(N102),LEN(N102)=10),1,0) -> 1 | AZ102: =IF(LEN(TRIM(O102))>=10,1,0) -> 1 | BA102: =IF(OR(ISBLANK(O102),O102=""),1,IF(ISTEXT(O102),1,0)) -> 1 | BB102: =IF(OR(ISBLANK(P102),P102=""),1,IF(ISTEXT(P102),1,0)) -> 1 | BC102: =IF(AND(ISNUMBER(R102),R102<=TODAY()),1,0) -> 1 | BD102: =IF(OR(ISBLANK(S102),S102=""),1,IF(ISTEXT(S102),1,0)) -> 1 | BE102: =IF(OR(ISBLANK(T102),T102=""),1,IF(ISTEXT(T102),1,0)) -> 1 | BF102: =IF(AND(ISNUMBER(U102),U102>0),1,0) -> 1 | BG102: =IF(AND(ISNUMBER(V102),V102<=TODAY()),1,0) -> 1
A103: =IF(AND(W103=1,X103=1),1,0) -> 1 | B103: =IF(AND(Y103=1,Z103=1,AA103=1,AB103=1,AC103=1,AD103=1,AE103=1,AF103=1,AG103=1,AH103=1,AI103=1,AJ103=1,AK103=1,AL103=1,AM103=1,AN103=1,AO103=1),1,0) -> 1 | C103: =IF(AND(AP103=1,AQ103=1,AR103=1,AS103=1,AT103=1,AU103=1,AV103=1,AW103=1,AX103=1,AY103=1,AZ103=1,BA103=1,BB103=1,BC103=1,BD103=1,BE103=1,BF103=1,BG103=1),1,0) -> 0 | D103: =IF(SUM(A103:C103)<3,1,0) -> 1 | E103: AF0102 | F103: CC | G103: 1000000102 | H103: Javier | I103: Restrepo | J103: Martinez | K103: M | L103: 37793 | M103: javier.restrepo102@email.com | N103: 3951858984 | O103: Calle 23 #54-75 | P103: Cali | Q103: Valle del Cauca | R103: 45999 | S103: Retirado | T103: Web | U103: 95000 | V103: 46212 | W103: =IF(COUNTIF(E$2:E$201,E103)>1,0,1) -> 1 | X103: =IF(COUNTIF(G$2:G$201,G103)>1,0,1) -> 1 | Y103: =IF(E103="",0,1) -> 1 | Z103: =IF(F103="",0,1) -> 1 | AA103: =IF(G103="",0,1) -> 1 | AB103: =IF(H103="",0,1) -> 1 | AC103: =IF(I103="",0,1) -> 1 | AD103: =IF(K103="",0,1) -> 1 | AE103: =IF(L103="",0,1) -> 1 | AF103: =IF(M103="",0,1) -> 1 | AG103: =IF(N103="",0,1) -> 1 | AH103: =IF(O103="",0,1) -> 1 | AI103: =IF(P103="",0,1) -> 1 | AJ103: =IF(Q103="",0,1) -> 1 | AK103: =IF(R103="",0,1) -> 1 | ... AO103: =IF(V103="",0,1) -> 1 | AP103: =IF(AND(LEFT(E103,2)="AF",LEN(E103)=6),1,0) -> 1 | AQ103: =IF(OR(F103="CC",F103="CE",F103="TI",F103="PAS"),1,0) -> 1 | AR103: =IF(AND(ISNUMBER(G103),COUNTIF($G:$G,G103)=1),1,0) -> 1 | AS103: {=IF(AND(H103<>"",SUMPRODUCT(--ISNUMBER(FIND({0;1;2;3;4;5;6;7;8;9},H103)))=0),1,0)} -> 1 | AT103: {=IF(AND(I103<>"",SUMPRODUCT(--ISNUMBER(FIND({0;1;2;3;4;5;6;7;8;9},I103)))=0),1,0)} -> 1 | AU103: {=IF(AND(J103<>"",SUMPRODUCT(--ISNUMBER(FIND({0;1;2;3;4;5;6;7;8;9},J103)))=0),1,0)} -> 1 | AV103: =IF(OR(ISBLANK(K103),K103=""),1,IF(ISTEXT(K103),1,0)) -> 1 | AW103: =IF(AND(ISNUMBER(L103),L103<=TODAY()),1,0) -> 1 | AX103: =IF(AND(ISNUMBER(SEARCH("@",M103)),ISNUMBER(SEARCH(".",M103,SEARCH("@",M103)+2)),NOT(ISNUMBER(SEARCH(" ",M103)))),1,0) -> 1 | AY103: =IF(AND(ISNUMBER(N103),LEN(N103)=10),1,0) -> 1 | AZ103: =IF(LEN(TRIM(O103))>=10,1,0) -> 1 | BA103: =IF(OR(ISBLANK(O103),O103=""),1,IF(ISTEXT(O103),1,0)) -> 1 | BB103: =IF(OR(ISBLANK(P103),P103=""),1,IF(ISTEXT(P103),1,0)) -> 1 | BC103: =IF(AND(ISNUMBER(R103),R103<=TODAY()),1,0) -> 1 | BD103: =IF(OR(ISBLANK(S103),S103=""),1,IF(ISTEXT(S103),1,0)) -> 1 | BE103: =IF(OR(ISBLANK(T103),T103=""),1,IF(ISTEXT(T103),1,0)) -> 1 | BF103: =IF(AND(ISNUMBER(U103),U103>0),1,0) -> 1 | BG103: =IF(AND(ISNUMBER(V103),V103<=TODAY()),1,0) -> 0
... A171: =IF(AND(W171=1,X171=1),1,0) -> 1 | B171: =IF(AND(Y171=1,Z171=1,AA171=1,AB171=1,AC171=1,AD171=1,AE171=1,AF171=1,AG171=1,AH171=1,AI171=1,AJ171=1,AK171=1,AL171=1,AM171=1,AN171=1,AO171=1),1,0) -> 1 | C171: =IF(AND(AP171=1,AQ171=1,AR171=1,AS171=1,AT171=1,AU171=1,AV171=1,AW171=1,AX171=1,AY171=1,AZ171=1,BA171=1,BB171=1,BC171=1,BD171=1,BE171=1,BF171=1,BG171=1),1,0) -> 1 | D171: =IF(SUM(A171:C171)<3,1,0) -> 0 | E171: AF0170 | F171: TI | G171: 1000000170 | H171: Ana | I171: Perez | J171: Rodriguez | K171: F | L171: 27992 | M171: ana.perez170@email.com | N171: 3685054955 | O171: Calle 86 #42-47 | P171: Envigado | Q171: Antioquia | R171: 45581 | S171: Suspendido | T171: Web | U171: 75000 | V171: 45788 | W171: =IF(COUNTIF(E$2:E$201,E171)>1,0,1) -> 1 | X171: =IF(COUNTIF(G$2:G$201,G171)>1,0,1) -> 1 | Y171: =IF(E171="",0,1) -> 1 | Z171: =IF(F171="",0,1) -> 1 | AA171: =IF(G171="",0,1) -> 1 | AB171: =IF(H171="",0,1) -> 1 | AC171: =IF(I171="",0,1) -> 1 | AD171: =IF(K171="",0,1) -> 1 | AE171: =IF(L171="",0,1) -> 1 | AF171: =IF(M171="",0,1) -> 1 | AG171: =IF(N171="",0,1) -> 1 | AH171: =IF(O171="",0,1) -> 1 | AI171: =IF(P171="",0,1) -> 1 | AJ171: =IF(Q171="",0,1) -> 1 | AK171: =IF(R171="",0,1) -> 1 | ... AO171: =IF(V171="",0,1) -> 1 | AP171: =IF(AND(LEFT(E171,2)="AF",LEN(E171)=6),1,0) -> 1 | AQ171: =IF(OR(F171="CC",F171="CE",F171="TI",F171="PAS"),1,0) -> 1 | AR171: =IF(AND(ISNUMBER(G171),COUNTIF($G:$G,G171)=1),1,0) -> 1 | AS171: {=IF(AND(H171<>"",SUMPRODUCT(--ISNUMBER(FIND({0;1;2;3;4;5;6;7;8;9},H171)))=0),1,0)} -> 1 | AT171: {=IF(AND(I171<>"",SUMPRODUCT(--ISNUMBER(FIND({0;1;2;3;4;5;6;7;8;9},I171)))=0),1,0)} -> 1 | AU171: {=IF(AND(J171<>"",SUMPRODUCT(--ISNUMBER(FIND({0;1;2;3;4;5;6;7;8;9},J171)))=0),1,0)} -> 1 | AV171: =IF(OR(ISBLANK(K171),K171=""),1,IF(ISTEXT(K171),1,0)) -> 1 | AW171: =IF(AND(ISNUMBER(L171),L171<=TODAY()),1,0) -> 1 | AX171: =IF(AND(ISNUMBER(SEARCH("@",M171)),ISNUMBER(SEARCH(".",M171,SEARCH("@",M171)+2)),NOT(ISNUMBER(SEARCH(" ",M171)))),1,0) -> 1 | AY171: =IF(AND(ISNUMBER(N171),LEN(N171)=10),1,0) -> 1 | AZ171: =IF(LEN(TRIM(O171))>=10,1,0) -> 1 | BA171: =IF(OR(ISBLANK(O171),O171=""),1,IF(ISTEXT(O171),1,0)) -> 1 | BB171: =IF(OR(ISBLANK(P171),P171=""),1,IF(ISTEXT(P171),1,0)) -> 1 | BC171: =IF(AND(ISNUMBER(R171),R171<=TODAY()),1,0) -> 1 | BD171: =IF(OR(ISBLANK(S171),S171=""),1,IF(ISTEXT(S171),1,0)) -> 1 | BE171: =IF(OR(ISBLANK(T171),T171=""),1,IF(ISTEXT(T171),1,0)) -> 1 | BF171: =IF(AND(ISNUMBER(U171),U171>0),1,0) -> 1 | BG171: =IF(AND(ISNUMBER(V171),V171<=TODAY()),1,0) -> 1
A172: =IF(AND(W172=1,X172=1),1,0) -> 1 | B172: =IF(AND(Y172=1,Z172=1,AA172=1,AB172=1,AC172=1,AD172=1,AE172=1,AF172=1,AG172=1,AH172=1,AI172=1,AJ172=1,AK172=1,AL172=1,AM172=1,AN172=1,AO172=1),1,0) -> 0 | C172: =IF(AND(AP172=1,AQ172=1,AR172=1,AS172=1,AT172=1,AU172=1,AV172=1,AW172=1,AX172=1,AY172=1,AZ172=1,BA172=1,BB172=1,BC172=1,BD172=1,BE172=1,BF172=1,BG172=1),1,0) -> 0 | D172: =IF(SUM(A172:C172)<3,1,0) -> 1 | E172: AF0171 | F172: CE | G172: 1000000171 | H172: Juan | I172: Leon | J172: Rodriguez | K172: M | L172: 35739 | M172: juan.leon171@email.com | N172: 3114225264 | O172: Calle 48 #7-47 | P172: Manizales | Q172: Caldas | S172: Activo | T172: Call Center | U172: 90000 | V172: 44807 | W172: =IF(COUNTIF(E$2:E$201,E172)>1,0,1) -> 1 | X172: =IF(COUNTIF(G$2:G$201,G172)>1,0,1) -> 1 | Y172: =IF(E172="",0,1) -> 1 | Z172: =IF(F172="",0,1) -> 1 | AA172: =IF(G172="",0,1) -> 1 | AB172: =IF(H172="",0,1) -> 1 | AC172: =IF(I172="",0,1) -> 1 | AD172: =IF(K172="",0,1) -> 1 | AE172: =IF(L172="",0,1) -> 1 | AF172: =IF(M172="",0,1) -> 1 | AG172: =IF(N172="",0,1) -> 1 | AH172: =IF(O172="",0,1) -> 1 | AI172: =IF(P172="",0,1) -> 1 | AJ172: =IF(Q172="",0,1) -> 1 | AK172: =IF(R172="",0,1) -> 0 | ... AO172: =IF(V172="",0,1) -> 1 | AP172: =IF(AND(LEFT(E172,2)="AF",LEN(E172)=6),1,0) -> 1 | AQ172: =IF(OR(F172="CC",F172="CE",F172="TI",F172="PAS"),1,0) -> 1 | AR172: =IF(AND(ISNUMBER(G172),COUNTIF($G:$G,G172)=1),1,0) -> 1 | AS172: {=IF(AND(H172<>"",SUMPRODUCT(--ISNUMBER(FIND({0;1;2;3;4;5;6;7;8;9},H172)))=0),1,0)} -> 1 | AT172: {=IF(AND(I172<>"",SUMPRODUCT(--ISNUMBER(FIND({0;1;2;3;4;5;6;7;8;9},I172)))=0),1,0)} -> 1 | AU172: {=IF(AND(J172<>"",SUMPRODUCT(--ISNUMBER(FIND({0;1;2;3;4;5;6;7;8;9},J172)))=0),1,0)} -> 1 | AV172: =IF(OR(ISBLANK(K172),K172=""),1,IF(ISTEXT(K172),1,0)) -> 1 | AW172: =IF(AND(ISNUMBER(L172),L172<=TODAY()),1,0) -> 1 | AX172: =IF(AND(ISNUMBER(SEARCH("@",M172)),ISNUMBER(SEARCH(".",M172,SEARCH("@",M172)+2)),NOT(ISNUMBER(SEARCH(" ",M172)))),1,0) -> 1 | AY172: =IF(AND(ISNUMBER(N172),LEN(N172)=10),1,0) -> 1 | AZ172: =IF(LEN(TRIM(O172))>=10,1,0) -> 1 | BA172: =IF(OR(ISBLANK(O172),O172=""),1,IF(ISTEXT(O172),1,0)) -> 1 | BB172: =IF(OR(ISBLANK(P172),P172=""),1,IF(ISTEXT(P172),1,0)) -> 1 | BC172: =IF(AND(ISNUMBER(R172),R172<=TODAY()),1,0) -> 0 | BD172: =IF(OR(ISBLANK(S172),S172=""),1,IF(ISTEXT(S172),1,0)) -> 1 | BE172: =IF(OR(ISBLANK(T172),T172=""),1,IF(ISTEXT(T172),1,0)) -> 1 | BF172: =IF(AND(ISNUMBER(U172),U172>0),1,0) -> 1 | BG172: =IF(AND(ISNUMBER(V172),V172<=TODAY()),1,0) -> 1
A173: =IF(AND(W173=1,X173=1),1,0) -> 1 | B173: =IF(AND(Y173=1,Z173=1,AA173=1,AB173=1,AC173=1,AD173=1,AE173=1,AF173=1,AG173=1,AH173=1,AI173=1,AJ173=1,AK173=1,AL173=1,AM173=1,AN173=1,AO173=1),1,0) -> 1 | C173: =IF(AND(AP173=1,AQ173=1,AR173=1,AS173=1,AT173=1,AU173=1,AV173=1,AW173=1,AX173=1,AY173=1,AZ173=1,BA173=1,BB173=1,BC173=1,BD173=1,BE173=1,BF173=1,BG173=1),1,0) -> 0 | D173: =IF(SUM(A173:C173)<3,1,0) -> 1 | E173: AF0172 | F173: CC | G173: 1000000172 | H173: Paula | I173: Torres | J173: Ramirez | K173: F | L173: 29135 | M173: paula.torres172@email.com | N173: 3987939591 | O173: Calle 106 #19-19 | P173: Pereira | Q173: Risaralda | R173: 46023 | S173: Retirado | T173: Call Center | U173: 90000 | V173: 46273 | W173: =IF(COUNTIF(E$2:E$201,E173)>1,0,1) -> 1 | X173: =IF(COUNTIF(G$2:G$201,G173)>1,0,1) -> 1 | Y173: =IF(E173="",0,1) -> 1 | Z173: =IF(F173="",0,1) -> 1 | AA173: =IF(G173="",0,1) -> 1 | AB173: =IF(H173="",0,1) -> 1 | AC173: =IF(I173="",0,1) -> 1 | AD173: =IF(K173="",0,1) -> 1 | AE173: =IF(L173="",0,1) -> 1 | AF173: =IF(M173="",0,1) -> 1 | AG173: =IF(N173="",0,1) -> 1 | AH173: =IF(O173="",0,1) -> 1 | AI173: =IF(P173="",0,1) -> 1 | AJ173: =IF(Q173="",0,1) -> 1 | AK173: =IF(R173="",0,1) -> 1 | ... AO173: =IF(V173="",0,1) -> 1 | AP173: =IF(AND(LEFT(E173,2)="AF",LEN(E173)=6),1,0) -> 1 | AQ173: =IF(OR(F173="CC",F173="CE",F173="TI",F173="PAS"),1,0) -> 1 | AR173: =IF(AND(ISNUMBER(G173),COUNTIF($G:$G,G173)=1),1,0) -> 1 | AS173: {=IF(AND(H173<>"",SUMPRODUCT(--ISNUMBER(FIND({0;1;2;3;4;5;6;7;8;9},H173)))=0),1,0)} -> 1 | AT173: {=IF(AND(I173<>"",SUMPRODUCT(--ISNUMBER(FIND({0;1;2;3;4;5;6;7;8;9},I173)))=0),1,0)} -> 1 | AU173: {=IF(AND(J173<>"",SUMPRODUCT(--ISNUMBER(FIND({0;1;2;3;4;5;6;7;8;9},J173)))=0),1,0)} -> 1 | AV173: =IF(OR(ISBLANK(K173),K173=""),1,IF(ISTEXT(K173),1,0)) -> 1 | AW173: =IF(AND(ISNUMBER(L173),L173<=TODAY()),1,0) -> 1 | AX173: =IF(AND(ISNUMBER(SEARCH("@",M173)),ISNUMBER(SEARCH(".",M173,SEARCH("@",M173)+2)),NOT(ISNUMBER(SEARCH(" ",M173)))),1,0) -> 1 | AY173: =IF(AND(ISNUMBER(N173),LEN(N173)=10),1,0) -> 1 | AZ173: =IF(LEN(TRIM(O173))>=10,1,0) -> 1 | BA173: =IF(OR(ISBLANK(O173),O173=""),1,IF(ISTEXT(O173),1,0)) -> 1 | BB173: =IF(OR(ISBLANK(P173),P173=""),1,IF(ISTEXT(P173),1,0)) -> 1 | BC173: =IF(AND(ISNUMBER(R173),R173<=TODAY()),1,0) -> 1 | BD173: =IF(OR(ISBLANK(S173),S173=""),1,IF(ISTEXT(S173),1,0)) -> 1 | BE173: =IF(OR(ISBLANK(T173),T173=""),1,IF(ISTEXT(T173),1,0)) -> 1 | BF173: =IF(AND(ISNUMBER(U173),U173>0),1,0) -> 1 | BG173: =IF(AND(ISNUMBER(V173),V173<=TODAY()),1,0) -> 0
A174: =IF(AND(W174=1,X174=1),1,0) -> 1 | B174: =IF(AND(Y174=1,Z174=1,AA174=1,AB174=1,AC174=1,AD174=1,AE174=1,AF174=1,AG174=1,AH174=1,AI174=1,AJ174=1,AK174=1,AL174=1,AM174=1,AN174=1,AO174=1),1,0) -> 1 | C174: =IF(AND(AP174=1,AQ174=1,AR174=1,AS174=1,AT174=1,AU174=1,AV174=1,AW174=1,AX174=1,AY174=1,AZ174=1,BA174=1,BB174=1,BC174=1,BD174=1,BE174=1,BF174=1,BG174=1),1,0) -> 1 | D174: =IF(SUM(A174:C174)<3,1,0) -> 0 | E174: AF0173 | F174: CE | G174: 1000000173 | H174: Carlos | I174: Perez | J174: Diaz | K174: M | L174: 31942 | M174: carlos.perez173@email.com | N174: 3354825243 | O174: Calle 21 #6-95 | P174: Barranquilla | Q174: Atlántico | R174: 45109 | S174: Retirado | T174: Call Center | U174: 90000 | V174: 45341 | W174: =IF(COUNTIF(E$2:E$201,E174)>1,0,1) -> 1 | X174: =IF(COUNTIF(G$2:G$201,G174)>1,0,1) -> 1 | Y174: =IF(E174="",0,1) -> 1 | Z174: =IF(F174="",0,1) -> 1 | AA174: =IF(G174="",0,1) -> 1 | AB174: =IF(H174="",0,1) -> 1 | AC174: =IF(I174="",0,1) -> 1 | AD174: =IF(K174="",0,1) -> 1 | AE174: =IF(L174="",0,1) -> 1 | AF174: =IF(M174="",0,1) -> 1 | AG174: =IF(N174="",0,1) -> 1 | AH174: =IF(O174="",0,1) -> 1 | AI174: =IF(P174="",0,1) -> 1 | AJ174: =IF(Q174="",0,1) -> 1 | AK174: =IF(R174="",0,1) -> 1 | ... AO174: =IF(V174="",0,1) -> 1 | AP174: =IF(AND(LEFT(E174,2)="AF",LEN(E174)=6),1,0) -> 1 | AQ174: =IF(OR(F174="CC",F174="CE",F174="TI",F174="PAS"),1,0) -> 1 | AR174: =IF(AND(ISNUMBER(G174),COUNTIF($G:$G,G174)=1),1,0) -> 1 | AS174: {=IF(AND(H174<>"",SUMPRODUCT(--ISNUMBER(FIND({0;1;2;3;4;5;6;7;8;9},H174)))=0),1,0)} -> 1 | AT174: {=IF(AND(I174<>"",SUMPRODUCT(--ISNUMBER(FIND({0;1;2;3;4;5;6;7;8;9},I174)))=0),1,0)} -> 1 | AU174: {=IF(AND(J174<>"",SUMPRODUCT(--ISNUMBER(FIND({0;1;2;3;4;5;6;7;8;9},J174)))=0),1,0)} -> 1 | AV174: =IF(OR(ISBLANK(K174),K174=""),1,IF(ISTEXT(K174),1,0)) -> 1 | AW174: =IF(AND(ISNUMBER(L174),L174<=TODAY()),1,0) -> 1 | AX174: =IF(AND(ISNUMBER(SEARCH("@",M174)),ISNUMBER(SEARCH(".",M174,SEARCH("@",M174)+2)),NOT(ISNUMBER(SEARCH(" ",M174)))),1,0) -> 1 | AY174: =IF(AND(ISNUMBER(N174),LEN(N174)=10),1,0) -> 1 | AZ174: =IF(LEN(TRIM(O174))>=10,1,0) -> 1 | BA174: =IF(OR(ISBLANK(O174),O174=""),1,IF(ISTEXT(O174),1,0)) -> 1 | BB174: =IF(OR(ISBLANK(P174),P174=""),1,IF(ISTEXT(P174),1,0)) -> 1 | BC174: =IF(AND(ISNUMBER(R174),R174<=TODAY()),1,0) -> 1 | BD174: =IF(OR(ISBLANK(S174),S174=""),1,IF(ISTEXT(S174),1,0)) -> 1 | BE174: =IF(OR(ISBLANK(T174),T174=""),1,IF(ISTEXT(T174),1,0)) -> 1 | BF174: =IF(AND(ISNUMBER(U174),U174>0),1,0) -> 1 | BG174: =IF(AND(ISNUMBER(V174),V174<=TODAY()),1,0) -> 1
A175: =IF(AND(W175=1,X175=1),1,0) -> 1 | B175: =IF(AND(Y175=1,Z175=1,AA175=1,AB175=1,AC175=1,AD175=1,AE175=1,AF175=1,AG175=1,AH175=1,AI175=1,AJ175=1,AK175=1,AL175=1,AM175=1,AN175=1,AO175=1),1,0) -> 1 | C175: =IF(AND(AP175=1,AQ175=1,AR175=1,AS175=1,AT175=1,AU175=1,AV175=1,AW175=1,AX175=1,AY175=1,AZ175=1,BA175=1,BB175=1,BC175=1,BD175=1,BE175=1,BF175=1,BG175=1),1,0) -> 1 | D175: =IF(SUM(A175:C175)<3,1,0) -> 0 | E175: AF0174 | F175: TI | G175: 1000000174 | H175: Daniela | I175: Martinez | J175: Sanchez | K175: F | L175: 30916 | M175: daniela.martinez174@email.com | N175: 3509513842 | O175: Calle 14 #41-35 | P175: Envigado | Q175: Antioquia | R175: 44857 | S175: Suspendido | T175: Web | U175: 95000 | V175: 45012 | W175: =IF(COUNTIF(E$2:E$201,E175)>1,0,1) -> 1 | X175: =IF(COUNTIF(G$2:G$201,G175)>1,0,1) -> 1 | Y175: =IF(E175="",0,1) -> 1 | Z175: =IF(F175="",0,1) -> 1 | AA175: =IF(G175="",0,1) -> 1 | AB175: =IF(H175="",0,1) -> 1 | AC175: =IF(I175="",0,1) -> 1 | AD175: =IF(K175="",0,1) -> 1 | AE175: =IF(L175="",0,1) -> 1 | AF175: =IF(M175="",0,1) -> 1 | AG175: =IF(N175="",0,1) -> 1 | AH175: =IF(O175="",0,1) -> 1 | AI175: =IF(P175="",0,1) -> 1 | AJ175: =IF(Q175="",0,1) -> 1 | AK175: =IF(R175="",0,1) -> 1 | ... AO175: =IF(V175="",0,1) -> 1 | AP175: =IF(AND(LEFT(E175,2)="AF",LEN(E175)=6),1,0) -> 1 | AQ175: =IF(OR(F175="CC",F175="CE",F175="TI",F175="PAS"),1,0) -> 1 | AR175: =IF(AND(ISNUMBER(G175),COUNTIF($G:$G,G175)=1),1,0) -> 1 | AS175: {=IF(AND(H175<>"",SUMPRODUCT(--ISNUMBER(FIND({0;1;2;3;4;5;6;7;8;9},H175)))=0),1,0)} -> 1 | AT175: {=IF(AND(I175<>"",SUMPRODUCT(--ISNUMBER(FIND({0;1;2;3;4;5;6;7;8;9},I175)))=0),1,0)} -> 1 | AU175: {=IF(AND(J175<>"",SUMPRODUCT(--ISNUMBER(FIND({0;1;2;3;4;5;6;7;8;9},J175)))=0),1,0)} -> 1 | AV175: =IF(OR(ISBLANK(K175),K175=""),1,IF(ISTEXT(K175),1,0)) -> 1 | AW175: =IF(AND(ISNUMBER(L175),L175<=TODAY()),1,0) -> 1 | AX175: =IF(AND(ISNUMBER(SEARCH("@",M175)),ISNUMBER(SEARCH(".",M175,SEARCH("@",M175)+2)),NOT(ISNUMBER(SEARCH(" ",M175)))),1,0) -> 1 | AY175: =IF(AND(ISNUMBER(N175),LEN(N175)=10),1,0) -> 1 | AZ175: =IF(LEN(TRIM(O175))>=10,1,0) -> 1 | BA175: =IF(OR(ISBLANK(O175),O175=""),1,IF(ISTEXT(O175),1,0)) -> 1 | BB175: =IF(OR(ISBLANK(P175),P175=""),1,IF(ISTEXT(P175),1,0)) -> 1 | BC175: =IF(AND(ISNUMBER(R175),R175<=TODAY()),1,0) -> 1 | BD175: =IF(OR(ISBLANK(S175),S175=""),1,IF(ISTEXT(S175),1,0)) -> 1 | BE175: =IF(OR(ISBLANK(T175),T175=""),1,IF(ISTEXT(T175),1,0)) -> 1 | BF175: =IF(AND(ISNUMBER(U175),U175>0),1,0) -> 1 | BG175: =IF(AND(ISNUMBER(V175),V175<=TODAY()),1,0) -> 1
A176: =IF(AND(W176=1,X176=1),1,0) -> 1 | B176: =IF(AND(Y176=1,Z176=1,AA176=1,AB176=1,AC176=1,AD176=1,AE176=1,AF176=1,AG176=1,AH176=1,AI176=1,AJ176=1,AK176=1,AL176=1,AM176=1,AN176=1,AO176=1),1,0) -> 0 | C176: =IF(AND(AP176=1,AQ176=1,AR176=1,AS176=1,AT176=1,AU176=1,AV176=1,AW176=1,AX176=1,AY176=1,AZ176=1,BA176=1,BB176=1,BC176=1,BD176=1,BE176=1,BF176=1,BG176=1),1,0) -> 0 | D176: =IF(SUM(A176:C176)<3,1,0) -> 1 | E176: AF0175 | F176: CE | G176: 1000000175 | H176: Ricardo | I176: Rodriguez | J176: Lopez | K176: M | L176: 35482 | M176: ricardo.rodriguez175@email.com | N176: 3791343029 | O176: Calle 75 #54-97 | P176: Pereira | Q176: Risaralda | S176: Activo | T176: Call Center | U176: 90000 | V176: 45842 | W176: =IF(COUNTIF(E$2:E$201,E176)>1,0,1) -> 1 | X176: =IF(COUNTIF(G$2:G$201,G176)>1,0,1) -> 1 | Y176: =IF(E176="",0,1) -> 1 | Z176: =IF(F176="",0,1) -> 1 | AA176: =IF(G176="",0,1) -> 1 | AB176: =IF(H176="",0,1) -> 1 | AC176: =IF(I176="",0,1) -> 1 | AD176: =IF(K176="",0,1) -> 1 | AE176: =IF(L176="",0,1) -> 1 | AF176: =IF(M176="",0,1) -> 1 | AG176: =IF(N176="",0,1) -> 1 | AH176: =IF(O176="",0,1) -> 1 | AI176: =IF(P176="",0,1) -> 1 | AJ176: =IF(Q176="",0,1) -> 1 | AK176: =IF(R176="",0,1) -> 0 | ... AO176: =IF(V176="",0,1) -> 1 | AP176: =IF(AND(LEFT(E176,2)="AF",LEN(E176)=6),1,0) -> 1 | AQ176: =IF(OR(F176="CC",F176="CE",F176="TI",F176="PAS"),1,0) -> 1 | AR176: =IF(AND(ISNUMBER(G176),COUNTIF($G:$G,G176)=1),1,0) -> 1 | AS176: {=IF(AND(H176<>"",SUMPRODUCT(--ISNUMBER(FIND({0;1;2;3;4;5;6;7;8;9},H176)))=0),1,0)} -> 1 | AT176: {=IF(AND(I176<>"",SUMPRODUCT(--ISNUMBER(FIND({0;1;2;3;4;5;6;7;8;9},I176)))=0),1,0)} -> 1 | AU176: {=IF(AND(J176<>"",SUMPRODUCT(--ISNUMBER(FIND({0;1;2;3;4;5;6;7;8;9},J176)))=0),1,0)} -> 1 | AV176: =IF(OR(ISBLANK(K176),K176=""),1,IF(ISTEXT(K176),1,0)) -> 1 | AW176: =IF(AND(ISNUMBER(L176),L176<=TODAY()),1,0) -> 1 | AX176: =IF(AND(ISNUMBER(SEARCH("@",M176)),ISNUMBER(SEARCH(".",M176,SEARCH("@",M176)+2)),NOT(ISNUMBER(SEARCH(" ",M176)))),1,0) -> 1 | AY176: =IF(AND(ISNUMBER(N176),LEN(N176)=10),1,0) -> 1 | AZ176: =IF(LEN(TRIM(O176))>=10,1,0) -> 1 | BA176: =IF(OR(ISBLANK(O176),O176=""),1,IF(ISTEXT(O176),1,0)) -> 1 | BB176: =IF(OR(ISBLANK(P176),P176=""),1,IF(ISTEXT(P176),1,0)) -> 1 | BC176: =IF(AND(ISNUMBER(R176),R176<=TODAY()),1,0) -> 0 | BD176: =IF(OR(ISBLANK(S176),S176=""),1,IF(ISTEXT(S176),1,0)) -> 1 | BE176: =IF(OR(ISBLANK(T176),T176=""),1,IF(ISTEXT(T176),1,0)) -> 1 | BF176: =IF(AND(ISNUMBER(U176),U176>0),1,0) -> 1 | BG176: =IF(AND(ISNUMBER(V176),V176<=TODAY()),1,0) -> 1
A177: =IF(AND(W177=1,X177=1),1,0) -> 1 | B177: =IF(AND(Y177=1,Z177=1,AA177=1,AB177=1,AC177=1,AD177=1,AE177=1,AF177=1,AG177=1,AH177=1,AI177=1,AJ177=1,AK177=1,AL177=1,AM177=1,AN177=1,AO177=1),1,0) -> 1 | C177: =IF(AND(AP177=1,AQ177=1,AR177=1,AS177=1,AT177=1,AU177=1,AV177=1,AW177=1,AX177=1,AY177=1,AZ177=1,BA177=1,BB177=1,BC177=1,BD177=1,BE177=1,BF177=1,BG177=1),1,0) -> 0 | D177: =IF(SUM(A177:C177)<3,1,0) -> 1 | E177: AF0176 | F177: CE | G177: 1000000176 | H177: Natalia | I177: Perez | J177: Martinez | K177: F | L177: 30107 | M177: natalia.perez176@email.com | N177: 3985287386 | O177: Calle 1 #70-2 | P177: Envigado | Q177: Antioquia | R177: 46150 | S177: Suspendido | T177: Web | U177: 90000 | V177: 46347 | W177: =IF(COUNTIF(E$2:E$201,E177)>1,0,1) -> 1 | X177: =IF(COUNTIF(G$2:G$201,G177)>1,0,1) -> 1 | Y177: =IF(E177="",0,1) -> 1 | Z177: =IF(F177="",0,1) -> 1 | AA177: =IF(G177="",0,1) -> 1 | AB177: =IF(H177="",0,1) -> 1 | AC177: =IF(I177="",0,1) -> 1 | AD177: =IF(K177="",0,1) -> 1 | AE177: =IF(L177="",0,1) -> 1 | AF177: =IF(M177="",0,1) -> 1 | AG177: =IF(N177="",0,1) -> 1 | AH177: =IF(O177="",0,1) -> 1 | AI177: =IF(P177="",0,1) -> 1 | AJ177: =IF(Q177="",0,1) -> 1 | AK177: =IF(R177="",0,1) -> 1 | ... AO177: =IF(V177="",0,1) -> 1 | AP177: =IF(AND(LEFT(E177,2)="AF",LEN(E177)=6),1,0) -> 1 | AQ177: =IF(OR(F177="CC",F177="CE",F177="TI",F177="PAS"),1,0) -> 1 | AR177: =IF(AND(ISNUMBER(G177),COUNTIF($G:$G,G177)=1),1,0) -> 1 | AS177: {=IF(AND(H177<>"",SUMPRODUCT(--ISNUMBER(FIND({0;1;2;3;4;5;6;7;8;9},H177)))=0),1,0)} -> 1 | AT177: {=IF(AND(I177<>"",SUMPRODUCT(--ISNUMBER(FIND({0;1;2;3;4;5;6;7;8;9},I177)))=0),1,0)} -> 1 | AU177: {=IF(AND(J177<>"",SUMPRODUCT(--ISNUMBER(FIND({0;1;2;3;4;5;6;7;8;9},J177)))=0),1,0)} -> 1 | AV177: =IF(OR(ISBLANK(K177),K177=""),1,IF(ISTEXT(K177),1,0)) -> 1 | AW177: =IF(AND(ISNUMBER(L177),L177<=TODAY()),1,0) -> 1 | AX177: =IF(AND(ISNUMBER(SEARCH("@",M177)),ISNUMBER(SEARCH(".",M177,SEARCH("@",M177)+2)),NOT(ISNUMBER(SEARCH(" ",M177)))),1,0) -> 1 | AY177: =IF(AND(ISNUMBER(N177),LEN(N177)=10),1,0) -> 1 | AZ177: =IF(LEN(TRIM(O177))>=10,1,0) -> 1 | BA177: =IF(OR(ISBLANK(O177),O177=""),1,IF(ISTEXT(O177),1,0)) -> 1 | BB177: =IF(OR(ISBLANK(P177),P177=""),1,IF(ISTEXT(P177),1,0)) -> 1 | BC177: =IF(AND(ISNUMBER(R177),R177<=TODAY()),1,0) -> 1 | BD177: =IF(OR(ISBLANK(S177),S177=""),1,IF(ISTEXT(S177),1,0)) -> 1 | BE177: =IF(OR(ISBLANK(T177),T177=""),1,IF(ISTEXT(T177),1,0)) -> 1 | BF177: =IF(AND(ISNUMBER(U177),U177>0),1,0) -> 1 | BG177: =IF(AND(ISNUMBER(V177),V177<=TODAY()),1,0) -> 0
A178: =IF(AND(W178=1,X178=1),1,0) -> 1 | B178: =IF(AND(Y178=1,Z178=1,AA178=1,AB178=1,AC178=1,AD178=1,AE178=1,AF178=1,AG178=1,AH178=1,AI178=1,AJ178=1,AK178=1,AL178=1,AM178=1,AN178=1,AO178=1),1,0) -> 1 | C178: =IF(AND(AP178=1,AQ178=1,AR178=1,AS178=1,AT178=1,AU178=1,AV178=1,AW178=1,AX178=1,AY178=1,AZ178=1,BA178=1,BB178=1,BC178=1,BD178=1,BE178=1,BF178=1,BG178=1),1,0) -> 1 | D178: =IF(SUM(A178:C178)<3,1,0) -> 0 | E178: AF0177 | F178: CC | G178: 1000000177 | H178: Ricardo | I178: Diaz | J178: Castro | K178: M | L178: 24057 | M178: ricardo.diaz177@email.com | N178: 3482465935 | O178: Calle 15 #95-66 | P178: Bogotá | Q178: Cundinamarca | R178: 45128 | S178: Retirado | T178: Web | U178: 90000 | V178: 45413 | W178: =IF(COUNTIF(E$2:E$201,E178)>1,0,1) -> 1 | X178: =IF(COUNTIF(G$2:G$201,G178)>1,0,1) -> 1 | Y178: =IF(E178="",0,1) -> 1 | Z178: =IF(F178="",0,1) -> 1 | AA178: =IF(G178="",0,1) -> 1 | AB178: =IF(H178="",0,1) -> 1 | AC178: =IF(I178="",0,1) -> 1 | AD178: =IF(K178="",0,1) -> 1 | AE178: =IF(L178="",0,1) -> 1 | AF178: =IF(M178="",0,1) -> 1 | AG178: =IF(N178="",0,1) -> 1 | AH178: =IF(O178="",0,1) -> 1 | AI178: =IF(P178="",0,1) -> 1 | AJ178: =IF(Q178="",0,1) -> 1 | AK178: =IF(R178="",0,1) -> 1 | ... AO178: =IF(V178="",0,1) -> 1 | AP178: =IF(AND(LEFT(E178,2)="AF",LEN(E178)=6),1,0) -> 1 | AQ178: =IF(OR(F178="CC",F178="CE",F178="TI",F178="PAS"),1,0) -> 1 | AR178: =IF(AND(ISNUMBER(G178),COUNTIF($G:$G,G178)=1),1,0) -> 1 | AS178: {=IF(AND(H178<>"",SUMPRODUCT(--ISNUMBER(FIND({0;1;2;3;4;5;6;7;8;9},H178)))=0),1,0)} -> 1 | AT178: {=IF(AND(I178<>"",SUMPRODUCT(--ISNUMBER(FIND({0;1;2;3;4;5;6;7;8;9},I178)))=0),1,0)} -> 1 | AU178: {=IF(AND(J178<>"",SUMPRODUCT(--ISNUMBER(FIND({0;1;2;3;4;5;6;7;8;9},J178)))=0),1,0)} -> 1 | AV178: =IF(OR(ISBLANK(K178),K178=""),1,IF(ISTEXT(K178),1,0)) -> 1 | AW178: =IF(AND(ISNUMBER(L178),L178<=TODAY()),1,0) -> 1 | AX178: =IF(AND(ISNUMBER(SEARCH("@",M178)),ISNUMBER(SEARCH(".",M178,SEARCH("@",M178)+2)),NOT(ISNUMBER(SEARCH(" ",M178)))),1,0) -> 1 | AY178: =IF(AND(ISNUMBER(N178),LEN(N178)=10),1,0) -> 1 | AZ178: =IF(LEN(TRIM(O178))>=10,1,0) -> 1 | BA178: =IF(OR(ISBLANK(O178),O178=""),1,IF(ISTEXT(O178),1,0)) -> 1 | BB178: =IF(OR(ISBLANK(P178),P178=""),1,IF(ISTEXT(P178),1,0)) -> 1 | BC178: =IF(AND(ISNUMBER(R178),R178<=TODAY()),1,0) -> 1 | BD178: =IF(OR(ISBLANK(S178),S178=""),1,IF(ISTEXT(S178),1,0)) -> 1 | BE178: =IF(OR(ISBLANK(T178),T178=""),1,IF(ISTEXT(T178),1,0)) -> 1 | BF178: =IF(AND(ISNUMBER(U178),U178>0),1,0) -> 1 | BG178: =IF(AND(ISNUMBER(V178),V178<=TODAY()),1,0) -> 1
A179: =IF(AND(W179=1,X179=1),1,0) -> 1 | B179: =IF(AND(Y179=1,Z179=1,AA179=1,AB179=1,AC179=1,AD179=1,AE179=1,AF179=1,AG179=1,AH179=1,AI179=1,AJ179=1,AK179=1,AL179=1,AM179=1,AN179=1,AO179=1),1,0) -> 1 | C179: =IF(AND(AP179=1,AQ179=1,AR179=1,AS179=1,AT179=1,AU179=1,AV179=1,AW179=1,AX179=1,AY179=1,AZ179=1,BA179=1,BB179=1,BC179=1,BD179=1,BE179=1,BF179=1,BG179=1),1,0) -> 1 | D179: =IF(SUM(A179:C179)<3,1,0) -> 0 | E179: AF0178 | F179: CC | G179: 1000000178 | H179: Felipe | I179: Torres | J179: Sanchez | K179: M | L179: 37109 | M179: felipe.torres178@email.com | N179: 3489451190 | O179: Calle 59 #62-89 | P179: Bogotá | Q179: Cundinamarca | R179: 45231 | S179: Suspendido | T179: Presencial | U179: 95000 | V179: 45342 | W179: =IF(COUNTIF(E$2:E$201,E179)>1,0,1) -> 1 | X179: =IF(COUNTIF(G$2:G$201,G179)>1,0,1) -> 1 | Y179: =IF(E179="",0,1) -> 1 | Z179: =IF(F179="",0,1) -> 1 | AA179: =IF(G179="",0,1) -> 1 | AB179: =IF(H179="",0,1) -> 1 | AC179: =IF(I179="",0,1) -> 1 | AD179: =IF(K179="",0,1) -> 1 | AE179: =IF(L179="",0,1) -> 1 | AF179: =IF(M179="",0,1) -> 1 | AG179: =IF(N179="",0,1) -> 1 | AH179: =IF(O179="",0,1) -> 1 | AI179: =IF(P179="",0,1) -> 1 | AJ179: =IF(Q179="",0,1) -> 1 | AK179: =IF(R179="",0,1) -> 1 | ... AO179: =IF(V179="",0,1) -> 1 | AP179: =IF(AND(LEFT(E179,2)="AF",LEN(E179)=6),1,0) -> 1 | AQ179: =IF(OR(F179="CC",F179="CE",F179="TI",F179="PAS"),1,0) -> 1 | AR179: =IF(AND(ISNUMBER(G179),COUNTIF($G:$G,G179)=1),1,0) -> 1 | AS179: {=IF(AND(H179<>"",SUMPRODUCT(--ISNUMBER(FIND({0;1;2;3;4;5;6;7;8;9},H179)))=0),1,0)} -> 1 | AT179: {=IF(AND(I179<>"",SUMPRODUCT(--ISNUMBER(FIND({0;1;2;3;4;5;6;7;8;9},I179)))=0),1,0)} -> 1 | AU179: {=IF(AND(J179<>"",SUMPRODUCT(--ISNUMBER(FIND({0;1;2;3;4;5;6;7;8;9},J179)))=0),1,0)} -> 1 | AV179: =IF(OR(ISBLANK(K179),K179=""),1,IF(ISTEXT(K179),1,0)) -> 1 | AW179: =IF(AND(ISNUMBER(L179),L179<=TODAY()),1,0) -> 1 | AX179: =IF(AND(ISNUMBER(SEARCH("@",M179)),ISNUMBER(SEARCH(".",M179,SEARCH("@",M179)+2)),NOT(ISNUMBER(SEARCH(" ",M179)))),1,0) -> 1 | AY179: =IF(AND(ISNUMBER(N179),LEN(N179)=10),1,0) -> 1 | AZ179: =IF(LEN(TRIM(O179))>=10,1,0) -> 1 | BA179: =IF(OR(ISBLANK(O179),O179=""),1,IF(ISTEXT(O179),1,0)) -> 1 | BB179: =IF(OR(ISBLANK(P179),P179=""),1,IF(ISTEXT(P179),1,0)) -> 1 | BC179: =IF(AND(ISNUMBER(R179),R179<=TODAY()),1,0) -> 1 | BD179: =IF(OR(ISBLANK(S179),S179=""),1,IF(ISTEXT(S179),1,0)) -> 1 | BE179: =IF(OR(ISBLANK(T179),T179=""),1,IF(ISTEXT(T179),1,0)) -> 1 | BF179: =IF(AND(ISNUMBER(U179),U179>0),1,0) -> 1 | BG179: =IF(AND(ISNUMBER(V179),V179<=TODAY()),1,0) -> 1
A180: =IF(AND(W180=1,X180=1),1,0) -> 1 | B180: =IF(AND(Y180=1,Z180=1,AA180=1,AB180=1,AC180=1,AD180=1,AE180=1,AF180=1,AG180=1,AH180=1,AI180=1,AJ180=1,AK180=1,AL180=1,AM180=1,AN180=1,AO180=1),1,0) -> 1 | C180: =IF(AND(AP180=1,AQ180=1,AR180=1,AS180=1,AT180=1,AU180=1,AV180=1,AW180=1,AX180=1,AY180=1,AZ180=1,BA180=1,BB180=1,BC180=1,BD180=1,BE180=1,BF180=1,BG180=1),1,0) -> 1 | D180: =IF(SUM(A180:C180)<3,1,0) -> 0 | E180: AF0179 | F180: CE | G180: 1000000179 | H180: Juan | I180: Gomez | J180: Torres | K180: M | L180: 32535 | M180: juan.gomez179@email.com | N180: 3386859325 | O180: Calle 27 #65-84 | P180: Manizales | Q180: Caldas | R180: 45067 | S180: Suspendido | T180: Web | U180: 85000 | V180: 45161 | W180: =IF(COUNTIF(E$2:E$201,E180)>1,0,1) -> 1 | X180: =IF(COUNTIF(G$2:G$201,G180)>1,0,1) -> 1 | Y180: =IF(E180="",0,1) -> 1 | Z180: =IF(F180="",0,1) -> 1 | AA180: =IF(G180="",0,1) -> 1 | AB180: =IF(H180="",0,1) -> 1 | AC180: =IF(I180="",0,1) -> 1 | AD180: =IF(K180="",0,1) -> 1 | AE180: =IF(L180="",0,1) -> 1 | AF180: =IF(M180="",0,1) -> 1 | AG180: =IF(N180="",0,1) -> 1 | AH180: =IF(O180="",0,1) -> 1 | AI180: =IF(P180="",0,1) -> 1 | AJ180: =IF(Q180="",0,1) -> 1 | AK180: =IF(R180="",0,1) -> 1 | ... AO180: =IF(V180="",0,1) -> 1 | AP180: =IF(AND(LEFT(E180,2)="AF",LEN(E180)=6),1,0) -> 1 | AQ180: =IF(OR(F180="CC",F180="CE",F180="TI",F180="PAS"),1,0) -> 1 | AR180: =IF(AND(ISNUMBER(G180),COUNTIF($G:$G,G180)=1),1,0) -> 1 | AS180: {=IF(AND(H180<>"",SUMPRODUCT(--ISNUMBER(FIND({0;1;2;3;4;5;6;7;8;9},H180)))=0),1,0)} -> 1 | AT180: {=IF(AND(I180<>"",SUMPRODUCT(--ISNUMBER(FIND({0;1;2;3;4;5;6;7;8;9},I180)))=0),1,0)} -> 1 | AU180: {=IF(AND(J180<>"",SUMPRODUCT(--ISNUMBER(FIND({0;1;2;3;4;5;6;7;8;9},J180)))=0),1,0)} -> 1 | AV180: =IF(OR(ISBLANK(K180),K180=""),1,IF(ISTEXT(K180),1,0)) -> 1 | AW180: =IF(AND(ISNUMBER(L180),L180<=TODAY()),1,0) -> 1 | AX180: =IF(AND(ISNUMBER(SEARCH("@",M180)),ISNUMBER(SEARCH(".",M180,SEARCH("@",M180)+2)),NOT(ISNUMBER(SEARCH(" ",M180)))),1,0) -> 1 | AY180: =IF(AND(ISNUMBER(N180),LEN(N180)=10),1,0) -> 1 | AZ180: =IF(LEN(TRIM(O180))>=10,1,0) -> 1 | BA180: =IF(OR(ISBLANK(O180),O180=""),1,IF(ISTEXT(O180),1,0)) -> 1 | BB180: =IF(OR(ISBLANK(P180),P180=""),1,IF(ISTEXT(P180),1,0)) -> 1 | BC180: =IF(AND(ISNUMBER(R180),R180<=TODAY()),1,0) -> 1 | BD180: =IF(OR(ISBLANK(S180),S180=""),1,IF(ISTEXT(S180),1,0)) -> 1 | BE180: =IF(OR(ISBLANK(T180),T180=""),1,IF(ISTEXT(T180),1,0)) -> 1 | BF180: =IF(AND(ISNUMBER(U180),U180>0),1,0) -> 1 | BG180: =IF(AND(ISNUMBER(V180),V180<=TODAY()),1,0) -> 1
A181: =IF(AND(W181=1,X181=1),1,0) -> 1 | B181: =IF(AND(Y181=1,Z181=1,AA181=1,AB181=1,AC181=1,AD181=1,AE181=1,AF181=1,AG181=1,AH181=1,AI181=1,AJ181=1,AK181=1,AL181=1,AM181=1,AN181=1,AO181=1),1,0) -> 1 | C181: =IF(AND(AP181=1,AQ181=1,AR181=1,AS181=1,AT181=1,AU181=1,AV181=1,AW181=1,AX181=1,AY181=1,AZ181=1,BA181=1,BB181=1,BC181=1,BD181=1,BE181=1,BF181=1,BG181=1),1,0) -> 1 | D181: =IF(SUM(A181:C181)<3,1,0) -> 0 | E181: AF0180 | F181: CC | G181: 1000000180 | H181: Laura | I181: Perez | J181: Ortiz | K181: F | L181: 34099 | M181: laura.perez180@email.com | N181: 3283416320 | O181: Calle 29 #38-71 | P181: Cali | Q181: Valle del Cauca | R181: 44780 | S181: Retirado | T181: Presencial | U181: 95000 | V181: 44864 | W181: =IF(COUNTIF(E$2:E$201,E181)>1,0,1) -> 1 | X181: =IF(COUNTIF(G$2:G$201,G181)>1,0,1) -> 1 | Y181: =IF(E181="",0,1) -> 1 | Z181: =IF(F181="",0,1) -> 1 | AA181: =IF(G181="",0,1) -> 1 | AB181: =IF(H181="",0,1) -> 1 | AC181: =IF(I181="",0,1) -> 1 | AD181: =IF(K181="",0,1) -> 1 | AE181: =IF(L181="",0,1) -> 1 | AF181: =IF(M181="",0,1) -> 1 | AG181: =IF(N181="",0,1) -> 1 | AH181: =IF(O181="",0,1) -> 1 | AI181: =IF(P181="",0,1) -> 1 | AJ181: =IF(Q181="",0,1) -> 1 | AK181: =IF(R181="",0,1) -> 1 | ... AO181: =IF(V181="",0,1) -> 1 | AP181: =IF(AND(LEFT(E181,2)="AF",LEN(E181)=6),1,0) -> 1 | AQ181: =IF(OR(F181="CC",F181="CE",F181="TI",F181="PAS"),1,0) -> 1 | AR181: =IF(AND(ISNUMBER(G181),COUNTIF($G:$G,G181)=1),1,0) -> 1 | AS181: {=IF(AND(H181<>"",SUMPRODUCT(--ISNUMBER(FIND({0;1;2;3;4;5;6;7;8;9},H181)))=0),1,0)} -> 1 | AT181: {=IF(AND(I181<>"",SUMPRODUCT(--ISNUMBER(FIND({0;1;2;3;4;5;6;7;8;9},I181)))=0),1,0)} -> 1 | AU181: {=IF(AND(J181<>"",SUMPRODUCT(--ISNUMBER(FIND({0;1;2;3;4;5;6;7;8;9},J181)))=0),1,0)} -> 1 | AV181: =IF(OR(ISBLANK(K181),K181=""),1,IF(ISTEXT(K181),1,0)) -> 1 | AW181: =IF(AND(ISNUMBER(L181),L181<=TODAY()),1,0) -> 1 | AX181: =IF(AND(ISNUMBER(SEARCH("@",M181)),ISNUMBER(SEARCH(".",M181,SEARCH("@",M181)+2)),NOT(ISNUMBER(SEARCH(" ",M181)))),1,0) -> 1 | AY181: =IF(AND(ISNUMBER(N181),LEN(N181)=10),1,0) -> 1 | AZ181: =IF(LEN(TRIM(O181))>=10,1,0) -> 1 | BA181: =IF(OR(ISBLANK(O181),O181=""),1,IF(ISTEXT(O181),1,0)) -> 1 | BB181: =IF(OR(ISBLANK(P181),P181=""),1,IF(ISTEXT(P181),1,0)) -> 1 | BC181: =IF(AND(ISNUMBER(R181),R181<=TODAY()),1,0) -> 1 | BD181: =IF(OR(ISBLANK(S181),S181=""),1,IF(ISTEXT(S181),1,0)) -> 1 | BE181: =IF(OR(ISBLANK(T181),T181=""),1,IF(ISTEXT(T181),1,0)) -> 1 | BF181: =IF(AND(ISNUMBER(U181),U181>0),1,0) -> 1 | BG181: =IF(AND(ISNUMBER(V181),V181<=TODAY()),1,0) -> 1
A182: =IF(AND(W182=1,X182=1),1,0) -> 1 | B182: =IF(AND(Y182=1,Z182=1,AA182=1,AB182=1,AC182=1,AD182=1,AE182=1,AF182=1,AG182=1,AH182=1,AI182=1,AJ182=1,AK182=1,AL182=1,AM182=1,AN182=1,AO182=1),1,0) -> 1 | C182: =IF(AND(AP182=1,AQ182=1,AR182=1,AS182=1,AT182=1,AU182=1,AV182=1,AW182=1,AX182=1,AY182=1,AZ182=1,BA182=1,BB182=1,BC182=1,BD182=1,BE182=1,BF182=1,BG182=1),1,0) -> 1 | D182: =IF(SUM(A182:C182)<3,1,0) -> 0 | E182: AF0181 | F182: TI | G182: 1000000181 | H182: Ana | I182: Ortiz | J182: Leon | K182: F | L182: 29966 | M182: ana.ortiz181@email.com | N182: 3706001094 | O182: Calle 7 #13-57 | P182: Manizales | Q182: Caldas | R182: 44562 | S182: Suspendido | T182: Presencial | U182: 90000 | V182: 44737 | W182: =IF(COUNTIF(E$2:E$201,E182)>1,0,1) -> 1 | X182: =IF(COUNTIF(G$2:G$201,G182)>1,0,1) -> 1 | Y182: =IF(E182="",0,1) -> 1 | Z182: =IF(F182="",0,1) -> 1 | AA182: =IF(G182="",0,1) -> 1 | AB182: =IF(H182="",0,1) -> 1 | AC182: =IF(I182="",0,1) -> 1 | AD182: =IF(K182="",0,1) -> 1 | AE182: =IF(L182="",0,1) -> 1 | AF182: =IF(M182="",0,1) -> 1 | AG182: =IF(N182="",0,1) -> 1 | AH182: =IF(O182="",0,1) -> 1 | AI182: =IF(P182="",0,1) -> 1 | AJ182: =IF(Q182="",0,1) -> 1 | AK182: =IF(R182="",0,1) -> 1 | ... AO182: =IF(V182="",0,1) -> 1 | AP182: =IF(AND(LEFT(E182,2)="AF",LEN(E182)=6),1,0) -> 1 | AQ182: =IF(OR(F182="CC",F182="CE",F182="TI",F182="PAS"),1,0) -> 1 | AR182: =IF(AND(ISNUMBER(G182),COUNTIF($G:$G,G182)=1),1,0) -> 1 | AS182: {=IF(AND(H182<>"",SUMPRODUCT(--ISNUMBER(FIND({0;1;2;3;4;5;6;7;8;9},H182)))=0),1,0)} -> 1 | AT182: {=IF(AND(I182<>"",SUMPRODUCT(--ISNUMBER(FIND({0;1;2;3;4;5;6;7;8;9},I182)))=0),1,0)} -> 1 | AU182: {=IF(AND(J182<>"",SUMPRODUCT(--ISNUMBER(FIND({0;1;2;3;4;5;6;7;8;9},J182)))=0),1,0)} -> 1 | AV182: =IF(OR(ISBLANK(K182),K182=""),1,IF(ISTEXT(K182),1,0)) -> 1 | AW182: =IF(AND(ISNUMBER(L182),L182<=TODAY()),1,0) -> 1 | AX182: =IF(AND(ISNUMBER(SEARCH("@",M182)),ISNUMBER(SEARCH(".",M182,SEARCH("@",M182)+2)),NOT(ISNUMBER(SEARCH(" ",M182)))),1,0) -> 1 | AY182: =IF(AND(ISNUMBER(N182),LEN(N182)=10),1,0) -> 1 | AZ182: =IF(LEN(TRIM(O182))>=10,1,0) -> 1 | BA182: =IF(OR(ISBLANK(O182),O182=""),1,IF(ISTEXT(O182),1,0)) -> 1 | BB182: =IF(OR(ISBLANK(P182),P182=""),1,IF(ISTEXT(P182),1,0)) -> 1 | BC182: =IF(AND(ISNUMBER(R182),R182<=TODAY()),1,0) -> 1 | BD182: =IF(OR(ISBLANK(S182),S182=""),1,IF(ISTEXT(S182),1,0)) -> 1 | BE182: =IF(OR(ISBLANK(T182),T182=""),1,IF(ISTEXT(T182),1,0)) -> 1 | BF182: =IF(AND(ISNUMBER(U182),U182>0),1,0) -> 1 | BG182: =IF(AND(ISNUMBER(V182),V182<=TODAY()),1,0) -> 1
A183: =IF(AND(W183=1,X183=1),1,0) -> 1 | B183: =IF(AND(Y183=1,Z183=1,AA183=1,AB183=1,AC183=1,AD183=1,AE183=1,AF183=1,AG183=1,AH183=1,AI183=1,AJ183=1,AK183=1,AL183=1,AM183=1,AN183=1,AO183=1),1,0) -> 1 | C183: =IF(AND(AP183=1,AQ183=1,AR183=1,AS183=1,AT183=1,AU183=1,AV183=1,AW183=1,AX183=1,AY183=1,AZ183=1,BA183=1,BB183=1,BC183=1,BD183=1,BE183=1,BF183=1,BG183=1),1,0) -> 1 | D183: =IF(SUM(A183:C183)<3,1,0) -> 0 | E183: AF0182 | F183: CC | G183: 1000000182 | H183: Sergio | I183: Munoz | J183: Gomez | K183: M | L183: 37925 | M183: sergio.munoz182@email.com | N183: 3580031464 | O183: Calle 111 #95-55 | P183: Medellín | Q183: Antioquia | R183: 45144 | S183: Suspendido | T183: Call Center | U183: 95000 | V183: 45308 | W183: =IF(COUNTIF(E$2:E$201,E183)>1,0,1) -> 1 | X183: =IF(COUNTIF(G$2:G$201,G183)>1,0,1) -> 1 | Y183: =IF(E183="",0,1) -> 1 | Z183: =IF(F183="",0,1) -> 1 | AA183: =IF(G183="",0,1) -> 1 | AB183: =IF(H183="",0,1) -> 1 | AC183: =IF(I183="",0,1) -> 1 | AD183: =IF(K183="",0,1) -> 1 | AE183: =IF(L183="",0,1) -> 1 | AF183: =IF(M183="",0,1) -> 1 | AG183: =IF(N183="",0,1) -> 1 | AH183: =IF(O183="",0,1) -> 1 | AI183: =IF(P183="",0,1) -> 1 | AJ183: =IF(Q183="",0,1) -> 1 | AK183: =IF(R183="",0,1) -> 1 | ... AO183: =IF(V183="",0,1) -> 1 | AP183: =IF(AND(LEFT(E183,2)="AF",LEN(E183)=6),1,0) -> 1 | AQ183: =IF(OR(F183="CC",F183="CE",F183="TI",F183="PAS"),1,0) -> 1 | AR183: =IF(AND(ISNUMBER(G183),COUNTIF($G:$G,G183)=1),1,0) -> 1 | AS183: {=IF(AND(H183<>"",SUMPRODUCT(--ISNUMBER(FIND({0;1;2;3;4;5;6;7;8;9},H183)))=0),1,0)} -> 1 | AT183: {=IF(AND(I183<>"",SUMPRODUCT(--ISNUMBER(FIND({0;1;2;3;4;5;6;7;8;9},I183)))=0),1,0)} -> 1 | AU183: {=IF(AND(J183<>"",SUMPRODUCT(--ISNUMBER(FIND({0;1;2;3;4;5;6;7;8;9},J183)))=0),1,0)} -> 1 | AV183: =IF(OR(ISBLANK(K183),K183=""),1,IF(ISTEXT(K183),1,0)) -> 1 | AW183: =IF(AND(ISNUMBER(L183),L183<=TODAY()),1,0) -> 1 | AX183: =IF(AND(ISNUMBER(SEARCH("@",M183)),ISNUMBER(SEARCH(".",M183,SEARCH("@",M183)+2)),NOT(ISNUMBER(SEARCH(" ",M183)))),1,0) -> 1 | AY183: =IF(AND(ISNUMBER(N183),LEN(N183)=10),1,0) -> 1 | AZ183: =IF(LEN(TRIM(O183))>=10,1,0) -> 1 | BA183: =IF(OR(ISBLANK(O183),O183=""),1,IF(ISTEXT(O183),1,0)) -> 1 | BB183: =IF(OR(ISBLANK(P183),P183=""),1,IF(ISTEXT(P183),1,0)) -> 1 | BC183: =IF(AND(ISNUMBER(R183),R183<=TODAY()),1,0) -> 1 | BD183: =IF(OR(ISBLANK(S183),S183=""),1,IF(ISTEXT(S183),1,0)) -> 1 | BE183: =IF(OR(ISBLANK(T183),T183=""),1,IF(ISTEXT(T183),1,0)) -> 1 | BF183: =IF(AND(ISNUMBER(U183),U183>0),1,0) -> 1 | BG183: =IF(AND(ISNUMBER(V183),V183<=TODAY()),1,0) -> 1
A184: =IF(AND(W184=1,X184=1),1,0) -> 1 | B184: =IF(AND(Y184=1,Z184=1,AA184=1,AB184=1,AC184=1,AD184=1,AE184=1,AF184=1,AG184=1,AH184=1,AI184=1,AJ184=1,AK184=1,AL184=1,AM184=1,AN184=1,AO184=1),1,0) -> 1 | C184: =IF(AND(AP184=1,AQ184=1,AR184=1,AS184=1,AT184=1,AU184=1,AV184=1,AW184=1,AX184=1,AY184=1,AZ184=1,BA184=1,BB184=1,BC184=1,BD184=1,BE184=1,BF184=1,BG184=1),1,0) -> 1 | D184: =IF(SUM(A184:C184)<3,1,0) -> 0 | E184: AF0183 | F184: TI | G184: 1000000183 | H184: Camila | I184: Lopez | J184: Diaz | K184: F | L184: 32014 | M184: camila.lopez183@email.com | N184: 3375811841 | O184: Calle 97 #90-53 | P184: Envigado | Q184: Antioquia | R184: 44937 | S184: Suspendido | T184: Call Center | U184: 90000 | V184: 45147 | W184: =IF(COUNTIF(E$2:E$201,E184)>1,0,1) -> 1 | X184: =IF(COUNTIF(G$2:G$201,G184)>1,0,1) -> 1 | Y184: =IF(E184="",0,1) -> 1 | Z184: =IF(F184="",0,1) -> 1 | AA184: =IF(G184="",0,1) -> 1 | AB184: =IF(H184="",0,1) -> 1 | AC184: =IF(I184="",0,1) -> 1 | AD184: =IF(K184="",0,1) -> 1 | AE184: =IF(L184="",0,1) -> 1 | AF184: =IF(M184="",0,1) -> 1 | AG184: =IF(N184="",0,1) -> 1 | AH184: =IF(O184="",0,1) -> 1 | AI184: =IF(P184="",0,1) -> 1 | AJ184: =IF(Q184="",0,1) -> 1 | AK184: =IF(R184="",0,1) -> 1 | ... AO184: =IF(V184="",0,1) -> 1 | AP184: =IF(AND(LEFT(E184,2)="AF",LEN(E184)=6),1,0) -> 1 | AQ184: =IF(OR(F184="CC",F184="CE",F184="TI",F184="PAS"),1,0) -> 1 | AR184: =IF(AND(ISNUMBER(G184),COUNTIF($G:$G,G184)=1),1,0) -> 1 | AS184: {=IF(AND(H184<>"",SUMPRODUCT(--ISNUMBER(FIND({0;1;2;3;4;5;6;7;8;9},H184)))=0),1,0)} -> 1 | AT184: {=IF(AND(I184<>"",SUMPRODUCT(--ISNUMBER(FIND({0;1;2;3;4;5;6;7;8;9},I184)))=0),1,0)} -> 1 | AU184: {=IF(AND(J184<>"",SUMPRODUCT(--ISNUMBER(FIND({0;1;2;3;4;5;6;7;8;9},J184)))=0),1,0)} -> 1 | AV184: =IF(OR(ISBLANK(K184),K184=""),1,IF(ISTEXT(K184),1,0)) -> 1 | AW184: =IF(AND(ISNUMBER(L184),L184<=TODAY()),1,0) -> 1 | AX184: =IF(AND(ISNUMBER(SEARCH("@",M184)),ISNUMBER(SEARCH(".",M184,SEARCH("@",M184)+2)),NOT(ISNUMBER(SEARCH(" ",M184)))),1,0) -> 1 | AY184: =IF(AND(ISNUMBER(N184),LEN(N184)=10),1,0) -> 1 | AZ184: =IF(LEN(TRIM(O184))>=10,1,0) -> 1 | BA184: =IF(OR(ISBLANK(O184),O184=""),1,IF(ISTEXT(O184),1,0)) -> 1 | BB184: =IF(OR(ISBLANK(P184),P184=""),1,IF(ISTEXT(P184),1,0)) -> 1 | BC184: =IF(AND(ISNUMBER(R184),R184<=TODAY()),1,0) -> 1 | BD184: =IF(OR(ISBLANK(S184),S184=""),1,IF(ISTEXT(S184),1,0)) -> 1 | BE184: =IF(OR(ISBLANK(T184),T184=""),1,IF(ISTEXT(T184),1,0)) -> 1 | BF184: =IF(AND(ISNUMBER(U184),U184>0),1,0) -> 1 | BG184: =IF(AND(ISNUMBER(V184),V184<=TODAY()),1,0) -> 1
A185: =IF(AND(W185=1,X185=1),1,0) -> 1 | B185: =IF(AND(Y185=1,Z185=1,AA185=1,AB185=1,AC185=1,AD185=1,AE185=1,AF185=1,AG185=1,AH185=1,AI185=1,AJ185=1,AK185=1,AL185=1,AM185=1,AN185=1,AO185=1),1,0) -> 1 | C185: =IF(AND(AP185=1,AQ185=1,AR185=1,AS185=1,AT185=1,AU185=1,AV185=1,AW185=1,AX185=1,AY185=1,AZ185=1,BA185=1,BB185=1,BC185=1,BD185=1,BE185=1,BF185=1,BG185=1),1,0) -> 1 | D185: =IF(SUM(A185:C185)<3,1,0) -> 0 | E185: AF0184 | F185: TI | G185: 1000000184 | H185: Diana | I185: Herrera | J185: Restrepo | K185: F | L185: 36590 | M185: diana.herrera184@email.com | N185: 3262199266 | O185: Calle 13 #70-81 | P185: Envigado | Q185: Antioquia | R185: 44989 | S185: Suspendido | T185: Call Center | U185: 95000 | V185: 45007 | W185: =IF(COUNTIF(E$2:E$201,E185)>1,0,1) -> 1 | X185: =IF(COUNTIF(G$2:G$201,G185)>1,0,1) -> 1 | Y185: =IF(E185="",0,1) -> 1 | Z185: =IF(F185="",0,1) -> 1 | AA185: =IF(G185="",0,1) -> 1 | AB185: =IF(H185="",0,1) -> 1 | AC185: =IF(I185="",0,1) -> 1 | AD185: =IF(K185="",0,1) -> 1 | AE185: =IF(L185="",0,1) -> 1 | AF185: =IF(M185="",0,1) -> 1 | AG185: =IF(N185="",0,1) -> 1 | AH185: =IF(O185="",0,1) -> 1 | AI185: =IF(P185="",0,1) -> 1 | AJ185: =IF(Q185="",0,1) -> 1 | AK185: =IF(R185="",0,1) -> 1 | ... AO185: =IF(V185="",0,1) -> 1 | AP185: =IF(AND(LEFT(E185,2)="AF",LEN(E185)=6),1,0) -> 1 | AQ185: =IF(OR(F185="CC",F185="CE",F185="TI",F185="PAS"),1,0) -> 1 | AR185: =IF(AND(ISNUMBER(G185),COUNTIF($G:$G,G185)=1),1,0) -> 1 | AS185: {=IF(AND(H185<>"",SUMPRODUCT(--ISNUMBER(FIND({0;1;2;3;4;5;6;7;8;9},H185)))=0),1,0)} -> 1 | AT185: {=IF(AND(I185<>"",SUMPRODUCT(--ISNUMBER(FIND({0;1;2;3;4;5;6;7;8;9},I185)))=0),1,0)} -> 1 | AU185: {=IF(AND(J185<>"",SUMPRODUCT(--ISNUMBER(FIND({0;1;2;3;4;5;6;7;8;9},J185)))=0),1,0)} -> 1 | AV185: =IF(OR(ISBLANK(K185),K185=""),1,IF(ISTEXT(K185),1,0)) -> 1 | AW185: =IF(AND(ISNUMBER(L185),L185<=TODAY()),1,0) -> 1 | AX185: =IF(AND(ISNUMBER(SEARCH("@",M185)),ISNUMBER(SEARCH(".",M185,SEARCH("@",M185)+2)),NOT(ISNUMBER(SEARCH(" ",M185)))),1,0) -> 1 | AY185: =IF(AND(ISNUMBER(N185),LEN(N185)=10),1,0) -> 1 | AZ185: =IF(LEN(TRIM(O185))>=10,1,0) -> 1 | BA185: =IF(OR(ISBLANK(O185),O185=""),1,IF(ISTEXT(O185),1,0)) -> 1 | BB185: =IF(OR(ISBLANK(P185),P185=""),1,IF(ISTEXT(P185),1,0)) -> 1 | BC185: =IF(AND(ISNUMBER(R185),R185<=TODAY()),1,0) -> 1 | BD185: =IF(OR(ISBLANK(S185),S185=""),1,IF(ISTEXT(S185),1,0)) -> 1 | BE185: =IF(OR(ISBLANK(T185),T185=""),1,IF(ISTEXT(T185),1,0)) -> 1 | BF185: =IF(AND(ISNUMBER(U185),U185>0),1,0) -> 1 | BG185: =IF(AND(ISNUMBER(V185),V185<=TODAY()),1,0) -> 1
A186: =IF(AND(W186=1,X186=1),1,0) -> 1 | B186: =IF(AND(Y186=1,Z186=1,AA186=1,AB186=1,AC186=1,AD186=1,AE186=1,AF186=1,AG186=1,AH186=1,AI186=1,AJ186=1,AK186=1,AL186=1,AM186=1,AN186=1,AO186=1),1,0) -> 1 | C186: =IF(AND(AP186=1,AQ186=1,AR186=1,AS186=1,AT186=1,AU186=1,AV186=1,AW186=1,AX186=1,AY186=1,AZ186=1,BA186=1,BB186=1,BC186=1,BD186=1,BE186=1,BF186=1,BG186=1),1,0) -> 1 | D186: =IF(SUM(A186:C186)<3,1,0) -> 0 | E186: AF0185 | F186: TI | G186: 1000000185 | H186: Nicolas | I186: Leon | J186: Rodriguez | K186: M | L186: 31256 | M186: nicolas.leon185@email.com | N186: 3858591277 | O186: Calle 74 #34-87 | P186: Cali | Q186: Valle del Cauca | R186: 45135 | S186: Activo | T186: Presencial | U186: 90000 | V186: 45392 | W186: =IF(COUNTIF(E$2:E$201,E186)>1,0,1) -> 1 | X186: =IF(COUNTIF(G$2:G$201,G186)>1,0,1) -> 1 | Y186: =IF(E186="",0,1) -> 1 | Z186: =IF(F186="",0,1) -> 1 | AA186: =IF(G186="",0,1) -> 1 | AB186: =IF(H186="",0,1) -> 1 | AC186: =IF(I186="",0,1) -> 1 | AD186: =IF(K186="",0,1) -> 1 | AE186: =IF(L186="",0,1) -> 1 | AF186: =IF(M186="",0,1) -> 1 | AG186: =IF(N186="",0,1) -> 1 | AH186: =IF(O186="",0,1) -> 1 | AI186: =IF(P186="",0,1) -> 1 | AJ186: =IF(Q186="",0,1) -> 1 | AK186: =IF(R186="",0,1) -> 1 | ... AO186: =IF(V186="",0,1) -> 1 | AP186: =IF(AND(LEFT(E186,2)="AF",LEN(E186)=6),1,0) -> 1 | AQ186: =IF(OR(F186="CC",F186="CE",F186="TI",F186="PAS"),1,0) -> 1 | AR186: =IF(AND(ISNUMBER(G186),COUNTIF($G:$G,G186)=1),1,0) -> 1 | AS186: {=IF(AND(H186<>"",SUMPRODUCT(--ISNUMBER(FIND({0;1;2;3;4;5;6;7;8;9},H186)))=0),1,0)} -> 1 | AT186: {=IF(AND(I186<>"",SUMPRODUCT(--ISNUMBER(FIND({0;1;2;3;4;5;6;7;8;9},I186)))=0),1,0)} -> 1 | AU186: {=IF(AND(J186<>"",SUMPRODUCT(--ISNUMBER(FIND({0;1;2;3;4;5;6;7;8;9},J186)))=0),1,0)} -> 1 | AV186: =IF(OR(ISBLANK(K186),K186=""),1,IF(ISTEXT(K186),1,0)) -> 1 | AW186: =IF(AND(ISNUMBER(L186),L186<=TODAY()),1,0) -> 1 | AX186: =IF(AND(ISNUMBER(SEARCH("@",M186)),ISNUMBER(SEARCH(".",M186,SEARCH("@",M186)+2)),NOT(ISNUMBER(SEARCH(" ",M186)))),1,0) -> 1 | AY186: =IF(AND(ISNUMBER(N186),LEN(N186)=10),1,0) -> 1 | AZ186: =IF(LEN(TRIM(O186))>=10,1,0) -> 1 | BA186: =IF(OR(ISBLANK(O186),O186=""),1,IF(ISTEXT(O186),1,0)) -> 1 | BB186: =IF(OR(ISBLANK(P186),P186=""),1,IF(ISTEXT(P186),1,0)) -> 1 | BC186: =IF(AND(ISNUMBER(R186),R186<=TODAY()),1,0) -> 1 | BD186: =IF(OR(ISBLANK(S186),S186=""),1,IF(ISTEXT(S186),1,0)) -> 1 | BE186: =IF(OR(ISBLANK(T186),T186=""),1,IF(ISTEXT(T186),1,0)) -> 1 | BF186: =IF(AND(ISNUMBER(U186),U186>0),1,0) -> 1 | BG186: =IF(AND(ISNUMBER(V186),V186<=TODAY()),1,0) -> 1
A187: =IF(AND(W187=1,X187=1),1,0) -> 1 | B187: =IF(AND(Y187=1,Z187=1,AA187=1,AB187=1,AC187=1,AD187=1,AE187=1,AF187=1,AG187=1,AH187=1,AI187=1,AJ187=1,AK187=1,AL187=1,AM187=1,AN187=1,AO187=1),1,0) -> 1 | C187: =IF(AND(AP187=1,AQ187=1,AR187=1,AS187=1,AT187=1,AU187=1,AV187=1,AW187=1,AX187=1,AY187=1,AZ187=1,BA187=1,BB187=1,BC187=1,BD187=1,BE187=1,BF187=1,BG187=1),1,0) -> 1 | D187: =IF(SUM(A187:C187)<3,1,0) -> 0 | E187: AF0186 | F187: TI | G187: 1000000186 | H187: Carlos | I187: Castro | J187: Valencia | K187: M | L187: 31588 | M187: carlos.castro186@email.com | N187: 3863463967 | O187: Calle 61 #44-97 | P187: Envigado | Q187: Antioquia | R187: 44643 | S187: Retirado | T187: Presencial | U187: 95000 | V187: 44646 | W187: =IF(COUNTIF(E$2:E$201,E187)>1,0,1) -> 1 | X187: =IF(COUNTIF(G$2:G$201,G187)>1,0,1) -> 1 | Y187: =IF(E187="",0,1) -> 1 | Z187: =IF(F187="",0,1) -> 1 | AA187: =IF(G187="",0,1) -> 1 | AB187: =IF(H187="",0,1) -> 1 | AC187: =IF(I187="",0,1) -> 1 | AD187: =IF(K187="",0,1) -> 1 | AE187: =IF(L187="",0,1) -> 1 | AF187: =IF(M187="",0,1) -> 1 | AG187: =IF(N187="",0,1) -> 1 | AH187: =IF(O187="",0,1) -> 1 | AI187: =IF(P187="",0,1) -> 1 | AJ187: =IF(Q187="",0,1) -> 1 | AK187: =IF(R187="",0,1) -> 1 | ... AO187: =IF(V187="",0,1) -> 1 | AP187: =IF(AND(LEFT(E187,2)="AF",LEN(E187)=6),1,0) -> 1 | AQ187: =IF(OR(F187="CC",F187="CE",F187="TI",F187="PAS"),1,0) -> 1 | AR187: =IF(AND(ISNUMBER(G187),COUNTIF($G:$G,G187)=1),1,0) -> 1 | AS187: {=IF(AND(H187<>"",SUMPRODUCT(--ISNUMBER(FIND({0;1;2;3;4;5;6;7;8;9},H187)))=0),1,0)} -> 1 | AT187: {=IF(AND(I187<>"",SUMPRODUCT(--ISNUMBER(FIND({0;1;2;3;4;5;6;7;8;9},I187)))=0),1,0)} -> 1 | AU187: {=IF(AND(J187<>"",SUMPRODUCT(--ISNUMBER(FIND({0;1;2;3;4;5;6;7;8;9},J187)))=0),1,0)} -> 1 | AV187: =IF(OR(ISBLANK(K187),K187=""),1,IF(ISTEXT(K187),1,0)) -> 1 | AW187: =IF(AND(ISNUMBER(L187),L187<=TODAY()),1,0) -> 1 | AX187: =IF(AND(ISNUMBER(SEARCH("@",M187)),ISNUMBER(SEARCH(".",M187,SEARCH("@",M187)+2)),NOT(ISNUMBER(SEARCH(" ",M187)))),1,0) -> 1 | AY187: =IF(AND(ISNUMBER(N187),LEN(N187)=10),1,0) -> 1 | AZ187: =IF(LEN(TRIM(O187))>=10,1,0) -> 1 | BA187: =IF(OR(ISBLANK(O187),O187=""),1,IF(ISTEXT(O187),1,0)) -> 1 | BB187: =IF(OR(ISBLANK(P187),P187=""),1,IF(ISTEXT(P187),1,0)) -> 1 | BC187: =IF(AND(ISNUMBER(R187),R187<=TODAY()),1,0) -> 1 | BD187: =IF(OR(ISBLANK(S187),S187=""),1,IF(ISTEXT(S187),1,0)) -> 1 | BE187: =IF(OR(ISBLANK(T187),T187=""),1,IF(ISTEXT(T187),1,0)) -> 1 | BF187: =IF(AND(ISNUMBER(U187),U187>0),1,0) -> 1 | BG187: =IF(AND(ISNUMBER(V187),V187<=TODAY()),1,0) -> 1
A188: =IF(AND(W188=1,X188=1),1,0) -> 1 | B188: =IF(AND(Y188=1,Z188=1,AA188=1,AB188=1,AC188=1,AD188=1,AE188=1,AF188=1,AG188=1,AH188=1,AI188=1,AJ188=1,AK188=1,AL188=1,AM188=1,AN188=1,AO188=1),1,0) -> 1 | C188: =IF(AND(AP188=1,AQ188=1,AR188=1,AS188=1,AT188=1,AU188=1,AV188=1,AW188=1,AX188=1,AY188=1,AZ188=1,BA188=1,BB188=1,BC188=1,BD188=1,BE188=1,BF188=1,BG188=1),1,0) -> 0 | D188: =IF(SUM(A188:C188)<3,1,0) -> 1 | E188: AF0187 | F188: TI | G188: 1000000187 | H188: Andres | I188: Moreno | J188: Castro | K188: M | L188: 34258 | M188: andres.moreno187@email.com | N188: 3843144096 | O188: Calle 25 #29-76 | P188: Bucaramanga | Q188: Santander | R188: 46060 | S188: Suspendido | T188: Web | U188: 90000 | V188: 46199 | W188: =IF(COUNTIF(E$2:E$201,E188)>1,0,1) -> 1 | X188: =IF(COUNTIF(G$2:G$201,G188)>1,0,1) -> 1 | Y188: =IF(E188="",0,1) -> 1 | Z188: =IF(F188="",0,1) -> 1 | AA188: =IF(G188="",0,1) -> 1 | AB188: =IF(H188="",0,1) -> 1 | AC188: =IF(I188="",0,1) -> 1 | AD188: =IF(K188="",0,1) -> 1 | AE188: =IF(L188="",0,1) -> 1 | AF188: =IF(M188="",0,1) -> 1 | AG188: =IF(N188="",0,1) -> 1 | AH188: =IF(O188="",0,1) -> 1 | AI188: =IF(P188="",0,1) -> 1 | AJ188: =IF(Q188="",0,1) -> 1 | AK188: =IF(R188="",0,1) -> 1 | ... AO188: =IF(V188="",0,1) -> 1 | AP188: =IF(AND(LEFT(E188,2)="AF",LEN(E188)=6),1,0) -> 1 | AQ188: =IF(OR(F188="CC",F188="CE",F188="TI",F188="PAS"),1,0) -> 1 | AR188: =IF(AND(ISNUMBER(G188),COUNTIF($G:$G,G188)=1),1,0) -> 1 | AS188: {=IF(AND(H188<>"",SUMPRODUCT(--ISNUMBER(FIND({0;1;2;3;4;5;6;7;8;9},H188)))=0),1,0)} -> 1 | AT188: {=IF(AND(I188<>"",SUMPRODUCT(--ISNUMBER(FIND({0;1;2;3;4;5;6;7;8;9},I188)))=0),1,0)} -> 1 | AU188: {=IF(AND(J188<>"",SUMPRODUCT(--ISNUMBER(FIND({0;1;2;3;4;5;6;7;8;9},J188)))=0),1,0)} -> 1 | AV188: =IF(OR(ISBLANK(K188),K188=""),1,IF(ISTEXT(K188),1,0)) -> 1 | AW188: =IF(AND(ISNUMBER(L188),L188<=TODAY()),1,0) -> 1 | AX188: =IF(AND(ISNUMBER(SEARCH("@",M188)),ISNUMBER(SEARCH(".",M188,SEARCH("@",M188)+2)),NOT(ISNUMBER(SEARCH(" ",M188)))),1,0) -> 1 | AY188: =IF(AND(ISNUMBER(N188),LEN(N188)=10),1,0) -> 1 | AZ188: =IF(LEN(TRIM(O188))>=10,1,0) -> 1 | BA188: =IF(OR(ISBLANK(O188),O188=""),1,IF(ISTEXT(O188),1,0)) -> 1 | BB188: =IF(OR(ISBLANK(P188),P188=""),1,IF(ISTEXT(P188),1,0)) -> 1 | BC188: =IF(AND(ISNUMBER(R188),R188<=TODAY()),1,0) -> 1 | BD188: =IF(OR(ISBLANK(S188),S188=""),1,IF(ISTEXT(S188),1,0)) -> 1 | BE188: =IF(OR(ISBLANK(T188),T188=""),1,IF(ISTEXT(T188),1,0)) -> 1 | BF188: =IF(AND(ISNUMBER(U188),U188>0),1,0) -> 1 | BG188: =IF(AND(ISNUMBER(V188),V188<=TODAY()),1,0) -> 0
... A201: =IF(AND(W201=1,X201=1),1,0) -> 1 | B201: =IF(AND(Y201=1,Z201=1,AA201=1,AB201=1,AC201=1,AD201=1,AE201=1,AF201=1,AG201=1,AH201=1,AI201=1,AJ201=1,AK201=1,AL201=1,AM201=1,AN201=1,AO201=1),1,0) -> 1 | C201: =IF(AND(AP201=1,AQ201=1,AR201=1,AS201=1,AT201=1,AU201=1,AV201=1,AW201=1,AX201=1,AY201=1,AZ201=1,BA201=1,BB201=1,BC201=1,BD201=1,BE201=1,BF201=1,BG201=1),1,0) -> 0 | D201: =IF(SUM(A201:C201)<3,1,0) -> 1 | E201: AF0200 | F201: TI | G201: 1000000200 | H201: Natalia | I201: Martinez | J201: Sanchez | K201: F | L201: 25119 | M201: natalia.martinez200@email.com | N201: 12345 | O201: Calle 70 #21-18 | P201: Manizales | Q201: Caldas | R201: 45334 | S201: Activo | T201: Web | U201: 85000 | V201: 45342 | W201: =IF(COUNTIF(E$2:E$201,E201)>1,0,1) -> 1 | X201: =IF(COUNTIF(G$2:G$201,G201)>1,0,1) -> 1 | Y201: =IF(E201="",0,1) -> 1 | Z201: =IF(F201="",0,1) -> 1 | AA201: =IF(G201="",0,1) -> 1 | AB201: =IF(H201="",0,1) -> 1 | AC201: =IF(I201="",0,1) -> 1 | AD201: =IF(K201="",0,1) -> 1 | AE201: =IF(L201="",0,1) -> 1 | AF201: =IF(M201="",0,1) -> 1 | AG201: =IF(N201="",0,1) -> 1 | AH201: =IF(O201="",0,1) -> 1 | AI201: =IF(P201="",0,1) -> 1 | AJ201: =IF(Q201="",0,1) -> 1 | AK201: =IF(R201="",0,1) -> 1 | ... AO201: =IF(V201="",0,1) -> 1 | AP201: =IF(AND(LEFT(E201,2)="AF",LEN(E201)=6),1,0) -> 1 | AQ201: =IF(OR(F201="CC",F201="CE",F201="TI",F201="PAS"),1,0) -> 1 | AR201: =IF(AND(ISNUMBER(G201),COUNTIF($G:$G,G201)=1),1,0) -> 1 | AS201: {=IF(AND(H201<>"",SUMPRODUCT(--ISNUMBER(FIND({0;1;2;3;4;5;6;7;8;9},H201)))=0),1,0)} -> 1 | AT201: {=IF(AND(I201<>"",SUMPRODUCT(--ISNUMBER(FIND({0;1;2;3;4;5;6;7;8;9},I201)))=0),1,0)} -> 1 | AU201: {=IF(AND(J201<>"",SUMPRODUCT(--ISNUMBER(FIND({0;1;2;3;4;5;6;7;8;9},J201)))=0),1,0)} -> 1 | AV201: =IF(OR(ISBLANK(K201),K201=""),1,IF(ISTEXT(K201),1,0)) -> 1 | AW201: =IF(AND(ISNUMBER(L201),L201<=TODAY()),1,0) -> 1 | AX201: =IF(AND(ISNUMBER(SEARCH("@",M201)),ISNUMBER(SEARCH(".",M201,SEARCH("@",M201)+2)),NOT(ISNUMBER(SEARCH(" ",M201)))),1,0) -> 1 | AY201: =IF(AND(ISNUMBER(N201),LEN(N201)=10),1,0) -> 0 | AZ201: =IF(LEN(TRIM(O201))>=10,1,0) -> 1 | BA201: =IF(OR(ISBLANK(O201),O201=""),1,IF(ISTEXT(O201),1,0)) -> 1 | BB201: =IF(OR(ISBLANK(P201),P201=""),1,IF(ISTEXT(P201),1,0)) -> 1 | BC201: =IF(AND(ISNUMBER(R201),R201<=TODAY()),1,0) -> 1 | BD201: =IF(OR(ISBLANK(S201),S201=""),1,IF(ISTEXT(S201),1,0)) -> 1 | BE201: =IF(OR(ISBLANK(T201),T201=""),1,IF(ISTEXT(T201),1,0)) -> 1 | BF201: =IF(AND(ISNUMBER(U201),U201>0),1,0) -> 1 | BG201: =IF(AND(ISNUMBER(V201),V201<=TODAY()),1,0) -> 1

Sheet F0005(Clasificacion cuentas)
A1: Cumple Unicidad (1=Si, 0=No) | B1: Cumple Completitud (1=Si, 0=No) | C1: Cumple Validez (1=Si, 0=No) | D1: Inconsistencia Detectada (1=Si, 0=No) | E1: Códigos | F1: Descripción | G1: Descripción 2 | H1: Unicidad Códigos | I1: Unicidad Descripción | J1: Completitud Códigos | K1: Completitud Descripción | L1: Validez Códigos
A2: 1 | B2: 1 | C2: 1 | D2: 0 | E2: ARR | F2: Arrendamientos | G2: RAGASA | H2: 1 | I2: 1 | J2: 1 | K2: 1 | L2: 1
A3: 1 | B3: 1 | C3: 1 | D3: 0 | E3: BAL | F3: Balance | G3: RAGASA | H3: 1 | I3: 1 | J3: 1 | K3: 1 | L3: 1
A4: 1 | B4: 1 | C4: 1 | D4: 0 | E4: CMP | F4: Gastos s/Compras | G4: RAGASA | H4: 1 | I4: 1 | J4: 1 | K4: 1 | L4: 1
A5: 1 | B5: 1 | C5: 1 | D5: 0 | E5: COM | F5: Comisiones | G5: RAGASA | H5: 1 | I5: 1 | J5: 1 | K5: 1 | L5: 1
A6: 1 | B6: 1 | C6: 1 | D6: 0 | E6: COR | F6: Cuentas de orden | G6: RAGASA | H6: 1 | I6: 1 | J6: 1 | K6: 1 | L6: 1
A7: 1 | B7: 1 | C7: 1 | D7: 0 | E7: CST | F7: Costos | G7: RAGASA | H7: 1 | I7: 1 | J7: 1 | K7: 1 | L7: 1
A8: 1 | B8: 1 | C8: 1 | D8: 0 | E8: CTO | F8: Costo de ventas | G8: RAGASA | H8: 1 | I8: 1 | J8: 1 | K8: 1 | L8: 1
A9: 1 | B9: 1 | C9: 1 | D9: 0 | E9: DEP | F9: Depreciación | G9: RAGASA | H9: 1 | I9: 1 | J9: 1 | K9: 1 | L9: 1
A10: 1 | B10: 1 | C10: 1 | D10: 0 | E10: ENE | F10: Energeticos | G10: RAGASA | H10: 1 | I10: 1 | J10: 1 | K10: 1 | L10: 1
A11: 1 | B11: 1 | C11: 1 | D11: 0 | E11: FLC | F11: Fletes de Compras | G11: RAGASA | H11: 1 | I11: 1 | J11: 1 | K11: 1 | L11: 1
A12: 1 | B12: 1 | C12: 1 | D12: 0 | E12: FLV | F12: Fletes de Ventas | G12: RAGASA | H12: 1 | I12: 1 | J12: 1 | K12: 1 | L12: 1
A13: 1 | B13: 1 | C13: 1 | D13: 0 | E13: GTC | F13: Gastos por Comunicaciones | G13: RAGASA | H13: 1 | I13: 1 | J13: 1 | K13: 1 | L13: 1
... A17: 1 | B17: 1 | C17: 1 | D17: 0 | E17: HON | F17: Honorarios | G17: RAGASA | H17: 1 | I17: 1 | J17: 1 | K17: 1 | L17: 1
A18: 1 | B18: 1 | C18: 1 | D18: 0 | E18: INC | F18: Incobrables | G18: RAGASA | H18: 1 | I18: 1 | J18: 1 | K18: 1 | L18: 1 | P18: 0
A19: 1 | B19: 1 | C19: 1 | D19: 0 | E19: ING | F19: Ingresos | G19: RAGASA | H19: 1 | I19: 1 | J19: 1 | K19: 1 | L19: 1
A20: 1 | B20: 1 | C20: 1 | D20: 0 | E20: IUT | F20: Impuestos a la utilidad | G20: RAGASA | H20: 1 | I20: 1 | J20: 1 | K20: 1 | L20: 1
A21: 1 | B21: 1 | C21: 1 | D21: 0 | E21: LAB | F21: Gastos de Laboratorio | G21: RAGASA | H21: 1 | I21: 1 | J21: 1 | K21: 1 | L21: 1
A22: 1 | B22: 1 | C22: 1 | D22: 0 | E22: MAG | F22: Gastos de Maquila de Ganado | G22: RAGASA | H22: 1 | I22: 1 | J22: 1 | K22: 1 | L22: 1
A23: 1 | B23: 1 | C23: 1 | D23: 0 | E23: MAQ | F23: Gastos de Maquila | G23: RAGASA | H23: 1 | I23: 1 | J23: 1 | K23: 1 | L23: 1
A24: 1 | B24: 1 | C24: 1 | D24: 0 | E24: MGG | F24: Matls. y Gastos para Ganado | G24: RAGASA | H24: 1 | I24: 1 | J24: 1 | K24: 1 | L24: 1
A25: 1 | B25: 1 | C25: 1 | D25: 0 | E25: OCD | F25: Otras Contrib. y Der. | G25: RAGASA | H25: 1 | I25: 1 | J25: 1 | K25: 1 | L25: 1
A26: 1 | B26: 1 | C26: 1 | D26: 0 | E26: OFI | F26: Otros Gastos Oficina | G26: RAGASA | H26: 1 | I26: 1 | J26: 1 | K26: 1 | L26: 1
A27: 1 | B27: 1 | C27: 1 | D27: 0 | E27: OIG | F27: Otros Ingresos y Gastos | G27: RAGASA | H27: 1 | I27: 1 | J27: 1 | K27: 1 | L27: 1
A28: 1 | B28: 1 | C28: 1 | D28: 0 | E28: OPL | F28: Otros Gastos Planta | G28: RAGASA | H28: 1 | I28: 1 | J28: 1 | K28: 1 | L28: 1
A29: 1 | B29: 1 | C29: 1 | D29: 0 | E29: PYP | F29: Publicidad y Propaganda | G29: RAGASA | H29: 1 | I29: 1 | J29: 1 | K29: 1 | L29: 1
A30: 1 | B30: 1 | C30: 1 | D30: 0 | E30: REA | F30: Reactivos | G30: RAGASA | H30: 1 | I30: 1 | J30: 1 | K30: 1 | L30: 1
... A35: 1 | B35: 1 | C35: 1 | D35: 0 | E35: SYS | F35: Sueldos,Salar y Prestaciones | G35: RAGASA | H35: 1 | I35: 1 | J35: 1 | K35: 1 | L35: 1
M91: =SUMA()
